Workbook

Sheet MasterSheet_WithPredictive
A1: KEY | B1: Country | C1: Year | D1: Global GDP | E1: Global_GDP_Growth | F1: Global Population | G1: Global_Population_Growth | H1: GDP | I1: GDP_Growth_Rate | J1: Country Population | K1: Country Population_Rate | L1: Global GDP % | M1: Import | N1: Export | O1: Trade Balance | P1: Trade Balance to GDP | Q1: Debt to GDP | R1: Debt_to_GDP_Growth | S1: Debt | T1: Interest | U1: Interest Payment | V1: Interest Payment to GDP | W1: Inflation | X1: PCI | Y1: Adjusted PCI | Z1: HDI | AA1: HDI_Growth | AB1: Ginni | AC1: Ginni_Growth | AD1: Adjusted HDI | AE1: Housing | AF1: Health | AG1: Energy | AH1: Education | AI1: Scio-Economic | AJ1: Heart Value | AK1: Heart Affordibility Value | AL1: Affordbility Ranking | AM1: Heart Score | AN1: Brief Description of HEART Scores | AO1: Brief Description of HEART Scores by Mr. Khurshid | AP1: Assumption
A2: =_xlfn.CONCAT(UPPER(B2),"|",C2) -> INDIA|2019 | B2: India | C2: 2019 | D2: 87700000000000 | F2: 7810000000 | H2: 2840000000000 | J2: 1390000000 | L2: 0.032383124 | M2: 632000000000 | N2: 538000000000 | O2: -94000000000 | P2: -0.033098592 | Q2: 0.75 | S2: 2130000000000 | T2: 0.0625 | U2: 133125000000 | V2: 0.046875 | W2: 0.0373 | X2: 2043.1655 | Y2: 1966.9554 | Z2: 0.651 | AB2: 0.338 | AD2: 0.313 | AE2: 0.06668832 | AF2: 0.011688304 | AG2: 0.036688203 | AH2: 0.032688219 | AI2: 0.14775305 | AJ2: 0.10016258 | AK2: 615.65704 | AL2: D- | AM2: 0.1D- | AN2: =_xlfn.CONCAT(_xlfn.IFS( AJ2>=0.7,"Superb", AJ2>=0.51,"Excellent", AJ2>=0.41,"Good", AJ2>=0.31,"Satisfactory", AJ2>=0.26,"Moderate", AJ2>=0.1,"Weak", AJ2<0.1,"Very Weak" ), " Economic Resilience with ",_xlfn.IFS( AK2<=2500,"Very Weak", AK2<=5000,"Poor", AK2<=10000,"Challenging", AK2<=12500,"Border Line", AK2<=15000,"Improved", AK2<=20000,"Moderate", AK2<=25000,"Satisfactory", AK2<=30000,"Good", AK2<=35000,"Very Good", AK2<=40000,"High", AK2<=50000,"Excellent", AK2<=100000,"Superb", AK2>100000,"Superb" ), " Affordability.") -> Weak Economic Resilience with Very Weak Affordability. | AP2: We will assume the 5 socio economic sector spending will increase by 5% every year, Socio Ecnomic Sectors are Health, Housing, Energy and Education. Based on this assumption we will predict the value of Heart next year
A3: =_xlfn.CONCAT(UPPER(B3),"|",C3) -> INDIA|2020 | B3: India | C3: 2020 | D3: 84750000000000 | E3: -0.0336374 | F3: 7890000000 | G3: 0.010243278 | H3: 2670000000000 | I3: -0.059859155 | J3: 1400000000 | K3: 0.0071942446 | L3: 0.031504425 | M3: 546000000000 | N3: 497000000000 | O3: -49000000000 | P3: -0.01835206 | Q3: 0.884 | R3: 0.17866667 | S3: 2360280000000 | T3: 0.044 | U3: 103852320000 | V3: 0.038896 | W3: 0.0662 | X3: 1907.1429 | Y3: 1780.89 | Z3: 0.652 | AA3: 0.0015360983 | AB3: 0.338 | AC3: 0 | AD3: 0.314 | AE3: 0.068632439 | AF3: 0.013632423 | AG3: 0.038632322 | AH3: 0.034632338 | AI3: 0.15552952 | AJ3: 0.12978589 | AK3: 559.19946 | AL3: D- | AM3: 0.13D- | AN3: =_xlfn.CONCAT(_xlfn.IFS( AJ3>=0.7,"Superb", AJ3>=0.51,"Excellent", AJ3>=0.41,"Good", AJ3>=0.31,"Satisfactory", AJ3>=0.26,"Moderate", AJ3>=0.1,"Weak", AJ3<0.1,"Very Weak" ), " Economic Resilience with ",_xlfn.IFS( AK3<=2500,"Very Weak", AK3<=5000,"Poor", AK3<=10000,"Challenging", AK3<=12500,"Border Line", AK3<=15000,"Improved", AK3<=20000,"Moderate", AK3<=25000,"Satisfactory", AK3<=30000,"Good", AK3<=35000,"Very Good", AK3<=40000,"High", AK3<=50000,"Excellent", AK3<=100000,"Superb", AK3>100000,"Superb" ), " Affordability.") -> Weak Economic Resilience with Very Weak Affordability. | AP3: We will assume the 5 socio economic sector spending will increase by 5% every year, Socio Ecnomic Sectors are Health, Housing, Energy and Education. Based on this assumption we will predict the value of Heart next year
A4: =_xlfn.CONCAT(UPPER(B4),"|",C4) -> INDIA|2021 | B4: India | C4: 2021 | D4: 96140000000000 | E4: 0.13439528 | F4: 7950000000 | G4: 0.0076045627 | H4: 3170000000000 | I4: 0.18726592 | J4: 1410000000 | K4: 0.0071428571 | L4: 0.032972748 | M4: 670000000000 | N4: 612000000000 | O4: -58000000000 | P4: -0.01829653 | Q4: 0.835 | R4: -0.055429864 | S4: 2646950000000 | T4: 0.04 | U4: 105878000000 | V4: 0.0334 | W4: 0.0513 | X4: 2248.227 | Y4: 2132.8929 | Z4: 0.647 | AA4: -0.0076687117 | AB4: 0.328 | AC4: -0.030487805 | AD4: 0.319 | AE4: 0.07067888 | AF4: 0.015678864 | AG4: 0.040678763 | AH4: 0.036678779 | AI4: 0.16371529 | AJ4: 0.1449915 | AK4: 680.39284 | AL4: D- | AM4: 0.14D- | AN4: =_xlfn.CONCAT(_xlfn.IFS( AJ4>=0.7,"Superb", AJ4>=0.51,"Excellent", AJ4>=0.41,"Good", AJ4>=0.31,"Satisfactory", AJ4>=0.26,"Moderate", AJ4>=0.1,"Weak", AJ4<0.1,"Very Weak" ), " Economic Resilience with ",_xlfn.IFS( AK4<=2500,"Very Weak", AK4<=5000,"Poor", AK4<=10000,"Challenging", AK4<=12500,"Border Line", AK4<=15000,"Improved", AK4<=20000,"Moderate", AK4<=25000,"Satisfactory", AK4<=30000,"Good", AK4<=35000,"Very Good", AK4<=40000,"High", AK4<=50000,"Excellent", AK4<=100000,"Superb", AK4>100000,"Superb" ), " Affordability.") -> Weak Economic Resilience with Very Weak Affordability. | AP4: We will assume the 5 socio economic sector spending will increase by 5% every year, Socio Ecnomic Sectors are Health, Housing, Energy and Education. Based on this assumption we will predict the value of Heart next year
A5: =_xlfn.CONCAT(UPPER(B5),"|",C5) -> INDIA|2022 | B5: India | C5: 2022 | D5: 101560000000000 | E5: 0.056376118 | F5: 8020000000 | G5: 0.0088050314 | H5: 3350000000000 | I5: 0.056782334 | J5: 1430000000 | K5: 0.014184397 | L5: 0.032985427 | M5: 788000000000 | N5: 743000000000 | O5: -45000000000 | P5: -0.013432836 | Q5: 0.822 | R5: -0.015568862 | S5: 2753700000000 | T5: 0.04 | U5: 110148000000 | V5: 0.03288 | W5: 0.067 | X5: 2342.6573 | Y5: 2185.6993 | Z5: 0.676 | AA5: 0.044822257 | AB5: 0.328 | AC5: 0 | AD5: 0.348 | AE5: 0.072833028 | AF5: 0.017833013 | AG5: 0.042832911 | AH5: 0.038832928 | AI5: 0.17233188 | AJ5: 0.15900447 | AK5: 760.62336 | AL5: D- | AM5: 0.16D- | AN5: =_xlfn.CONCAT(_xlfn.IFS( AJ5>=0.7,"Superb", AJ5>=0.51,"Excellent", AJ5>=0.41,"Good", AJ5>=0.31,"Satisfactory", AJ5>=0.26,"Moderate", AJ5>=0.1,"Weak", AJ5<0.1,"Very Weak" ), " Economic Resilience with ",_xlfn.IFS( AK5<=2500,"Very Weak", AK5<=5000,"Poor", AK5<=10000,"Challenging", AK5<=12500,"Border Line", AK5<=15000,"Improved", AK5<=20000,"Moderate", AK5<=25000,"Satisfactory", AK5<=30000,"Good", AK5<=35000,"Very Good", AK5<=40000,"High", AK5<=50000,"Excellent", AK5<=100000,"Superb", AK5>100000,"Superb" ), " Affordability.") -> Weak Economic Resilience with Very Weak Affordability. | AP5: We will assume the 5 socio economic sector spending will increase by 5% every year, Socio Ecnomic Sectors are Health, Housing, Energy and Education. Based on this assumption we will predict the value of Heart next year
A6: =_xlfn.CONCAT(UPPER(B6),"|",C6) -> INDIA|2023 | B6: India | C6: 2023 | D6: 106800000000000 | E6: 0.051595116 | F6: 8090000000 | G6: 0.0087281796 | H6: 3640000000000 | I6: 0.086567164 | J6: 1440000000 | K6: 0.006993007 | L6: 0.034082397 | M6: 856650000000 | N6: 774000000000 | O6: -82650000000 | P6: -0.022706044 | Q6: 0.812 | R6: -0.01216545 | S6: 2955680000000 | T6: 0.065 | U6: 192119200000 | V6: 0.05278 | W6: 0.0565 | X6: 2527.7778 | Y6: 2384.9583 | Z6: 0.685 | AA6: 0.013313609 | AB6: 0.328 | AC6: 0 | AD6: 0.357 | AE6: 0.075100553 | AF6: 0.020100538 | AG6: 0.045100436 | AH6: 0.041100452 | AI6: 0.18140198 | AJ6: 0.13999833 | AK6: 851.43012 | AL6: D- | AM6: 0.14D- | AN6: =_xlfn.CONCAT(_xlfn.IFS( AJ6>=0.7,"Superb", AJ6>=0.51,"Excellent", AJ6>=0.41,"Good", AJ6>=0.31,"Satisfactory", AJ6>=0.26,"Moderate", AJ6>=0.1,"Weak", AJ6<0.1,"Very Weak" ), " Economic Resilience with ",_xlfn.IFS( AK6<=2500,"Very Weak", AK6<=5000,"Poor", AK6<=10000,"Challenging", AK6<=12500,"Border Line", AK6<=15000,"Improved", AK6<=20000,"Moderate", AK6<=25000,"Satisfactory", AK6<=30000,"Good", AK6<=35000,"Very Good", AK6<=40000,"High", AK6<=50000,"Excellent", AK6<=100000,"Superb", AK6>100000,"Superb" ), " Affordability.") -> Weak Economic Resilience with Very Weak Affordability. | AP6: We will assume the 5 socio economic sector spending will increase by 5% every year, Socio Ecnomic Sectors are Health, Housing, Energy and Education. Based on this assumption we will predict the value of Heart next year
A7: =_xlfn.CONCAT(UPPER(B7),"|",C7) -> INDIA|2024 | B7: India | C7: 2024 | D7: 112600000000000 | E7: 0.054307116 | F7: 8161972572 | G7: 0.008896486 | H7: 3910000000000 | I7: 0.074175824 | J7: 1450000000 | K7: 0.0069444444 | L7: 0.034724689 | M7: 919210000000 | N7: 828630000000 | O7: -90580000000 | P7: -0.02316624 | Q7: 0.813 | R7: 0.0012315271 | S7: 3178830000000 | T7: 0.065 | U7: 206623950000 | V7: 0.052845 | W7: 0.0495 | X7: 2696.5517 | Y7: 2563.0724 | Z7: 0.685 | AA7: 0 | AB7: 0.328 | AC7: 0 | AD7: 0.357 | AE7: 0.077487421 | AF7: 0.022487406 | AG7: 0.047487304 | AH7: 0.04348732 | AI7: 0.19094945 | AJ7: 0.1496629 | AK7: 915.01685 | AL7: D- | AM7: 0.15D- | AN7: =_xlfn.CONCAT(_xlfn.IFS( AJ7>=0.7,"Superb", AJ7>=0.51,"Excellent", AJ7>=0.41,"Good", AJ7>=0.31,"Satisfactory", AJ7>=0.26,"Moderate", AJ7>=0.1,"Weak", AJ7<0.1,"Very Weak" ), " Economic Resilience with ",_xlfn.IFS( AK7<=2500,"Very Weak", AK7<=5000,"Poor", AK7<=10000,"Challenging", AK7<=12500,"Border Line", AK7<=15000,"Improved", AK7<=20000,"Moderate", AK7<=25000,"Satisfactory", AK7<=30000,"Good", AK7<=35000,"Very Good", AK7<=40000,"High", AK7<=50000,"Excellent", AK7<=100000,"Superb", AK7>100000,"Superb" ), " Affordability.") -> Weak Economic Resilience with Very Weak Affordability. | AP7: We will assume the 5 socio economic sector spending will increase by 5% every year, Socio Ecnomic Sectors are Health, Housing, Energy and Education. Based on this assumption we will predict the value of Heart next year
A8: =_xlfn.CONCAT(UPPER(B8),"|",C8) -> INDIA|2025 | B8: India | C8: 2025 | D8: 113795678000000 | E8: 0.01061881 | F8: 8231613070 | G8: 0.0085323122 | H8: 4187017000000 | I8: 0.070848338 | J8: 1425000000 | K8: -0.017241379 | L8: 0.036794165 | M8: 918920000000 | N8: 828920000000 | O8: -90000000000 | P8: -0.021495017 | Q8: 0.82999997 | R8: 0.020910177 | S8: 3475224000000 | T8: 0.055 | U8: 191137320000 | V8: 0.045649999 | W8: 0.0282 | X8: 2938.2575 | Y8: 2855.3987 | Z8: 0.685 | AA8: 0 | AB8: 0.328 | AC8: 0 | AD8: 0.357 | AE8: 0.079999914 | AF8: 0.024999898 | AG8: 0.049999797 | AH8: 0.045999813 | AI8: 0.20099942 | AJ8: 0.17064857 | AK8: 1019.3773 | AL8: D- | AM8: 0.17D- | AN8: =_xlfn.CONCAT(_xlfn.IFS( AJ8>=0.7,"Superb", AJ8>=0.51,"Excellent", AJ8>=0.41,"Good", AJ8>=0.31,"Satisfactory", AJ8>=0.26,"Moderate", AJ8>=0.1,"Weak", AJ8<0.1,"Very Weak" ), " Economic Resilience with ",_xlfn.IFS( AK8<=2500,"Very Weak", AK8<=5000,"Poor", AK8<=10000,"Challenging", AK8<=12500,"Border Line", AK8<=15000,"Improved", AK8<=20000,"Moderate", AK8<=25000,"Satisfactory", AK8<=30000,"Good", AK8<=35000,"Very Good", AK8<=40000,"High", AK8<=50000,"Excellent", AK8<=100000,"Superb", AK8>100000,"Superb" ), " Affordability.") -> Weak Economic Resilience with Very Weak Affordability. | AO8: 4th largest per GDP but underperformed against peer China.Very low Affordability and Human development. Must adopt inclussive economy & fix US tarrif threat. | AP8: We will assume the 5 socio economic sector spending will increase by 5% every year, Socio Ecnomic Sectors are Health, Housing, Energy and Education. Based on this assumption we will predict the value of Heart next year
A9: =_xlfn.CONCAT(UPPER(B9),"|",C9) -> INDIA|2026 | B9: India | C9: 2026 | D9: 120063810405112 | E9: 0.055082342 | F9: 8302201675 | G9: 0.0085753064 | H9: 4435586665427 | I9: 0.059366768 | J9: 1442637444 | K9: 0.012377153 | L9: 0.036943577 | M9: 1017801428571 | N9: 931367142857 | O9: -86434285714 | P9: -0.019486551 | Q9: 0.83892275 | R9: 0.010750333 | S9: 3721114563803 | T9: 0.059428571 | U9: 221140522649 | V9: 0.049855981 | W9: 0.042928571 | X9: 3074.6371 | Y9: 2942.6474 | Z9: 0.69453995 | AA9: 0.013926931 | AB9: 0.32502381 | AC9: -0.0091568383 | AD9: 0.36951614 | AE9: 0.082512407 | AF9: 0.027512391 | AG9: 0.05251229 | AH9: 0.048512306 | AI9: 0.21104939 | AJ9: 0.17865044 | AK9: 1087.3557 | AL9: D- | AM9: 0.18D- | AN9: =_xlfn.CONCAT(_xlfn.IFS( AJ9>=0.7,"Superb", AJ9>=0.51,"Excellent", AJ9>=0.41,"Good", AJ9>=0.31,"Satisfactory", AJ9>=0.26,"Moderate", AJ9>=0.1,"Weak", AJ9<0.1,"Very Weak" ), " Economic Resilience with ",_xlfn.IFS( AK9<=2500,"Very Weak", AK9<=5000,"Poor", AK9<=10000,"Challenging", AK9<=12500,"Border Line", AK9<=15000,"Improved", AK9<=20000,"Moderate", AK9<=25000,"Satisfactory", AK9<=30000,"Good", AK9<=35000,"Very Good", AK9<=40000,"High", AK9<=50000,"Excellent", AK9<=100000,"Superb", AK9>100000,"Superb" ), " Affordability.") -> Weak Economic Resilience with Very Weak Affordability. | AP9: We will assume the 5 socio economic sector spending will increase by 5% every year, Socio Ecnomic Sectors are Health, Housing, Energy and Education. Based on this assumption we will predict the value of Heart next year
A10: =_xlfn.CONCAT(UPPER(B10),"|",C10) -> INDIA|2027 | B10: India | C10: 2027 | D10: 125735541889780 | E10: 0.047239309 | F10: 8372937901 | G10: 0.0085201769 | H10: 4700572377145 | I10: 0.059740849 | J10: 1453619908 | K10: 0.0076127683 | L10: 0.037384596 | M10: 1081866785714 | N10: 992010714286 | O10: -89856071429 | P10: -0.019115985 | Q10: 0.84611799 | R10: 0.0085767638 | S10: 3977238863025 | T10: 0.061017857 | U10: 242682592767 | V10: 0.051628307 | W10: 0.040946429 | X10: 3233.7012 | Y10: 3101.2926 | Z10: 0.70239004 | AA10: 0.011302582 | AB10: 0.32288318 | AC10: -0.0066297278 | AD10: 0.37950686 | AE10: 0.085150524 | AF10: 0.030150509 | AG10: 0.055150407 | AH10: 0.051150423 | AI10: 0.22160186 | AJ10: 0.18824217 | AK10: 1176.9618 | AL10: D- | AM10: 0.19D- | AN10: =_xlfn.CONCAT(_xlfn.IFS( AJ10>=0.7,"Superb", AJ10>=0.51,"Excellent", AJ10>=0.41,"Good", AJ10>=0.31,"Satisfactory", AJ10>=0.26,"Moderate", AJ10>=0.1,"Weak", AJ10<0.1,"Very Weak" ), " Economic Resilience with ",_xlfn.IFS( AK10<=2500,"Very Weak", AK10<=5000,"Poor", AK10<=10000,"Challenging", AK10<=12500,"Border Line", AK10<=15000,"Improved", AK10<=20000,"Moderate", AK10<=25000,"Satisfactory", AK10<=30000,"Good", AK10<=35000,"Very Good", AK10<=40000,"High", AK10<=50000,"Excellent", AK10<=100000,"Superb", AK10>100000,"Superb" ), " Affordability.") -> Weak Economic Resilience with Very Weak Affordability. | AP10: We will assume the 5 socio economic sector spending will increase by 5% every year, Socio Ecnomic Sectors are Health, Housing, Energy and Education. Based on this assumption we will predict the value of Heart next year
A11: =_xlfn.CONCAT(UPPER(B11),"|",C11) -> INDIA|2028 | B11: India | C11: 2028 | D11: 131237442252096 | E11: 0.043757718 | F11: 8443822776 | G11: 0.0084659502 | H11: 4974261388939 | I11: 0.058224614 | J11: 1462336629 | K11: 0.0059965613 | L11: 0.037902761 | M11: 1145932142857 | N11: 1052654285714 | O11: -93277857143 | P11: -0.018752102 | Q11: 0.8527313 | R11: 0.0078160571 | S11: 4241708375729 | T11: 0.062607143 | U11: 265561242238 | V11: 0.05338707 | W11: 0.038964286 | X11: 3401.5843 | Y11: 3269.044 | Z11: 0.70967244 | AA11: 0.010368019 | AB11: 0.32102777 | AC11: -0.0057795964 | AD11: 0.38864467 | AE11: 0.087920548 | AF11: 0.032920532 | AG11: 0.05792043 | AH11: 0.053920447 | AI11: 0.23268196 | AJ11: 0.19844555 | AK11: 1270.4965 | AL11: D- | AM11: 0.2D- | AN11: =_xlfn.CONCAT(_xlfn.IFS( AJ11>=0.7,"Superb", AJ11>=0.51,"Excellent", AJ11>=0.41,"Good", AJ11>=0.31,"Satisfactory", AJ11>=0.26,"Moderate", AJ11>=0.1,"Weak", AJ11<0.1,"Very Weak" ), " Economic Resilience with ",_xlfn.IFS( AK11<=2500,"Very Weak", AK11<=5000,"Poor", AK11<=10000,"Challenging", AK11<=12500,"Border Line", AK11<=15000,"Improved", AK11<=20000,"Moderate", AK11<=25000,"Satisfactory", AK11<=30000,"Good", AK11<=35000,"Very Good", AK11<=40000,"High", AK11<=50000,"Excellent", AK11<=100000,"Superb", AK11>100000,"Superb" ), " Affordability.") -> Weak Economic Resilience with Very Weak Affordability. | AP11: We will assume the 5 socio economic sector spending will increase by 5% every year, Socio Ecnomic Sectors are Health, Housing, Energy and Education. Based on this assumption we will predict the value of Heart next year
A12: =_xlfn.CONCAT(UPPER(B12),"|",C12) -> INDIA|2029 | B12: India | C12: 2029 | D12: 136712479650225 | E12: 0.041718562 | F12: 8514849364 | G12: 0.0084116625 | H12: 5253763699966 | I12: 0.056189711 | J12: 1470250482 | K12: 0.0054117861 | L12: 0.038429291 | M12: 1209997500000 | N12: 1113297857143 | O12: -96699642857 | P12: -0.018405785 | Q12: 0.85914709 | R12: 0.007523812 | S12: 4513755788876 | T12: 0.064196429 | U12: 289767001089 | V12: 0.055154175 | W12: 0.036982143 | X12: 3573.38 | Y12: 3441.2288 | Z12: 0.71676148 | AA12: 0.0099891712 | AB12: 0.31927477 | AC12: -0.0054905762 | AD12: 0.39748671 | AE12: 0.090829072 | AF12: 0.035829056 | AG12: 0.060828955 | AH12: 0.056828971 | AI12: 0.24431605 | AJ12: 0.20918539 | AK12: 1367.8427 | AL12: D- | AM12: 0.21D- | AN12: =_xlfn.CONCAT(_xlfn.IFS( AJ12>=0.7,"Superb", AJ12>=0.51,"Excellent", AJ12>=0.41,"Good", AJ12>=0.31,"Satisfactory", AJ12>=0.26,"Moderate", AJ12>=0.1,"Weak", AJ12<0.1,"Very Weak" ), " Economic Resilience with ",_xlfn.IFS( AK12<=2500,"Very Weak", AK12<=5000,"Poor", AK12<=10000,"Challenging", AK12<=12500,"Border Line", AK12<=15000,"Improved", AK12<=20000,"Moderate", AK12<=25000,"Satisfactory", AK12<=30000,"Good", AK12<=35000,"Very Good", AK12<=40000,"High", AK12<=50000,"Excellent", AK12<=100000,"Superb", AK12>100000,"Superb" ), " Affordability.") -> Weak Economic Resilience with Very Weak Affordability. | AP12: We will assume the 5 socio economic sector spending will increase by 5% every year, Socio Ecnomic Sectors are Health, Housing, Energy and Education. Based on this assumption we will predict the value of Heart next year
A13: =_xlfn.CONCAT(UPPER(B13),"|",C13) -> INDIA|2030 | B13: India | C13: 2030 | D13: 142137128357288 | F13: 8586617399 | H13: 5548925439435 | J13: 1475246999 | L13: 0.03903924 | M13: 1274062857143 | N13: 1173941428571 | O13: -100121428571 | P13: -0.01804339 | Q13: 0.86549985 | S13: 4802594109468 | T13: 0.065785714 | U13: 315942083916 | V13: 0.056937526 | W13: 0.035 | X13: 3761.3535 | Y13: 3629.7061 | Z13: 0.72378782 | AB13: 0.31756052 | AD13: 0.4062273 | AE13: 0.093883023 | AF13: 0.038883007 | AG13: 0.063882906 | AH13: 0.059882922 | AI13: 0.25653186 | AJ13: 0.22059018 | AK13: 1474.4857 | AL13: D- | AM13: 0.22D- | AN13: =_xlfn.CONCAT(_xlfn.IFS( AJ13>=0.7,"Superb", AJ13>=0.51,"Excellent", AJ13>=0.41,"Good", AJ13>=0.31,"Satisfactory", AJ13>=0.26,"Moderate", AJ13>=0.1,"Weak", AJ13<0.1,"Very Weak" ), " Economic Resilience with ",_xlfn.IFS( AK13<=2500,"Very Weak", AK13<=5000,"Poor", AK13<=10000,"Challenging", AK13<=12500,"Border Line", AK13<=15000,"Improved", AK13<=20000,"Moderate", AK13<=25000,"Satisfactory", AK13<=30000,"Good", AK13<=35000,"Very Good", AK13<=40000,"High", AK13<=50000,"Excellent", AK13<=100000,"Superb", AK13>100000,"Superb" ), " Affordability.") -> Weak Economic Resilience with Very Weak Affordability. | AP13: We will assume the 5 socio economic sector spending will increase by 5% every year, Socio Ecnomic Sectors are Health, Housing, Energy and Education. Based on this assumption we will predict the value of Heart next year
A14: =_xlfn.CONCAT(UPPER(B14),"|",C14) -> USA|2019 | B14: USA | C14: 2019 | D14: 87700000000000 | F14: 7810000000 | H14: 21540000000000 | J14: 330226227 | L14: 0.24561003 | M14: 2512360000000 | N14: 1655100000000 | O14: -857260000000 | P14: -0.039798514 | Q14: 1.054754 | S14: 22719401753434 | T14: 0.0225 | U14: 511186539452 | V14: 0.023731966 | W14: 0.02 | X14: 65228.011 | Y14: 63923.451 | Z14: 0.936 | AB14: 0.419 | AD14: 0.517 | AE14: 0.12978058 | AF14: 0.14478058 | AG14: 0.048780579 | AH14: 0.023180579 | AI14: 0.34652232 | AJ14: 0.52860187 | AK14: 33048.424 | AL14: B+ | AM14: 0.53B+ | AN14: =_xlfn.CONCAT(_xlfn.IFS( AJ14>=0.7,"Superb", AJ14>=0.51,"Excellent", AJ14>=0.41,"Good", AJ14>=0.31,"Satisfactory", AJ14>=0.26,"Moderate", AJ14>=0.1,"Weak", AJ14<0.1,"Very Weak" ), " Economic Resilience with ",_xlfn.IFS( AK14<=2500,"Very Weak", AK14<=5000,"Poor", AK14<=10000,"Challenging", AK14<=12500,"Border Line", AK14<=15000,"Improved", AK14<=20000,"Moderate", AK14<=25000,"Satisfactory", AK14<=30000,"Good", AK14<=35000,"Very Good", AK14<=40000,"High", AK14<=50000,"Excellent", AK14<=100000,"Superb", AK14>100000,"Superb" ), " Affordability.") -> Excellent Economic Resilience with Very Good Affordability. | AP14: We will assume the 5 socio economic sector spending will increase by 5% every year, Socio Ecnomic Sectors are Health, Housing, Energy and Education. Based on this assumption we will predict the value of Heart next year
A15: =_xlfn.CONCAT(UPPER(B15),"|",C15) -> USA|2020 | B15: USA | C15: 2020 | D15: 84750000000000 | E15: -0.0336374 | F15: 7890000000 | G15: 0.010243278 | H15: 21350000000000 | I15: -0.0088207985 | J15: 331577720 | K15: 0.0040926277 | L15: 0.2519174 | M15: 2346730000000 | N15: 1433850000000 | O15: -912880000000 | P15: -0.042757845 | Q15: 1.2620792 | R15: 0.19656259 | S15: 26945391194615 | T15: 0.0025 | U15: 67363477987 | V15: 0.003155198 | W15: 0.003 | X15: 64389.127 | Y15: 64195.96 | Z15: 0.925 | AA15: -0.011752137 | AB15: 0.4 | AC15: -0.0475 | AD15: 0.525 | AE15: 0.13434008 | AF15: 0.14934008 | AG15: 0.053340083 | AH15: 0.027740083 | AI15: 0.36476033 | AJ15: 0.57076469 | AK15: 33702.879 | AL15: B+ | AM15: 0.57B+ | AN15: =_xlfn.CONCAT(_xlfn.IFS( AJ15>=0.7,"Superb", AJ15>=0.51,"Excellent", AJ15>=0.41,"Good", AJ15>=0.31,"Satisfactory", AJ15>=0.26,"Moderate", AJ15>=0.1,"Weak", AJ15<0.1,"Very Weak" ), " Economic Resilience with ",_xlfn.IFS( AK15<=2500,"Very Weak", AK15<=5000,"Poor", AK15<=10000,"Challenging", AK15<=12500,"Border Line", AK15<=15000,"Improved", AK15<=20000,"Moderate", AK15<=25000,"Satisfactory", AK15<=30000,"Good", AK15<=35000,"Very Good", AK15<=40000,"High", AK15<=50000,"Excellent", AK15<=100000,"Superb", AK15>100000,"Superb" ), " Affordability.") -> Excellent Economic Resilience with Very Good Affordability. | AP15: We will assume the 5 socio economic sector spending will increase by 5% every year, Socio Ecnomic Sectors are Health, Housing, Energy and Education. Based on this assumption we will predict the value of Heart next year
A16: =_xlfn.CONCAT(UPPER(B16),"|",C16) -> USA|2021 | B16: USA | C16: 2021 | D16: 96140000000000 | E16: 0.13439528 | F16: 7950000000 | G16: 0.0076045627 | H16: 23680000000000 | I16: 0.10913349 | J16: 332099760 | K16: 0.0015744122 | L16: 0.24630747 | M16: 2849040000000 | N16: 1765850000000 | O16: -1083190000000 | P16: -0.045742821 | Q16: 1.2005455 | R16: -0.048755787 | S16: 2.8428919e+13 | T16: 0.0025 | U16: 71072296425 | V16: 0.0030013639 | W16: 0.042 | X16: 71303.876 | Y16: 68309.113 | Z16: 0.921 | AA16: -0.0043243243 | AB16: 0.397 | AC16: -0.0075566751 | AD16: 0.524 | AE16: 0.13913956 | AF16: 0.15413956 | AG16: 0.058139562 | AH16: 0.032539562 | AI16: 0.38395825 | AJ16: 0.58152153 | AK16: 35793.975 | AL16: A- | AM16: 0.58A- | AN16: =_xlfn.CONCAT(_xlfn.IFS( AJ16>=0.7,"Superb", AJ16>=0.51,"Excellent", AJ16>=0.41,"Good", AJ16>=0.31,"Satisfactory", AJ16>=0.26,"Moderate", AJ16>=0.1,"Weak", AJ16<0.1,"Very Weak" ), " Economic Resilience with ",_xlfn.IFS( AK16<=2500,"Very Weak", AK16<=5000,"Poor", AK16<=10000,"Challenging", AK16<=12500,"Border Line", AK16<=15000,"Improved", AK16<=20000,"Moderate", AK16<=25000,"Satisfactory", AK16<=30000,"Good", AK16<=35000,"Very Good", AK16<=40000,"High", AK16<=50000,"Excellent", AK16<=100000,"Superb", AK16>100000,"Superb" ), " Affordability.") -> Excellent Economic Resilience with High Affordability. | AP16: We will assume the 5 socio economic sector spending will increase by 5% every year, Socio Ecnomic Sectors are Health, Housing, Energy and Education. Based on this assumption we will predict the value of Heart next year
A17: =_xlfn.CONCAT(UPPER(B17),"|",C17) -> USA|2022 | B17: USA | C17: 2022 | D17: 101560000000000 | E17: 0.056376118 | F17: 8020000000 | G17: 0.0088050314 | H17: 26010000000000 | I17: 0.09839527 | J17: 334017321 | K17: 0.0057740511 | L17: 0.25610477 | M17: 3270280000000 | N17: 2090340000000 | O17: -1179940000000 | P17: -0.04536486 | Q17: 1.1891162 | R17: -0.0095201523 | S17: 30928911613307 | T17: 0.025 | U17: 773222790333 | V17: 0.029727904 | W17: 0.083 | X17: 77870.213 | Y17: 71406.986 | Z17: 0.93 | AA17: 0.009771987 | AB17: 0.417 | AC17: 0.047961631 | AD17: 0.513 | AE17: 0.14419164 | AF17: 0.15919164 | AG17: 0.063191644 | AH17: 0.037591644 | AI17: 0.40416657 | AJ17: 0.58517858 | AK17: 36631.784 | AL17: A- | AM17: 0.59A- | AN17: =_xlfn.CONCAT(_xlfn.IFS( AJ17>=0.7,"Superb", AJ17>=0.51,"Excellent", AJ17>=0.41,"Good", AJ17>=0.31,"Satisfactory", AJ17>=0.26,"Moderate", AJ17>=0.1,"Weak", AJ17<0.1,"Very Weak" ), " Economic Resilience with ",_xlfn.IFS( AK17<=2500,"Very Weak", AK17<=5000,"Poor", AK17<=10000,"Challenging", AK17<=12500,"Border Line", AK17<=15000,"Improved", AK17<=20000,"Moderate", AK17<=25000,"Satisfactory", AK17<=30000,"Good", AK17<=35000,"Very Good", AK17<=40000,"High", AK17<=50000,"Excellent", AK17<=100000,"Superb", AK17>100000,"Superb" ), " Affordability.") -> Excellent Economic Resilience with High Affordability. | AP17: We will assume the 5 socio economic sector spending will increase by 5% every year, Socio Ecnomic Sectors are Health, Housing, Energy and Education. Based on this assumption we will predict the value of Heart next year
A18: =_xlfn.CONCAT(UPPER(B18),"|",C18) -> USA|2023 | B18: USA | C18: 2023 | D18: 106800000000000 | E18: 0.051595116 | F18: 8090000000 | G18: 0.0087281796 | H18: 27720000000000 | I18: 0.065743945 | J18: 336806231 | K18: 0.0083495969 | L18: 0.25955056 | M18: 3108510000000 | N18: 2045220000000 | O18: -1063290000000 | P18: -0.038358225 | Q18: 1.1965128 | R18: 0.0062202509 | S18: 33167334044723 | T18: 0.055 | U18: 1824203372460 | V18: 0.065808202 | W18: 0.049 | X18: 82302.515 | Y18: 78269.692 | Z18: 0.938 | AA18: 0.0086021505 | AB18: 0.418 | AC18: 0.0023923445 | AD18: 0.52 | AE18: 0.14950963 | AF18: 0.16450962 | AG18: 0.068509625 | AH18: 0.042909625 | AI18: 0.4254385 | AJ18: 0.58082263 | AK18: 40700.24 | AL18: A | AM18: 0.58A | AN18: =_xlfn.CONCAT(_xlfn.IFS( AJ18>=0.7,"Superb", AJ18>=0.51,"Excellent", AJ18>=0.41,"Good", AJ18>=0.31,"Satisfactory", AJ18>=0.26,"Moderate", AJ18>=0.1,"Weak", AJ18<0.1,"Very Weak" ), " Economic Resilience with ",_xlfn.IFS( AK18<=2500,"Very Weak", AK18<=5000,"Poor", AK18<=10000,"Challenging", AK18<=12500,"Border Line", AK18<=15000,"Improved", AK18<=20000,"Moderate", AK18<=25000,"Satisfactory", AK18<=30000,"Good", AK18<=35000,"Very Good", AK18<=40000,"High", AK18<=50000,"Excellent", AK18<=100000,"Superb", AK18>100000,"Superb" ), " Affordability.") -> Excellent Economic Resilience with Excellent Affordability. | AP18: We will assume the 5 socio economic sector spending will increase by 5% every year, Socio Ecnomic Sectors are Health, Housing, Energy and Education. Based on this assumption we will predict the value of Heart next year
A19: =_xlfn.CONCAT(UPPER(B19),"|",C19) -> USA|2024 | B19: USA | C19: 2024 | D19: 112600000000000 | E19: 0.054307116 | F19: 8161972572 | G19: 0.008896486 | H19: 29180000000000 | I19: 0.052669553 | J19: 340110988 | K19: 0.0098120423 | L19: 0.25914742 | M19: 3296240000000 | N19: 2093250000000 | O19: -1202990000000 | P19: -0.041226525 | Q19: 1.2153761 | R19: 0.015765235 | S19: 35464673929172 | T19: 0.055 | U19: 1950557066104 | V19: 0.066845684 | W19: 0.034 | X19: 85795.523 | Y19: 82878.475 | Z19: 0.943 | AA19: 0.0053304904 | AB19: 0.419 | AC19: 0.0023866348 | AD19: 0.524 | AE19: 0.1551075 | AF19: 0.1701075 | AG19: 0.0741075 | AH19: 0.0485075 | AI19: 0.44783 | AJ19: 0.59890522 | AK19: 43428.321 | AL19: A | AM19: 0.6A | AN19: =_xlfn.CONCAT(_xlfn.IFS( AJ19>=0.7,"Superb", AJ19>=0.51,"Excellent", AJ19>=0.41,"Good", AJ19>=0.31,"Satisfactory", AJ19>=0.26,"Moderate", AJ19>=0.1,"Weak", AJ19<0.1,"Very Weak" ), " Economic Resilience with ",_xlfn.IFS( AK19<=2500,"Very Weak", AK19<=5000,"Poor", AK19<=10000,"Challenging", AK19<=12500,"Border Line", AK19<=15000,"Improved", AK19<=20000,"Moderate", AK19<=25000,"Satisfactory", AK19<=30000,"Good", AK19<=35000,"Very Good", AK19<=40000,"High", AK19<=50000,"Excellent", AK19<=100000,"Superb", AK19>100000,"Superb" ), " Affordability.") -> Excellent Economic Resilience with Excellent Affordability. | AP19: We will assume the 5 socio economic sector spending will increase by 5% every year, Socio Ecnomic Sectors are Health, Housing, Energy and Education. Based on this assumption we will predict the value of Heart next year
A20: =_xlfn.CONCAT(UPPER(B20),"|",C20) -> USA|2025 | B20: USA | C20: 2025 | D20: 113795678000000 | E20: 0.01061881 | F20: 8231613070 | G20: 0.0085323122 | H20: 30507217000000 | I20: 0.04548379 | J20: 338000000 | K20: -0.0062067621 | L20: 0.26808766 | M20: 3393000000000 | N20: 2393000000000 | O20: -1000000000000 | P20: -0.032779129 | Q20: 1.1866045 | R20: -0.023673009 | S20: 36200000000000 | T20: 0.045 | U20: 1629000000000 | V20: 0.053397201 | W20: 0.0235 | X20: 90258.038 | Y20: 88136.975 | Z20: 0.948 | AA20: 0.0053022269 | AB20: 0.42 | AC20: 0.0023809524 | AD20: 0.528 | AE20: 0.161 | AF20: 0.176 | AG20: 0.08 | AH20: 0.0544 | AI20: 0.4714 | AJ20: 0.65331133 | AK20: 46536.323 | AL20: A | AM20: 0.65A | AN20: =_xlfn.CONCAT(_xlfn.IFS( AJ20>=0.7,"Superb", AJ20>=0.51,"Excellent", AJ20>=0.41,"Good", AJ20>=0.31,"Satisfactory", AJ20>=0.26,"Moderate", AJ20>=0.1,"Weak", AJ20<0.1,"Very Weak" ), " Economic Resilience with ",_xlfn.IFS( AK20<=2500,"Very Weak", AK20<=5000,"Poor", AK20<=10000,"Challenging", AK20<=12500,"Border Line", AK20<=15000,"Improved", AK20<=20000,"Moderate", AK20<=25000,"Satisfactory", AK20<=30000,"Good", AK20<=35000,"Very Good", AK20<=40000,"High", AK20<=50000,"Excellent", AK20<=100000,"Superb", AK20>100000,"Superb" ), " Affordability.") -> Excellent Economic Resilience with Excellent Affordability. | AO20: Biggest economy per GDP.Facing high debt/GDP and trade defecit challenges. Uncertain and unpredictable trade policies are inflationary and would put pressure on economic growth. Must reach economic normality quickly to fix US and global economy. | AP20: We will assume the 5 socio economic sector spending will increase by 5% every year, Socio Ecnomic Sectors are Health, Housing, Energy and Education. Based on this assumption we will predict the value of Heart next year
A21: =_xlfn.CONCAT(UPPER(B21),"|",C21) -> USA|2026 | B21: USA | C21: 2026 | D21: 120063810405112 | E21: 0.055082342 | F21: 8302201675 | G21: 0.0085753064 | H21: 32360367393707 | I21: 0.060744656 | J21: 3.402256e+08 | K21: 0.0065846118 | L21: 0.26952641 | M21: 3653795714286 | N21: 2469782857143 | O21: -1184012857143 | P21: -0.036588363 | Q21: 1.2213168 | R21: 0.029253536 | S21: 39522261786479 | T21: 0.061785714 | U21: 2441911174665 | V21: 0.075459934 | W21: 0.047714286 | X21: 95114.44 | Y21: 90576.123 | Z21: 0.94859293 | AA21: 0.00062545325 | AB21: 0.42085941 | AC21: 0.0020420451 | AD21: 0.52773352 | AE21: 0.1668925 | AF21: 0.1818925 | AG21: 0.0858925 | AH21: 0.0602925 | AI21: 0.49497 | AJ21: 0.65244811 | AK21: 47800.056 | AL21: A | AM21: 0.65A | AN21: =_xlfn.CONCAT(_xlfn.IFS( AJ21>=0.7,"Superb", AJ21>=0.51,"Excellent", AJ21>=0.41,"Good", AJ21>=0.31,"Satisfactory", AJ21>=0.26,"Moderate", AJ21>=0.1,"Weak", AJ21<0.1,"Very Weak" ), " Economic Resilience with ",_xlfn.IFS( AK21<=2500,"Very Weak", AK21<=5000,"Poor", AK21<=10000,"Challenging", AK21<=12500,"Border Line", AK21<=15000,"Improved", AK21<=20000,"Moderate", AK21<=25000,"Satisfactory", AK21<=30000,"Good", AK21<=35000,"Very Good", AK21<=40000,"High", AK21<=50000,"Excellent", AK21<=100000,"Superb", AK21>100000,"Superb" ), " Affordability.") -> Excellent Economic Resilience with Excellent Affordability. | AP21: We will assume the 5 socio economic sector spending will increase by 5% every year, Socio Ecnomic Sectors are Health, Housing, Energy and Education. Based on this assumption we will predict the value of Heart next year
A22: =_xlfn.CONCAT(UPPER(B22),"|",C22) -> USA|2027 | B22: USA | C22: 2027 | D22: 125735541889780 | E22: 0.047239309 | F22: 8372937901 | G22: 0.0085201769 | H22: 34173461630718 | I22: 0.056028234 | J22: 341986344 | K22: 0.0051752285 | L22: 0.2717884 | M22: 3825238928572 | N22: 2605921071429 | O22: -1219317857143 | P22: -0.035680256 | Q22: 1.2430331 | R22: 0.017781044 | S22: 42478745078487 | T22: 0.069821429 | U22: 2965926665302 | V22: 0.086790349 | W22: 0.050553571 | X22: 99926.392 | Y22: 94874.756 | Z22: 0.9507382 | AA22: 0.0022615245 | AB22: 0.42224361 | AC22: 0.0032781979 | AD22: 0.52849458 | AE22: 0.17307962 | AF22: 0.18807963 | AG22: 0.092079625 | AH22: 0.066479625 | AI22: 0.5197185 | AJ22: 0.66903629 | AK22: 50140.795 | AL22: A+ | AM22: 0.67A+ | AN22: =_xlfn.CONCAT(_xlfn.IFS( AJ22>=0.7,"Superb", AJ22>=0.51,"Excellent", AJ22>=0.41,"Good", AJ22>=0.31,"Satisfactory", AJ22>=0.26,"Moderate", AJ22>=0.1,"Weak", AJ22<0.1,"Very Weak" ), " Economic Resilience with ",_xlfn.IFS( AK22<=2500,"Very Weak", AK22<=5000,"Poor", AK22<=10000,"Challenging", AK22<=12500,"Border Line", AK22<=15000,"Improved", AK22<=20000,"Moderate", AK22<=25000,"Satisfactory", AK22<=30000,"Good", AK22<=35000,"Very Good", AK22<=40000,"High", AK22<=50000,"Excellent", AK22<=100000,"Superb", AK22>100000,"Superb" ), " Affordability.") -> Excellent Economic Resilience with Superb Affordability. | AP22: We will assume the 5 socio economic sector spending will increase by 5% every year, Socio Ecnomic Sectors are Health, Housing, Energy and Education. Based on this assumption we will predict the value of Heart next year
A23: =_xlfn.CONCAT(UPPER(B23),"|",C23) -> USA|2028 | B23: USA | C23: 2028 | D23: 131237442252096 | E23: 0.043757718 | F23: 8443822776 | G23: 0.0084659502 | H23: 35989111080848 | I23: 0.053130393 | J23: 3.4358954e+08 | K23: 0.0046878804 | L23: 0.27422899 | M23: 3996682142857 | N23: 2742059285714 | O23: -1254622857143 | P23: -0.034861179 | Q23: 1.2602965 | R23: 0.013888116 | S23: 45356951496476 | T23: 0.077857143 | U23: 3531362652226 | V23: 0.098123086 | W23: 0.053392857 | X23: 104744.49 | Y23: 99151.884 | Z23: 0.95341342 | AA23: 0.0028138365 | AB23: 0.42380656 | AC23: 0.0036878855 | AD23: 0.52960686 | AE23: 0.17957611 | AF23: 0.19457611 | AG23: 0.098576106 | AH23: 0.072976106 | AI23: 0.54570443 | AJ23: 0.68694915 | AK23: 52511.517 | AL23: A+ | AM23: 0.69A+ | AN23: =_xlfn.CONCAT(_xlfn.IFS( AJ23>=0.7,"Superb", AJ23>=0.51,"Excellent", AJ23>=0.41,"Good", AJ23>=0.31,"Satisfactory", AJ23>=0.26,"Moderate", AJ23>=0.1,"Weak", AJ23<0.1,"Very Weak" ), " Economic Resilience with ",_xlfn.IFS( AK23<=2500,"Very Weak", AK23<=5000,"Poor", AK23<=10000,"Challenging", AK23<=12500,"Border Line", AK23<=15000,"Improved", AK23<=20000,"Moderate", AK23<=25000,"Satisfactory", AK23<=30000,"Good", AK23<=35000,"Very Good", AK23<=40000,"High", AK23<=50000,"Excellent", AK23<=100000,"Superb", AK23>100000,"Superb" ), " Affordability.") -> Excellent Economic Resilience with Superb Affordability. | AP23: We will assume the 5 socio economic sector spending will increase by 5% every year, Socio Ecnomic Sectors are Health, Housing, Energy and Education. Based on this assumption we will predict the value of Heart next year
A24: =_xlfn.CONCAT(UPPER(B24),"|",C24) -> USA|2029 | B24: USA | C24: 2029 | D24: 136712479650225 | E24: 0.041718562 | F24: 8514849364 | G24: 0.0084116625 | H24: 37820753641775 | I24: 0.050894354 | J24: 3.451375e+08 | K24: 0.0045052869 | L24: 0.27664449 | M24: 4168125357143 | N24: 2878197500000 | O24: -1289927857143 | P24: -0.03410635 | Q24: 1.2759889 | R24: 0.012451305 | S24: 48258860210723 | T24: 0.085892857 | U24: 4145091385957 | V24: 0.10959833 | W24: 0.056232143 | X24: 109581.7 | Y24: 103419.68 | Z24: 0.95627833 | AA24: 0.0030048995 | AB24: 0.42543341 | AC24: 0.0038239694 | AD24: 0.53084492 | AE24: 0.18639741 | AF24: 0.20139741 | AG24: 0.10539741 | AH24: 0.079797412 | AI24: 0.57298965 | AJ24: 0.70592945 | AK24: 54899.814 | AL24: A+ | AM24: 0.71A+ | AN24: =_xlfn.CONCAT(_xlfn.IFS( AJ24>=0.7,"Superb", AJ24>=0.51,"Excellent", AJ24>=0.41,"Good", AJ24>=0.31,"Satisfactory", AJ24>=0.26,"Moderate", AJ24>=0.1,"Weak", AJ24<0.1,"Very Weak" ), " Economic Resilience with ",_xlfn.IFS( AK24<=2500,"Very Weak", AK24<=5000,"Poor", AK24<=10000,"Challenging", AK24<=12500,"Border Line", AK24<=15000,"Improved", AK24<=20000,"Moderate", AK24<=25000,"Satisfactory", AK24<=30000,"Good", AK24<=35000,"Very Good", AK24<=40000,"High", AK24<=50000,"Excellent", AK24<=100000,"Superb", AK24>100000,"Superb" ), " Affordability.") -> Superb Economic Resilience with Superb Affordability. | AP24: We will assume the 5 socio economic sector spending will increase by 5% every year, Socio Ecnomic Sectors are Health, Housing, Energy and Education. Based on this assumption we will predict the value of Heart next year
A25: =_xlfn.CONCAT(UPPER(B25),"|",C25) -> USA|2030 | B25: USA | C25: 2030 | D25: 141834754671550 | F25: 8586617399 | H25: 39740172889890 | J25: 3.4676317e+08 | L25: 0.28018643 | M25: 4339568571429 | N25: 3014335714286 | O25: -1325232857143 | P25: -0.033347436 | Q25: 1.291128 | S25: 51309650444299 | T25: 0.093928571 | U25: 4819442166733 | V25: 0.12127381 | W25: 0.059071429 | X25: 114603.21 | Y25: 107833.44 | Z25: 0.95921414 | AB25: 0.42708417 | AD25: 0.53212997 | AE25: 0.19355978 | AF25: 0.20855978 | AG25: 0.11255978 | AH25: 0.086959782 | AI25: 0.60163913 | AJ25: 0.72720431 | AK25: 57381.403 | AL25: A+ | AM25: 0.73A+ | AN25: =_xlfn.CONCAT(_xlfn.IFS( AJ25>=0.7,"Superb", AJ25>=0.51,"Excellent", AJ25>=0.41,"Good", AJ25>=0.31,"Satisfactory", AJ25>=0.26,"Moderate", AJ25>=0.1,"Weak", AJ25<0.1,"Very Weak" ), " Economic Resilience with ",_xlfn.IFS( AK25<=2500,"Very Weak", AK25<=5000,"Poor", AK25<=10000,"Challenging", AK25<=12500,"Border Line", AK25<=15000,"Improved", AK25<=20000,"Moderate", AK25<=25000,"Satisfactory", AK25<=30000,"Good", AK25<=35000,"Very Good", AK25<=40000,"High", AK25<=50000,"Excellent", AK25<=100000,"Superb", AK25>100000,"Superb" ), " Affordability.") -> Superb Economic Resilience with Superb Affordability. | AP25: We will assume the 5 socio economic sector spending will increase by 5% every year, Socio Ecnomic Sectors are Health, Housing, Energy and Education. Based on this assumption we will predict the value of Heart next year
A26: =_xlfn.CONCAT(UPPER(B26),"|",C26) -> UNITED KINGDOM|2019 | B26: United Kingdom | C26: 2019 | D26: 87700000000000 | F26: 7810000000 | H26: 2880000000000 | J26: 66631000 | L26: 0.032839225 | M26: 745700000000 | N26: 718800000000 | O26: -26900000000 | P26: -0.0093402778 | Q26: 0.796 | S26: 2292480000000 | T26: 0.0075 | U26: 17193600000 | V26: 0.00597 | W26: 0.017 | X26: 43223.124 | Y26: 42488.331 | Z26: 0.92 | AB26: 0.36 | AD26: 0.56 | AE26: 0.15337673 | AF26: 0.084376735 | AG26: 0.043376735 | AH26: 0.014376735 | AI26: 0.29550694 | AJ26: 0.31303589 | AK26: 23793.465 | AL26: B- | AM26: 0.31B- | AN26: =_xlfn.CONCAT(_xlfn.IFS( AJ26>=0.7,"Superb", AJ26>=0.51,"Excellent", AJ26>=0.41,"Good", AJ26>=0.31,"Satisfactory", AJ26>=0.26,"Moderate", AJ26>=0.1,"Weak", AJ26<0.1,"Very Weak" ), " Economic Resilience with ",_xlfn.IFS( AK26<=2500,"Very Weak", AK26<=5000,"Poor", AK26<=10000,"Challenging", AK26<=12500,"Border Line", AK26<=15000,"Improved", AK26<=20000,"Moderate", AK26<=25000,"Satisfactory", AK26<=30000,"Good", AK26<=35000,"Very Good", AK26<=40000,"High", AK26<=50000,"Excellent", AK26<=100000,"Superb", AK26>100000,"Superb" ), " Affordability.") -> Satisfactory Economic Resilience with Satisfactory Affordability. | AP26: We will assume the 5 socio economic sector spending will increase by 5% every year, Socio Ecnomic Sectors are Health, Housing, Energy and Education. Based on this assumption we will predict the value of Heart next year
A27: =_xlfn.CONCAT(UPPER(B27),"|",C27) -> UNITED KINGDOM|2020 | B27: United Kingdom | C27: 2020 | D27: 84750000000000 | E27: -0.0336374 | F27: 7890000000 | G27: 0.010243278 | H27: 2720000000000 | I27: -0.055555556 | J27: 66744000 | K27: 0.0016959073 | L27: 0.032094395 | M27: 620700000000 | N27: 636000000000 | O27: 15300000000 | P27: 0.005625 | Q27: 0.845 | R27: 0.061557789 | S27: 2298400000000 | T27: 0.001 | U27: 2298400000 | V27: 0.000845 | W27: 0.01 | X27: 40752.727 | Y27: 40345.2 | Z27: 0.93 | AA27: 0.010869565 | AB27: 0.354 | AC27: -0.016949153 | AD27: 0.576 | AE27: 0.15726498 | AF27: 0.088264984 | AG27: 0.047264984 | AH27: 0.018264984 | AI27: 0.31105994 | AJ27: 0.34793433 | AK27: 23238.835 | AL27: B- | AM27: 0.35B- | AN27: =_xlfn.CONCAT(_xlfn.IFS( AJ27>=0.7,"Superb", AJ27>=0.51,"Excellent", AJ27>=0.41,"Good", AJ27>=0.31,"Satisfactory", AJ27>=0.26,"Moderate", AJ27>=0.1,"Weak", AJ27<0.1,"Very Weak" ), " Economic Resilience with ",_xlfn.IFS( AK27<=2500,"Very Weak", AK27<=5000,"Poor", AK27<=10000,"Challenging", AK27<=12500,"Border Line", AK27<=15000,"Improved", AK27<=20000,"Moderate", AK27<=25000,"Satisfactory", AK27<=30000,"Good", AK27<=35000,"Very Good", AK27<=40000,"High", AK27<=50000,"Excellent", AK27<=100000,"Superb", AK27>100000,"Superb" ), " Affordability.") -> Satisfactory Economic Resilience with Satisfactory Affordability. | AP27: We will assume the 5 socio economic sector spending will increase by 5% every year, Socio Ecnomic Sectors are Health, Housing, Energy and Education. Based on this assumption we will predict the value of Heart next year
A28: =_xlfn.CONCAT(UPPER(B28),"|",C28) -> UNITED KINGDOM|2021 | B28: United Kingdom | C28: 2021 | D28: 96140000000000 | E28: 0.13439528 | F28: 7950000000 | G28: 0.0076045627 | H28: 3190000000000 | I28: 0.17279412 | J28: 66984000 | K28: 0.0035958288 | L28: 0.033180778 | M28: 679400000000 | N28: 680300000000 | O28: 900000000 | P28: 0.00028213166 | Q28: 0.954 | R28: 0.12899408 | S28: 3043260000000 | T28: 0.0025 | U28: 7608150000 | V28: 0.002385 | W28: 0.025 | X28: 47623.313 | Y28: 46432.73 | Z28: 0.92 | AA28: -0.010752688 | AB28: 0.344 | AC28: -0.029069767 | AD28: 0.576 | AE28: 0.16135788 | AF28: 0.092357878 | AG28: 0.051357878 | AH28: 0.022357878 | AI28: 0.32743151 | AJ28: 0.35850942 | AK28: 26745.253 | AL28: B | AM28: 0.36B | AN28: =_xlfn.CONCAT(_xlfn.IFS( AJ28>=0.7,"Superb", AJ28>=0.51,"Excellent", AJ28>=0.41,"Good", AJ28>=0.31,"Satisfactory", AJ28>=0.26,"Moderate", AJ28>=0.1,"Weak", AJ28<0.1,"Very Weak" ), " Economic Resilience with ",_xlfn.IFS( AK28<=2500,"Very Weak", AK28<=5000,"Poor", AK28<=10000,"Challenging", AK28<=12500,"Border Line", AK28<=15000,"Improved", AK28<=20000,"Moderate", AK28<=25000,"Satisfactory", AK28<=30000,"Good", AK28<=35000,"Very Good", AK28<=40000,"High", AK28<=50000,"Excellent", AK28<=100000,"Superb", AK28>100000,"Superb" ), " Affordability.") -> Satisfactory Economic Resilience with Good Affordability. | AP28: We will assume the 5 socio economic sector spending will increase by 5% every year, Socio Ecnomic Sectors are Health, Housing, Energy and Education. Based on this assumption we will predict the value of Heart next year
A29: =_xlfn.CONCAT(UPPER(B29),"|",C29) -> UNITED KINGDOM|2022 | B29: United Kingdom | C29: 2022 | D29: 101560000000000 | E29: 0.056376118 | F29: 8020000000 | G29: 0.0088050314 | H29: 3180000000000 | I29: -0.0031347962 | J29: 67604000 | K29: 0.0092559417 | L29: 0.03131154 | M29: 906900000000 | N29: 879100000000 | O29: -27800000000 | P29: -0.0087421384 | Q29: 0.943 | R29: -0.011530398 | S29: 2998740000000 | T29: 0.01 | U29: 29987400000 | V29: 0.00943 | W29: 0.079 | X29: 47038.637 | Y29: 43322.584 | Z29: 0.94 | AA29: 0.02173913 | AB29: 0.355 | AC29: 0.030985915 | AD29: 0.585 | AE29: 0.16566619 | AF29: 0.096666188 | AG29: 0.055666187 | AH29: 0.026666188 | AI29: 0.34466475 | AJ29: 0.35780415 | AK29: 25343.712 | AL29: B | AM29: 0.36B | AN29: =_xlfn.CONCAT(_xlfn.IFS( AJ29>=0.7,"Superb", AJ29>=0.51,"Excellent", AJ29>=0.41,"Good", AJ29>=0.31,"Satisfactory", AJ29>=0.26,"Moderate", AJ29>=0.1,"Weak", AJ29<0.1,"Very Weak" ), " Economic Resilience with ",_xlfn.IFS( AK29<=2500,"Very Weak", AK29<=5000,"Poor", AK29<=10000,"Challenging", AK29<=12500,"Border Line", AK29<=15000,"Improved", AK29<=20000,"Moderate", AK29<=25000,"Satisfactory", AK29<=30000,"Good", AK29<=35000,"Very Good", AK29<=40000,"High", AK29<=50000,"Excellent", AK29<=100000,"Superb", AK29>100000,"Superb" ), " Affordability.") -> Satisfactory Economic Resilience with Good Affordability. | AP29: We will assume the 5 socio economic sector spending will increase by 5% every year, Socio Ecnomic Sectors are Health, Housing, Energy and Education. Based on this assumption we will predict the value of Heart next year
A30: =_xlfn.CONCAT(UPPER(B30),"|",C30) -> UNITED KINGDOM|2023 | B30: United Kingdom | C30: 2023 | D30: 106800000000000 | E30: 0.051595116 | F30: 8090000000 | G30: 0.0087281796 | H30: 3420000000000 | I30: 0.075471698 | J30: 68492000 | K30: 0.013135317 | L30: 0.032022472 | M30: 910400000000 | N30: 878300000000 | O30: -32100000000 | P30: -0.0093859649 | Q30: 0.932 | R30: -0.011664899 | S30: 3187440000000 | T30: 0.045 | U30: 143434800000 | V30: 0.04194 | W30: 0.068 | X30: 49932.839 | Y30: 46537.406 | Z30: 0.95 | AA30: 0.010638298 | AB30: 0.331 | AC30: -0.072507553 | AD30: 0.619 | AE30: 0.17020125 | AF30: 0.10120125 | AG30: 0.06020125 | AH30: 0.03120125 | AI30: 0.362805 | AJ30: 0.34350151 | AK30: 28806.654 | AL30: B | AM30: 0.34B | AN30: =_xlfn.CONCAT(_xlfn.IFS( AJ30>=0.7,"Superb", AJ30>=0.51,"Excellent", AJ30>=0.41,"Good", AJ30>=0.31,"Satisfactory", AJ30>=0.26,"Moderate", AJ30>=0.1,"Weak", AJ30<0.1,"Very Weak" ), " Economic Resilience with ",_xlfn.IFS( AK30<=2500,"Very Weak", AK30<=5000,"Poor", AK30<=10000,"Challenging", AK30<=12500,"Border Line", AK30<=15000,"Improved", AK30<=20000,"Moderate", AK30<=25000,"Satisfactory", AK30<=30000,"Good", AK30<=35000,"Very Good", AK30<=40000,"High", AK30<=50000,"Excellent", AK30<=100000,"Superb", AK30>100000,"Superb" ), " Affordability.") -> Satisfactory Economic Resilience with Good Affordability. | AP30: We will assume the 5 socio economic sector spending will increase by 5% every year, Socio Ecnomic Sectors are Health, Housing, Energy and Education. Based on this assumption we will predict the value of Heart next year
A31: =_xlfn.CONCAT(UPPER(B31),"|",C31) -> UNITED KINGDOM|2024 | B31: United Kingdom | C31: 2024 | D31: 112600000000000 | E31: 0.054307116 | F31: 8161972572 | G31: 0.008896486 | H31: 3686033040000 | I31: 0.077787439 | J31: 69226000 | K31: 0.01071658 | L31: 0.03273564 | M31: 918700000000 | N31: 893200000000 | O31: -25500000000 | P31: -0.0069180064 | Q31: 0.944 | R31: 0.012875536 | S31: 3479615189760 | T31: 0.05 | U31: 173980759488 | V31: 0.0472 | W31: 0.033 | X31: 53246.368 | Y31: 51489.237 | Z31: 0.948 | AA31: -0.0021052632 | AB31: 0.329 | AC31: -0.0060790274 | AD31: 0.619 | AE31: 0.174975 | AF31: 0.105975 | AG31: 0.064975 | AH31: 0.035975 | AI31: 0.3819 | AJ31: 0.36051763 | AK31: 31871.838 | AL31: B+ | AM31: 0.36B+ | AN31: =_xlfn.CONCAT(_xlfn.IFS( AJ31>=0.7,"Superb", AJ31>=0.51,"Excellent", AJ31>=0.41,"Good", AJ31>=0.31,"Satisfactory", AJ31>=0.26,"Moderate", AJ31>=0.1,"Weak", AJ31<0.1,"Very Weak" ), " Economic Resilience with ",_xlfn.IFS( AK31<=2500,"Very Weak", AK31<=5000,"Poor", AK31<=10000,"Challenging", AK31<=12500,"Border Line", AK31<=15000,"Improved", AK31<=20000,"Moderate", AK31<=25000,"Satisfactory", AK31<=30000,"Good", AK31<=35000,"Very Good", AK31<=40000,"High", AK31<=50000,"Excellent", AK31<=100000,"Superb", AK31>100000,"Superb" ), " Affordability.") -> Satisfactory Economic Resilience with Very Good Affordability. | AP31: We will assume the 5 socio economic sector spending will increase by 5% every year, Socio Ecnomic Sectors are Health, Housing, Energy and Education. Based on this assumption we will predict the value of Heart next year
A32: =_xlfn.CONCAT(UPPER(B32),"|",C32) -> UNITED KINGDOM|2025 | B32: United Kingdom | C32: 2025 | D32: 113795678000000 | E32: 0.01061881 | F32: 8231613070 | G32: 0.0085323122 | H32: 3839000000000 | I32: 0.041499075 | J32: 68300000 | K32: -0.013376477 | L32: 0.033735903 | M32: 959400000000 | N32: 928900000000 | O32: -30500000000 | P32: -0.0079447773 | Q32: 0.96 | R32: 0.016949153 | S32: 3685440000000 | T32: 0.0425 | U32: 156631200000 | V32: 0.0408 | W32: 0.034 | X32: 56207.906 | Y32: 54296.837 | Z32: 0.946 | AA32: -0.0021097046 | AB32: 0.354 | AC32: 0.070621469 | AD32: 0.592 | AE32: 0.18 | AF32: 0.111 | AG32: 0.07 | AH32: 0.041 | AI32: 0.402 | AJ32: 0.38699113 | AK32: 32143.728 | AL32: B+ | AM32: 0.39B+ | AN32: =_xlfn.CONCAT(_xlfn.IFS( AJ32>=0.7,"Superb", AJ32>=0.51,"Excellent", AJ32>=0.41,"Good", AJ32>=0.31,"Satisfactory", AJ32>=0.26,"Moderate", AJ32>=0.1,"Weak", AJ32<0.1,"Very Weak" ), " Economic Resilience with ",_xlfn.IFS( AK32<=2500,"Very Weak", AK32<=5000,"Poor", AK32<=10000,"Challenging", AK32<=12500,"Border Line", AK32<=15000,"Improved", AK32<=20000,"Moderate", AK32<=25000,"Satisfactory", AK32<=30000,"Good", AK32<=35000,"Very Good", AK32<=40000,"High", AK32<=50000,"Excellent", AK32<=100000,"Superb", AK32>100000,"Superb" ), " Affordability.") -> Satisfactory Economic Resilience with Very Good Affordability. | AO32: 6th largest per GDP. Facing economic growth and US tarrifs challenges.Political decision leaving EU did not go well economically as it restricted market access.Economic diversification needed. | AP32: We will assume the 5 socio economic sector spending will increase by 5% every year, Socio Ecnomic Sectors are Health, Housing, Energy and Education. Based on this assumption we will predict the value of Heart next year
A33: =_xlfn.CONCAT(UPPER(B33),"|",C33) -> UNITED KINGDOM|2026 | B33: United Kingdom | C33: 2026 | D33: 120063810405112 | E33: 0.055082342 | F33: 8302201675 | G33: 0.0085753064 | H33: 4015031459899 | I33: 0.045853467 | J33: 68968137 | K33: 0.0097823927 | L33: 0.033440813 | M33: 1029900000000 | N33: 993900000000 | O33: -36000000000 | P33: -0.0089663058 | Q33: 0.9987745 | R33: 0.040390105 | S33: 4010111043094 | T33: 0.057714286 | U33: 231440694487 | V33: 0.057643557 | W33: 0.058 | X33: 58215.744 | Y33: 54839.231 | Z33: 0.95365793 | AA33: 0.0080950591 | AB33: 0.34389298 | AC33: -0.029390003 | AD33: 0.60976494 | AE33: 0.185025 | AF33: 0.116025 | AG33: 0.075025 | AH33: 0.046025 | AI33: 0.4221 | AJ33: 0.38893095 | AK33: 33439.041 | AL33: B+ | AM33: 0.39B+ | AN33: =_xlfn.CONCAT(_xlfn.IFS( AJ33>=0.7,"Superb", AJ33>=0.51,"Excellent", AJ33>=0.41,"Good", AJ33>=0.31,"Satisfactory", AJ33>=0.26,"Moderate", AJ33>=0.1,"Weak", AJ33<0.1,"Very Weak" ), " Economic Resilience with ",_xlfn.IFS( AK33<=2500,"Very Weak", AK33<=5000,"Poor", AK33<=10000,"Challenging", AK33<=12500,"Border Line", AK33<=15000,"Improved", AK33<=20000,"Moderate", AK33<=25000,"Satisfactory", AK33<=30000,"Good", AK33<=35000,"Very Good", AK33<=40000,"High", AK33<=50000,"Excellent", AK33<=100000,"Superb", AK33>100000,"Superb" ), " Affordability.") -> Satisfactory Economic Resilience with Very Good Affordability. | AP33: We will assume the 5 socio economic sector spending will increase by 5% every year, Socio Ecnomic Sectors are Health, Housing, Energy and Education. Based on this assumption we will predict the value of Heart next year
A34: =_xlfn.CONCAT(UPPER(B34),"|",C34) -> UNITED KINGDOM|2027 | B34: United Kingdom | C34: 2027 | D34: 125735541889780 | E34: 0.047239309 | F34: 8372937901 | G34: 0.0085201769 | H34: 4201345719753 | I34: 0.046404184 | J34: 69440404 | K34: 0.0068476123 | L34: 0.033414146 | M34: 1082332142857 | N34: 1041853571429 | O34: -40478571429 | P34: -0.0096346681 | Q34: 1.029458 | R34: 0.030721182 | S34: 4325109107856 | T34: 0.066482143 | U34: 287542521581 | V34: 0.068440576 | W34: 0.063 | X34: 60502.898 | Y34: 56691.216 | Z34: 0.95950693 | AA34: 0.0061332258 | AB34: 0.33897217 | AC34: -0.014516858 | AD34: 0.62053475 | AE34: 0.19030125 | AF34: 0.12130125 | AG34: 0.08030125 | AH34: 0.05130125 | AI34: 0.443205 | AJ34: 0.3985439 | AK34: 35178.869 | AL34: A- | AM34: 0.4A- | AN34: =_xlfn.CONCAT(_xlfn.IFS( AJ34>=0.7,"Superb", AJ34>=0.51,"Excellent", AJ34>=0.41,"Good", AJ34>=0.31,"Satisfactory", AJ34>=0.26,"Moderate", AJ34>=0.1,"Weak", AJ34<0.1,"Very Weak" ), " Economic Resilience with ",_xlfn.IFS( AK34<=2500,"Very Weak", AK34<=5000,"Poor", AK34<=10000,"Challenging", AK34<=12500,"Border Line", AK34<=15000,"Improved", AK34<=20000,"Moderate", AK34<=25000,"Satisfactory", AK34<=30000,"Good", AK34<=35000,"Very Good", AK34<=40000,"High", AK34<=50000,"Excellent", AK34<=100000,"Superb", AK34>100000,"Superb" ), " Affordability.") -> Satisfactory Economic Resilience with High Affordability. | AP34: We will assume the 5 socio economic sector spending will increase by 5% every year, Socio Ecnomic Sectors are Health, Housing, Energy and Education. Based on this assumption we will predict the value of Heart next year
A35: =_xlfn.CONCAT(UPPER(B35),"|",C35) -> UNITED KINGDOM|2028 | B35: United Kingdom | C35: 2028 | D35: 131237442252096 | E35: 0.043757718 | F35: 8443822776 | G35: 0.0084659502 | H35: 4392794551938 | I35: 0.045568455 | J35: 69846120 | K35: 0.0058426468 | L35: 0.033472113 | M35: 1134764285714 | N35: 1089807142857 | O35: -44957142857 | P35: -0.010234292 | Q35: 1.0574551 | R35: 0.027195937 | S35: 4645183049143 | T35: 0.07525 | U35: 349550024448 | V35: 0.079573497 | W35: 0.068 | X35: 62892.463 | Y35: 58615.776 | Z35: 0.96474239 | AA35: 0.005456407 | AB35: 0.33582093 | AC35: -0.0093837146 | AD35: 0.62892146 | AE35: 0.19584131 | AF35: 0.12684131 | AG35: 0.085841313 | AH35: 0.056841312 | AI35: 0.46536525 | AJ35: 0.40902957 | AK35: 36864.719 | AL35: A- | AM35: 0.41A- | AN35: =_xlfn.CONCAT(_xlfn.IFS( AJ35>=0.7,"Superb", AJ35>=0.51,"Excellent", AJ35>=0.41,"Good", AJ35>=0.31,"Satisfactory", AJ35>=0.26,"Moderate", AJ35>=0.1,"Weak", AJ35<0.1,"Very Weak" ), " Economic Resilience with ",_xlfn.IFS( AK35<=2500,"Very Weak", AK35<=5000,"Poor", AK35<=10000,"Challenging", AK35<=12500,"Border Line", AK35<=15000,"Improved", AK35<=20000,"Moderate", AK35<=25000,"Satisfactory", AK35<=30000,"Good", AK35<=35000,"Very Good", AK35<=40000,"High", AK35<=50000,"Excellent", AK35<=100000,"Superb", AK35>100000,"Superb" ), " Affordability.") -> Satisfactory Economic Resilience with High Affordability. | AP35: We will assume the 5 socio economic sector spending will increase by 5% every year, Socio Ecnomic Sectors are Health, Housing, Energy and Education. Based on this assumption we will predict the value of Heart next year
A36: =_xlfn.CONCAT(UPPER(B36),"|",C36) -> UNITED KINGDOM|2029 | B36: United Kingdom | C36: 2029 | D36: 136712479650225 | E36: 0.041718562 | F36: 8514849364 | G36: 0.0084116625 | H36: 4587498480202 | I36: 0.044323477 | J36: 70228370 | K36: 0.0054727353 | L36: 0.033555814 | M36: 1187196428571 | N36: 1137760714286 | O36: -49435714286 | P36: -0.010776181 | Q36: 1.0845907 | R36: 0.025661248 | S36: 4975558318685 | T36: 0.084017857 | U36: 418035748025 | V36: 0.091124989 | W36: 0.073 | X36: 65322.583 | Y36: 60554.034 | Z36: 0.9697626 | AA36: 0.0052036832 | AB36: 0.33329911 | AC36: -0.0075662193 | AD36: 0.63646349 | AE36: 0.20165838 | AF36: 0.13265838 | AG36: 0.091658378 | AH36: 0.062658378 | AI36: 0.48863351 | AJ36: 0.42028816 | AK36: 38540.432 | AL36: A- | AM36: 0.42A- | AN36: =_xlfn.CONCAT(_xlfn.IFS( AJ36>=0.7,"Superb", AJ36>=0.51,"Excellent", AJ36>=0.41,"Good", AJ36>=0.31,"Satisfactory", AJ36>=0.26,"Moderate", AJ36>=0.1,"Weak", AJ36<0.1,"Very Weak" ), " Economic Resilience with ",_xlfn.IFS( AK36<=2500,"Very Weak", AK36<=5000,"Poor", AK36<=10000,"Challenging", AK36<=12500,"Border Line", AK36<=15000,"Improved", AK36<=20000,"Moderate", AK36<=25000,"Satisfactory", AK36<=30000,"Good", AK36<=35000,"Very Good", AK36<=40000,"High", AK36<=50000,"Excellent", AK36<=100000,"Superb", AK36>100000,"Superb" ), " Affordability.") -> Good Economic Resilience with High Affordability. | AP36: We will assume the 5 socio economic sector spending will increase by 5% every year, Socio Ecnomic Sectors are Health, Housing, Energy and Education. Based on this assumption we will predict the value of Heart next year
A37: =_xlfn.CONCAT(UPPER(B37),"|",C37) -> UNITED KINGDOM|2030 | B37: United Kingdom | C37: 2030 | D37: 141834754671550 | F37: 8586617399 | H37: 4781569921881 | J37: 70606569 | L37: 0.033712259 | M37: 1239628571429 | N37: 1185714285714 | O37: -53914285714 | P37: -0.011275436 | Q37: 1.1115065 | S37: 5314745903260 | T37: 0.092785714 | U37: 493132494881 | V37: 0.10313192 | W37: 0.078 | X37: 67721.318 | Y37: 62439.055 | Z37: 0.97470664 | AB37: 0.33101004 | AD37: 0.6436966 | AE37: 0.2077663 | AF37: 0.1387663 | AG37: 0.097766297 | AH37: 0.068766297 | AI37: 0.51306519 | AJ37: 0.43237009 | AK37: 40191.808 | AL37: A | AM37: 0.43A | AN37: =_xlfn.CONCAT(_xlfn.IFS( AJ37>=0.7,"Superb", AJ37>=0.51,"Excellent", AJ37>=0.41,"Good", AJ37>=0.31,"Satisfactory", AJ37>=0.26,"Moderate", AJ37>=0.1,"Weak", AJ37<0.1,"Very Weak" ), " Economic Resilience with ",_xlfn.IFS( AK37<=2500,"Very Weak", AK37<=5000,"Poor", AK37<=10000,"Challenging", AK37<=12500,"Border Line", AK37<=15000,"Improved", AK37<=20000,"Moderate", AK37<=25000,"Satisfactory", AK37<=30000,"Good", AK37<=35000,"Very Good", AK37<=40000,"High", AK37<=50000,"Excellent", AK37<=100000,"Superb", AK37>100000,"Superb" ), " Affordability.") -> Good Economic Resilience with Excellent Affordability. | AP37: We will assume the 5 socio economic sector spending will increase by 5% every year, Socio Ecnomic Sectors are Health, Housing, Energy and Education. Based on this assumption we will predict the value of Heart next year
A38: =_xlfn.CONCAT(UPPER(B38),"|",C38) -> JAPAN|2019 | B38: Japan | C38: 2019 | D38: 87700000000000 | F38: 7810000000 | H38: 5120000000000 | J38: 126633000 | L38: 0.058380844 | M38: 908590000000 | N38: 893780000000 | O38: -14810000000 | P38: -0.0028925781 | Q38: 1.9746 | S38: 10109952000000 | T38: -0.001 | U38: -10109952000 | V38: -0.0019746 | W38: 0.005 | X38: 40431.799 | Y38: 40229.64 | Z38: 0.918 | AB38: 0.33 | AD38: 0.588 | AE38: 0.084436367 | AF38: 0.094436367 | AG38: 0.077436367 | AH38: 0.027436367 | AI38: 0.28374547 | AJ38: 0.34120834 | AK38: 23655.028 | AL38: B- | AM38: 0.34B- | AN38: =_xlfn.CONCAT(_xlfn.IFS( AJ38>=0.7,"Superb", AJ38>=0.51,"Excellent", AJ38>=0.41,"Good", AJ38>=0.31,"Satisfactory", AJ38>=0.26,"Moderate", AJ38>=0.1,"Weak", AJ38<0.1,"Very Weak" ), " Economic Resilience with ",_xlfn.IFS( AK38<=2500,"Very Weak", AK38<=5000,"Poor", AK38<=10000,"Challenging", AK38<=12500,"Border Line", AK38<=15000,"Improved", AK38<=20000,"Moderate", AK38<=25000,"Satisfactory", AK38<=30000,"Good", AK38<=35000,"Very Good", AK38<=40000,"High", AK38<=50000,"Excellent", AK38<=100000,"Superb", AK38>100000,"Superb" ), " Affordability.") -> Satisfactory Economic Resilience with Satisfactory Affordability. | AP38: We will assume the 5 socio economic sector spending will increase by 5% every year, Socio Ecnomic Sectors are Health, Housing, Energy and Education. Based on this assumption we will predict the value of Heart next year
A39: =_xlfn.CONCAT(UPPER(B39),"|",C39) -> JAPAN|2020 | B39: Japan | C39: 2020 | D39: 84750000000000 | E39: -0.0336374 | F39: 7890000000 | G39: 0.010243278 | H39: 5050000000000 | I39: -0.013671875 | J39: 126261000 | K39: -0.0029376229 | L39: 0.059587021 | M39: 798650000000 | N39: 785060000000 | O39: -13590000000 | P39: -0.0026910891 | Q39: 2.0556 | R39: 0.041020966 | S39: 10380780000000 | T39: -0.001 | U39: -10380780000 | V39: -0.0020556 | W39: 0.0015 | X39: 39996.515 | Y39: 39936.52 | Z39: 0.917 | AA39: -0.0010893246 | AB39: 0.323 | AC39: -0.021671827 | AD39: 0.594 | AE39: 0.08816986 | AF39: 0.09816986 | AG39: 0.08116986 | AH39: 0.03116986 | AI39: 0.29867944 | AJ39: 0.35763097 | AK39: 23722.293 | AL39: B- | AM39: 0.36B- | AN39: =_xlfn.CONCAT(_xlfn.IFS( AJ39>=0.7,"Superb", AJ39>=0.51,"Excellent", AJ39>=0.41,"Good", AJ39>=0.31,"Satisfactory", AJ39>=0.26,"Moderate", AJ39>=0.1,"Weak", AJ39<0.1,"Very Weak" ), " Economic Resilience with ",_xlfn.IFS( AK39<=2500,"Very Weak", AK39<=5000,"Poor", AK39<=10000,"Challenging", AK39<=12500,"Border Line", AK39<=15000,"Improved", AK39<=20000,"Moderate", AK39<=25000,"Satisfactory", AK39<=30000,"Good", AK39<=35000,"Very Good", AK39<=40000,"High", AK39<=50000,"Excellent", AK39<=100000,"Superb", AK39>100000,"Superb" ), " Affordability.") -> Satisfactory Economic Resilience with Satisfactory Affordability. | AP39: We will assume the 5 socio economic sector spending will increase by 5% every year, Socio Ecnomic Sectors are Health, Housing, Energy and Education. Based on this assumption we will predict the value of Heart next year
A40: =_xlfn.CONCAT(UPPER(B40),"|",C40) -> JAPAN|2021 | B40: Japan | C40: 2021 | D40: 96140000000000 | E40: 0.13439528 | F40: 7950000000 | G40: 0.0076045627 | H40: 5040000000000 | I40: -0.001980198 | J40: 125681593 | K40: -0.0045889625 | L40: 0.052423549 | M40: 938760000000 | N40: 912550000000 | O40: -26210000000 | P40: -0.0052003968 | Q40: 2.1413 | R40: 0.04169099 | S40: 10792152000000 | T40: -0.001 | U40: -10792152000 | V40: -0.0021413 | W40: -0.002 | X40: 40101.338 | Y40: 40181.54 | Z40: 0.92 | AA40: 0.0032715376 | AB40: 0.3075 | AC40: -0.050406504 | AD40: 0.6125 | AE40: 0.092099853 | AF40: 0.10209985 | AG40: 0.085099853 | AH40: 0.035099853 | AI40: 0.31439941 | AJ40: 0.36376386 | AK40: 24611.193 | AL40: B- | AM40: 0.36B- | AN40: =_xlfn.CONCAT(_xlfn.IFS( AJ40>=0.7,"Superb", AJ40>=0.51,"Excellent", AJ40>=0.41,"Good", AJ40>=0.31,"Satisfactory", AJ40>=0.26,"Moderate", AJ40>=0.1,"Weak", AJ40<0.1,"Very Weak" ), " Economic Resilience with ",_xlfn.IFS( AK40<=2500,"Very Weak", AK40<=5000,"Poor", AK40<=10000,"Challenging", AK40<=12500,"Border Line", AK40<=15000,"Improved", AK40<=20000,"Moderate", AK40<=25000,"Satisfactory", AK40<=30000,"Good", AK40<=35000,"Very Good", AK40<=40000,"High", AK40<=50000,"Excellent", AK40<=100000,"Superb", AK40>100000,"Superb" ), " Affordability.") -> Satisfactory Economic Resilience with Satisfactory Affordability. | AP40: We will assume the 5 socio economic sector spending will increase by 5% every year, Socio Ecnomic Sectors are Health, Housing, Energy and Education. Based on this assumption we will predict the value of Heart next year
A41: =_xlfn.CONCAT(UPPER(B41),"|",C41) -> JAPAN|2022 | B41: Japan | C41: 2022 | D41: 101560000000000 | E41: 0.056376118 | F41: 8020000000 | G41: 0.0088050314 | H41: 4260000000000 | I41: -0.1547619 | J41: 125124989 | K41: -0.0044286835 | L41: 0.041945648 | M41: 1077000000000 | N41: 918410000000 | O41: -158590000000 | P41: -0.0372277 | Q41: 2.1477 | R41: 0.0029888386 | S41: 9149202000000 | T41: -0.001 | U41: -9149202000 | V41: -0.0021477 | W41: 0.025 | X41: 34045.957 | Y41: 33194.808 | Z41: 0.92 | AA41: 0 | AB41: 0.29975 | AC41: -0.025854879 | AD41: 0.62025 | AE41: 0.096236688 | AF41: 0.10623669 | AG41: 0.089236687 | AH41: 0.039236687 | AI41: 0.33094675 | AJ41: 0.3378124 | AK41: 20589.08 | AL41: B- | AM41: 0.34B- | AN41: =_xlfn.CONCAT(_xlfn.IFS( AJ41>=0.7,"Superb", AJ41>=0.51,"Excellent", AJ41>=0.41,"Good", AJ41>=0.31,"Satisfactory", AJ41>=0.26,"Moderate", AJ41>=0.1,"Weak", AJ41<0.1,"Very Weak" ), " Economic Resilience with ",_xlfn.IFS( AK41<=2500,"Very Weak", AK41<=5000,"Poor", AK41<=10000,"Challenging", AK41<=12500,"Border Line", AK41<=15000,"Improved", AK41<=20000,"Moderate", AK41<=25000,"Satisfactory", AK41<=30000,"Good", AK41<=35000,"Very Good", AK41<=40000,"High", AK41<=50000,"Excellent", AK41<=100000,"Superb", AK41>100000,"Superb" ), " Affordability.") -> Satisfactory Economic Resilience with Satisfactory Affordability. | AP41: We will assume the 5 socio economic sector spending will increase by 5% every year, Socio Ecnomic Sectors are Health, Housing, Energy and Education. Based on this assumption we will predict the value of Heart next year
A42: =_xlfn.CONCAT(UPPER(B42),"|",C42) -> JAPAN|2023 | B42: Japan | C42: 2023 | D42: 106800000000000 | E42: 0.051595116 | F42: 8090000000 | G42: 0.0087281796 | H42: 4210000000000 | I42: -0.011737089 | J42: 124516650 | K42: -0.0048618506 | L42: 0.039419476 | M42: 981840000000 | N42: 920640000000 | O42: -61200000000 | P42: -0.014536817 | Q42: 2.0565 | R42: -0.042464031 | S42: 8657865000000 | T42: -0.001 | U42: -8657865000 | V42: -0.0020565 | W42: 0.033 | X42: 33810.739 | Y42: 32694.985 | Z42: 0.93 | AA42: 0.010869565 | AB42: 0.295875 | AC42: -0.013096747 | AD42: 0.634125 | AE42: 0.10059125 | AF42: 0.11059125 | AG42: 0.09359125 | AH42: 0.04359125 | AI42: 0.348365 | AJ42: 0.37530416 | AK42: 20732.707 | AL42: B- | AM42: 0.38B- | AN42: =_xlfn.CONCAT(_xlfn.IFS( AJ42>=0.7,"Superb", AJ42>=0.51,"Excellent", AJ42>=0.41,"Good", AJ42>=0.31,"Satisfactory", AJ42>=0.26,"Moderate", AJ42>=0.1,"Weak", AJ42<0.1,"Very Weak" ), " Economic Resilience with ",_xlfn.IFS( AK42<=2500,"Very Weak", AK42<=5000,"Poor", AK42<=10000,"Challenging", AK42<=12500,"Border Line", AK42<=15000,"Improved", AK42<=20000,"Moderate", AK42<=25000,"Satisfactory", AK42<=30000,"Good", AK42<=35000,"Very Good", AK42<=40000,"High", AK42<=50000,"Excellent", AK42<=100000,"Superb", AK42>100000,"Superb" ), " Affordability.") -> Satisfactory Economic Resilience with Satisfactory Affordability. | AP42: We will assume the 5 socio economic sector spending will increase by 5% every year, Socio Ecnomic Sectors are Health, Housing, Energy and Education. Based on this assumption we will predict the value of Heart next year
A43: =_xlfn.CONCAT(UPPER(B43),"|",C43) -> JAPAN|2024 | B43: Japan | C43: 2024 | D43: 112600000000000 | E43: 0.054307116 | F43: 8161972572 | G43: 0.008896486 | H43: 4030000000000 | I43: -0.042755344 | J43: 122631432 | K43: -0.015140288 | L43: 0.035790409 | M43: 952040000000 | N43: 917040000000 | O43: -35000000000 | P43: -0.0086848635 | Q43: 2.0093 | R43: -0.022951617 | S43: 8097479000000 | T43: 0.001 | U43: 8097479000 | V43: 0.0020093 | W43: 0.027 | X43: 32862.7 | Y43: 31975.407 | Z43: 0.9345 | AA43: 0.0048387097 | AB43: 0.2939375 | AC43: -0.0065915373 | AD43: 0.6405625 | AE43: 0.105175 | AF43: 0.115175 | AG43: 0.098175 | AH43: 0.048175 | AI43: 0.3667 | AJ43: 0.39179624 | AK43: 20482.247 | AL43: B- | AM43: 0.39B- | AN43: =_xlfn.CONCAT(_xlfn.IFS( AJ43>=0.7,"Superb", AJ43>=0.51,"Excellent", AJ43>=0.41,"Good", AJ43>=0.31,"Satisfactory", AJ43>=0.26,"Moderate", AJ43>=0.1,"Weak", AJ43<0.1,"Very Weak" ), " Economic Resilience with ",_xlfn.IFS( AK43<=2500,"Very Weak", AK43<=5000,"Poor", AK43<=10000,"Challenging", AK43<=12500,"Border Line", AK43<=15000,"Improved", AK43<=20000,"Moderate", AK43<=25000,"Satisfactory", AK43<=30000,"Good", AK43<=35000,"Very Good", AK43<=40000,"High", AK43<=50000,"Excellent", AK43<=100000,"Superb", AK43>100000,"Superb" ), " Affordability.") -> Satisfactory Economic Resilience with Satisfactory Affordability. | AP43: We will assume the 5 socio economic sector spending will increase by 5% every year, Socio Ecnomic Sectors are Health, Housing, Energy and Education. Based on this assumption we will predict the value of Heart next year
A44: =_xlfn.CONCAT(UPPER(B44),"|",C44) -> JAPAN|2025 | B44: Japan | C44: 2025 | D44: 113795678000000 | E44: 0.01061881 | F44: 8231613070 | G44: 0.0085323122 | H44: 4186000000000 | I44: 0.038709677 | J44: 123400000 | K44: 0.0062673002 | L44: 0.036785228 | M44: 1385000000000 | N44: 1377000000000 | O44: -8000000000 | P44: -0.0019111323 | Q44: 0.42 | R44: -0.79097198 | S44: 1758120000000 | T44: 0.0275 | U44: 48348300000 | V44: 0.01155 | W44: 0.017 | X44: 33922.204 | Y44: 33345.527 | Z44: 0.939 | AA44: 0.0048154093 | AB44: 0.292 | AC44: -0.006635274 | AD44: 0.647 | AE44: 0.11 | AF44: 0.12 | AG44: 0.103 | AH44: 0.053 | AI44: 0.386 | AJ44: 0.4093241 | AK44: 21574.556 | AL44: B- | AM44: 0.41B- | AN44: =_xlfn.CONCAT(_xlfn.IFS( AJ44>=0.7,"Superb", AJ44>=0.51,"Excellent", AJ44>=0.41,"Good", AJ44>=0.31,"Satisfactory", AJ44>=0.26,"Moderate", AJ44>=0.1,"Weak", AJ44<0.1,"Very Weak" ), " Economic Resilience with ",_xlfn.IFS( AK44<=2500,"Very Weak", AK44<=5000,"Poor", AK44<=10000,"Challenging", AK44<=12500,"Border Line", AK44<=15000,"Improved", AK44<=20000,"Moderate", AK44<=25000,"Satisfactory", AK44<=30000,"Good", AK44<=35000,"Very Good", AK44<=40000,"High", AK44<=50000,"Excellent", AK44<=100000,"Superb", AK44>100000,"Superb" ), " Affordability.") -> Satisfactory Economic Resilience with Satisfactory Affordability. | AO44: 5th largest per GDP. Facing growth,ageing population and US threat challenges. | AP44: We will assume the 5 socio economic sector spending will increase by 5% every year, Socio Ecnomic Sectors are Health, Housing, Energy and Education. Based on this assumption we will predict the value of Heart next year
A45: =_xlfn.CONCAT(UPPER(B45),"|",C45) -> JAPAN|2026 | B45: Japan | C45: 2026 | D45: 120063810405112 | E45: 0.055082342 | F45: 8302201675 | G45: 0.0085753064 | H45: 3901191229772 | I45: -0.068038407 | J45: 1.2258765e+08 | K45: -0.006583083 | L45: 0.032492649 | M45: 1260138571429 | N45: 1206598571429 | O45: -53540000000 | P45: -0.013724013 | Q45: 0.75186882 | R45: 0.79016385 | S45: 2933184038658 | T45: 0.016142857 | U45: 47349970910 | V45: 0.012137311 | W45: 0.032642857 | X45: 31823.689 | Y45: 30784.873 | Z45: 0.94174102 | AA45: 0.0029190864 | AB45: 0.28285588 | AC45: -0.032327831 | AD45: 0.65888514 | AE45: 0.114825 | AF45: 0.124825 | AG45: 0.107825 | AH45: 0.057825 | AI45: 0.4053 | AJ45: 0.41193132 | AK45: 20283.696 | AL45: B- | AM45: 0.41B- | AN45: =_xlfn.CONCAT(_xlfn.IFS( AJ45>=0.7,"Superb", AJ45>=0.51,"Excellent", AJ45>=0.41,"Good", AJ45>=0.31,"Satisfactory", AJ45>=0.26,"Moderate", AJ45>=0.1,"Weak", AJ45<0.1,"Very Weak" ), " Economic Resilience with ",_xlfn.IFS( AK45<=2500,"Very Weak", AK45<=5000,"Poor", AK45<=10000,"Challenging", AK45<=12500,"Border Line", AK45<=15000,"Improved", AK45<=20000,"Moderate", AK45<=25000,"Satisfactory", AK45<=30000,"Good", AK45<=35000,"Very Good", AK45<=40000,"High", AK45<=50000,"Excellent", AK45<=100000,"Superb", AK45>100000,"Superb" ), " Affordability.") -> Good Economic Resilience with Satisfactory Affordability. | AP45: We will assume the 5 socio economic sector spending will increase by 5% every year, Socio Ecnomic Sectors are Health, Housing, Energy and Education. Based on this assumption we will predict the value of Heart next year
A46: =_xlfn.CONCAT(UPPER(B46),"|",C46) -> JAPAN|2027 | B46: Japan | C46: 2027 | D46: 125735541889780 | E46: 0.047239309 | F46: 8372937901 | G46: 0.0085201769 | H46: 3690334857977 | I46: -0.054049227 | J46: 1.2191043e+08 | K46: -0.0055243496 | L46: 0.029349974 | M46: 1323677500000 | N46: 1268088214286 | O46: -55589285714 | P46: -0.01506348 | Q46: 0.76291905 | R46: 0.014697026 | S46: 2815426777805 | T46: 0.019339286 | U46: 54448342864 | V46: 0.01475431 | W46: 0.037 | X46: 30270.871 | Y46: 29150.848 | Z46: 0.9451902 | AA46: 0.0036625569 | AB46: 0.27563676 | AC46: -0.02619071 | AD46: 0.66955344 | AE46: 0.11989125 | AF46: 0.12989125 | AG46: 0.11289125 | AH46: 0.06289125 | AI46: 0.425565 | AJ46: 0.42509718 | AK46: 19518.051 | AL46: C+ | AM46: 0.43C+ | AN46: =_xlfn.CONCAT(_xlfn.IFS( AJ46>=0.7,"Superb", AJ46>=0.51,"Excellent", AJ46>=0.41,"Good", AJ46>=0.31,"Satisfactory", AJ46>=0.26,"Moderate", AJ46>=0.1,"Weak", AJ46<0.1,"Very Weak" ), " Economic Resilience with ",_xlfn.IFS( AK46<=2500,"Very Weak", AK46<=5000,"Poor", AK46<=10000,"Challenging", AK46<=12500,"Border Line", AK46<=15000,"Improved", AK46<=20000,"Moderate", AK46<=25000,"Satisfactory", AK46<=30000,"Good", AK46<=35000,"Very Good", AK46<=40000,"High", AK46<=50000,"Excellent", AK46<=100000,"Superb", AK46>100000,"Superb" ), " Affordability.") -> Good Economic Resilience with Moderate Affordability. | AP46: We will assume the 5 socio economic sector spending will increase by 5% every year, Socio Ecnomic Sectors are Health, Housing, Energy and Education. Based on this assumption we will predict the value of Heart next year
A47: =_xlfn.CONCAT(UPPER(B47),"|",C47) -> JAPAN|2028 | B47: Japan | C47: 2028 | D47: 131237442252096 | E47: 0.043757718 | F47: 8443822776 | G47: 0.0084659502 | H47: 3505185724021 | I47: -0.050171364 | J47: 1.2127952e+08 | K47: -0.005175177 | L47: 0.026708732 | M47: 1387216428571 | N47: 1329577857143 | O47: -57638571429 | P47: -0.0164438 | Q47: 0.66451124 | R47: -0.12898853 | S47: 2329235325767 | T47: 0.022535714 | U47: 52490981806 | V47: 0.014975236 | W47: 0.041357143 | X47: 28901.711 | Y47: 27706.419 | Z47: 0.94888325 | AA47: 0.0039072027 | AB47: 0.26908809 | AC47: -0.024336537 | AD47: 0.67979516 | AE47: 0.12521081 | AF47: 0.13521081 | AG47: 0.11821081 | AH47: 0.068210812 | AI47: 0.44684325 | AJ47: 0.44213295 | AK47: 18834.69 | AL47: C+ | AM47: 0.44C+ | AN47: =_xlfn.CONCAT(_xlfn.IFS( AJ47>=0.7,"Superb", AJ47>=0.51,"Excellent", AJ47>=0.41,"Good", AJ47>=0.31,"Satisfactory", AJ47>=0.26,"Moderate", AJ47>=0.1,"Weak", AJ47<0.1,"Very Weak" ), " Economic Resilience with ",_xlfn.IFS( AK47<=2500,"Very Weak", AK47<=5000,"Poor", AK47<=10000,"Challenging", AK47<=12500,"Border Line", AK47<=15000,"Improved", AK47<=20000,"Moderate", AK47<=25000,"Satisfactory", AK47<=30000,"Good", AK47<=35000,"Very Good", AK47<=40000,"High", AK47<=50000,"Excellent", AK47<=100000,"Superb", AK47>100000,"Superb" ), " Affordability.") -> Good Economic Resilience with Moderate Affordability. | AP47: We will assume the 5 socio economic sector spending will increase by 5% every year, Socio Ecnomic Sectors are Health, Housing, Energy and Education. Based on this assumption we will predict the value of Heart next year
A48: =_xlfn.CONCAT(UPPER(B48),"|",C48) -> JAPAN|2029 | B48: Japan | C48: 2029 | D48: 136712479650225 | E48: 0.041718562 | F48: 8514849364 | G48: 0.0084116625 | H48: 3329974985170 | I48: -0.04998615 | J48: 1.2066545e+08 | K48: -0.0050632958 | L48: 0.024357506 | M48: 1450755357143 | N48: 1391067500000 | O48: -59687857143 | P48: -0.017924416 | Q48: 0.52768659 | R48: -0.20590268 | S48: 1757183160425 | T48: 0.025732143 | U48: 45216088110 | V48: 0.013578507 | W48: 0.045714286 | X48: 27596.756 | Y48: 26335.19 | Z48: 0.95266533 | AA48: 0.003985822 | AB48: 0.26279405 | AC48: -0.023950442 | AD48: 0.68987128 | AE48: 0.13079635 | AF48: 0.14079635 | AG48: 0.12379635 | AH48: 0.073796353 | AI48: 0.46918541 | AJ48: 0.46204 | AK48: 18167.891 | AL48: C+ | AM48: 0.46C+ | AN48: =_xlfn.CONCAT(_xlfn.IFS( AJ48>=0.7,"Superb", AJ48>=0.51,"Excellent", AJ48>=0.41,"Good", AJ48>=0.31,"Satisfactory", AJ48>=0.26,"Moderate", AJ48>=0.1,"Weak", AJ48<0.1,"Very Weak" ), " Economic Resilience with ",_xlfn.IFS( AK48<=2500,"Very Weak", AK48<=5000,"Poor", AK48<=10000,"Challenging", AK48<=12500,"Border Line", AK48<=15000,"Improved", AK48<=20000,"Moderate", AK48<=25000,"Satisfactory", AK48<=30000,"Good", AK48<=35000,"Very Good", AK48<=40000,"High", AK48<=50000,"Excellent", AK48<=100000,"Superb", AK48>100000,"Superb" ), " Affordability.") -> Good Economic Resilience with Moderate Affordability. | AP48: We will assume the 5 socio economic sector spending will increase by 5% every year, Socio Ecnomic Sectors are Health, Housing, Energy and Education. Based on this assumption we will predict the value of Heart next year
A49: =_xlfn.CONCAT(UPPER(B49),"|",C49) -> JAPAN|2030 | B49: Japan | C49: 2030 | D49: 141834754671550 | F49: 8586617399 | H49: 3163692913291 | J49: 1.2003582e+08 | L49: 0.022305484 | M49: 1514294285714 | N49: 1452557142857 | O49: -61737142857 | P49: -0.019514265 | Q49: 0.37839314 | S49: 1197119689323 | T49: 0.028928571 | U49: 34630962441 | V49: 0.010946373 | W49: 0.050071429 | X49: 26356.24 | Y49: 25036.546 | Z49: 0.95648221 | AB49: 0.25660999 | AD49: 0.69987222 | AE49: 0.13666117 | AF49: 0.14666117 | AG49: 0.12966117 | AH49: 0.079661171 | AI49: 0.49264468 | AJ49: 0.48448953 | AK49: 17522.383 | AL49: C+ | AM49: 0.48C+ | AN49: =_xlfn.CONCAT(_xlfn.IFS( AJ49>=0.7,"Superb", AJ49>=0.51,"Excellent", AJ49>=0.41,"Good", AJ49>=0.31,"Satisfactory", AJ49>=0.26,"Moderate", AJ49>=0.1,"Weak", AJ49<0.1,"Very Weak" ), " Economic Resilience with ",_xlfn.IFS( AK49<=2500,"Very Weak", AK49<=5000,"Poor", AK49<=10000,"Challenging", AK49<=12500,"Border Line", AK49<=15000,"Improved", AK49<=20000,"Moderate", AK49<=25000,"Satisfactory", AK49<=30000,"Good", AK49<=35000,"Very Good", AK49<=40000,"High", AK49<=50000,"Excellent", AK49<=100000,"Superb", AK49>100000,"Superb" ), " Affordability.") -> Good Economic Resilience with Moderate Affordability. | AP49: We will assume the 5 socio economic sector spending will increase by 5% every year, Socio Ecnomic Sectors are Health, Housing, Energy and Education. Based on this assumption we will predict the value of Heart next year
A50: =_xlfn.CONCAT(UPPER(B50),"|",C50) -> CHINA|2019 | B50: China | C50: 2019 | D50: 87700000000000 | F50: 7810000000 | H50: 14560000000000 | J50: 1410000000 | L50: 0.16602052 | M50: 2500000000000 | N50: 2630000000000 | O50: 130000000000 | P50: 0.0089285714 | Q50: 0.594 | S50: 8648640000000 | T50: 0.0415 | U50: 358918560000 | V50: 0.024651 | W50: 0.029 | X50: 10326.241 | Y50: 10026.78 | Z50: 0.76 | AB50: 0.382 | AD50: 0.378 | AE50: 0.28470099 | AF50: 0.034700994 | AG50: 0.067700994 | AH50: 0.0047009944 | AI50: 0.39180398 | AJ50: 0.54210207 | AK50: 3790.1229 | AL50: D | AM50: 0.54D | AN50: =_xlfn.CONCAT(_xlfn.IFS( AJ50>=0.7,"Superb", AJ50>=0.51,"Excellent", AJ50>=0.41,"Good", AJ50>=0.31,"Satisfactory", AJ50>=0.26,"Moderate", AJ50>=0.1,"Weak", AJ50<0.1,"Very Weak" ), " Economic Resilience with ",_xlfn.IFS( AK50<=2500,"Very Weak", AK50<=5000,"Poor", AK50<=10000,"Challenging", AK50<=12500,"Border Line", AK50<=15000,"Improved", AK50<=20000,"Moderate", AK50<=25000,"Satisfactory", AK50<=30000,"Good", AK50<=35000,"Very Good", AK50<=40000,"High", AK50<=50000,"Excellent", AK50<=100000,"Superb", AK50>100000,"Superb" ), " Affordability.") -> Excellent Economic Resilience with Poor Affordability. | AP50: We will assume the 5 socio economic sector spending will increase by 5% every year, Socio Ecnomic Sectors are Health, Housing, Energy and Education. Based on this assumption we will predict the value of Heart next year
A51: =_xlfn.CONCAT(UPPER(B51),"|",C51) -> CHINA|2020 | B51: China | C51: 2020 | D51: 84750000000000 | E51: -0.0336374 | F51: 7890000000 | G51: 0.010243278 | H51: 15000000000000 | I51: 0.03021978 | J51: 1410000000 | K51: 0 | L51: 0.17699115 | M51: 2370000000000 | N51: 2730000000000 | O51: 360000000000 | P51: 0.024 | Q51: 0.69 | R51: 0.16161616 | S51: 10350000000000 | T51: 0.038 | U51: 393300000000 | V51: 0.02622 | W51: 0.024 | X51: 10638.298 | Y51: 10382.979 | Z51: 0.77 | AA51: 0.013157895 | AB51: 0.371 | AC51: -0.029649596 | AD51: 0.399 | AE51: 0.28985631 | AF51: 0.03985631 | AG51: 0.07285631 | AH51: 0.0098563099 | AI51: 0.41242524 | AJ51: 0.58719639 | AK51: 4142.8085 | AL51: D | AM51: 0.59D | AN51: =_xlfn.CONCAT(_xlfn.IFS( AJ51>=0.7,"Superb", AJ51>=0.51,"Excellent", AJ51>=0.41,"Good", AJ51>=0.31,"Satisfactory", AJ51>=0.26,"Moderate", AJ51>=0.1,"Weak", AJ51<0.1,"Very Weak" ), " Economic Resilience with ",_xlfn.IFS( AK51<=2500,"Very Weak", AK51<=5000,"Poor", AK51<=10000,"Challenging", AK51<=12500,"Border Line", AK51<=15000,"Improved", AK51<=20000,"Moderate", AK51<=25000,"Satisfactory", AK51<=30000,"Good", AK51<=35000,"Very Good", AK51<=40000,"High", AK51<=50000,"Excellent", AK51<=100000,"Superb", AK51>100000,"Superb" ), " Affordability.") -> Excellent Economic Resilience with Poor Affordability. | AP51: We will assume the 5 socio economic sector spending will increase by 5% every year, Socio Ecnomic Sectors are Health, Housing, Energy and Education. Based on this assumption we will predict the value of Heart next year
A52: =_xlfn.CONCAT(UPPER(B52),"|",C52) -> CHINA|2021 | B52: China | C52: 2021 | D52: 96140000000000 | E52: 0.13439528 | F52: 7950000000 | G52: 0.0076045627 | H52: 18200000000000 | I52: 0.21333333 | J52: 1410000000 | K52: 0 | L52: 0.18930726 | M52: 3090000000000 | N52: 3550000000000 | O52: 460000000000 | P52: 0.025274725 | Q52: 0.701 | R52: 0.015942029 | S52: 12758200000000 | T52: 0.0385 | U52: 491190700000 | V52: 0.0269885 | W52: 0.01 | X52: 12907.801 | Y52: 12778.723 | Z52: 0.79 | AA52: 0.025974026 | AB52: 0.357 | AC52: -0.039215686 | AD52: 0.433 | AE52: 0.29528296 | AF52: 0.045282958 | AG52: 0.078282958 | AH52: 0.015282958 | AI52: 0.43413183 | AJ52: 0.62172532 | AK52: 5533.1872 | AL52: D+ | AM52: 0.62D+ | AN52: =_xlfn.CONCAT(_xlfn.IFS( AJ52>=0.7,"Superb", AJ52>=0.51,"Excellent", AJ52>=0.41,"Good", AJ52>=0.31,"Satisfactory", AJ52>=0.26,"Moderate", AJ52>=0.1,"Weak", AJ52<0.1,"Very Weak" ), " Economic Resilience with ",_xlfn.IFS( AK52<=2500,"Very Weak", AK52<=5000,"Poor", AK52<=10000,"Challenging", AK52<=12500,"Border Line", AK52<=15000,"Improved", AK52<=20000,"Moderate", AK52<=25000,"Satisfactory", AK52<=30000,"Good", AK52<=35000,"Very Good", AK52<=40000,"High", AK52<=50000,"Excellent", AK52<=100000,"Superb", AK52>100000,"Superb" ), " Affordability.") -> Excellent Economic Resilience with Challenging Affordability. | AP52: We will assume the 5 socio economic sector spending will increase by 5% every year, Socio Ecnomic Sectors are Health, Housing, Energy and Education. Based on this assumption we will predict the value of Heart next year
A53: =_xlfn.CONCAT(UPPER(B53),"|",C53) -> CHINA|2022 | B53: China | C53: 2022 | D53: 101560000000000 | E53: 0.056376118 | F53: 8020000000 | G53: 0.0088050314 | H53: 18320000000000 | I53: 0.0065934066 | J53: 1410000000 | K53: 0 | L53: 0.18038598 | M53: 3140000000000 | N53: 3720000000000 | O53: 580000000000 | P53: 0.031659389 | Q53: 0.755 | R53: 0.07703281 | S53: 13831600000000 | T53: 0.0365 | U53: 504853400000 | V53: 0.0275575 | W53: 0.02 | X53: 12992.908 | Y53: 12733.05 | Z53: 0.79 | AA53: 0 | AB53: 0.36 | AC53: 0.0083333333 | AD53: 0.43 | AE53: 0.30099522 | AF53: 0.050995219 | AG53: 0.083995219 | AH53: 0.020995219 | AI53: 0.45698088 | AJ53: 0.64146874 | AK53: 5475.2113 | AL53: D+ | AM53: 0.64D+ | AN53: =_xlfn.CONCAT(_xlfn.IFS( AJ53>=0.7,"Superb", AJ53>=0.51,"Excellent", AJ53>=0.41,"Good", AJ53>=0.31,"Satisfactory", AJ53>=0.26,"Moderate", AJ53>=0.1,"Weak", AJ53<0.1,"Very Weak" ), " Economic Resilience with ",_xlfn.IFS( AK53<=2500,"Very Weak", AK53<=5000,"Poor", AK53<=10000,"Challenging", AK53<=12500,"Border Line", AK53<=15000,"Improved", AK53<=20000,"Moderate", AK53<=25000,"Satisfactory", AK53<=30000,"Good", AK53<=35000,"Very Good", AK53<=40000,"High", AK53<=50000,"Excellent", AK53<=100000,"Superb", AK53>100000,"Superb" ), " Affordability.") -> Excellent Economic Resilience with Challenging Affordability. | AP53: We will assume the 5 socio economic sector spending will increase by 5% every year, Socio Ecnomic Sectors are Health, Housing, Energy and Education. Based on this assumption we will predict the value of Heart next year
A54: =_xlfn.CONCAT(UPPER(B54),"|",C54) -> CHINA|2023 | B54: China | C54: 2023 | D54: 106800000000000 | E54: 0.051595116 | F54: 8090000000 | G54: 0.0087281796 | H54: 18270000000000 | I54: -0.0027292576 | J54: 1410000000 | K54: 0 | L54: 0.17106742 | M54: 3110000000000 | N54: 3490000000000 | O54: 380000000000 | P54: 0.020799124 | Q54: 0.82 | R54: 0.086092715 | S54: 14981400000000 | T54: 0.0345 | U54: 516858300000 | V54: 0.02829 | W54: 0.002 | X54: 12957.447 | Y54: 12931.532 | Z54: 0.8 | AA54: 0.012658228 | AB54: 0.3585 | AC54: -0.0041841004 | AD54: 0.4415 | AE54: 0.30700813 | AF54: 0.057008125 | AG54: 0.090008125 | AH54: 0.027008125 | AI54: 0.4810325 | AJ54: 0.64460904 | AK54: 5709.2713 | AL54: D+ | AM54: 0.64D+ | AN54: =_xlfn.CONCAT(_xlfn.IFS( AJ54>=0.7,"Superb", AJ54>=0.51,"Excellent", AJ54>=0.41,"Good", AJ54>=0.31,"Satisfactory", AJ54>=0.26,"Moderate", AJ54>=0.1,"Weak", AJ54<0.1,"Very Weak" ), " Economic Resilience with ",_xlfn.IFS( AK54<=2500,"Very Weak", AK54<=5000,"Poor", AK54<=10000,"Challenging", AK54<=12500,"Border Line", AK54<=15000,"Improved", AK54<=20000,"Moderate", AK54<=25000,"Satisfactory", AK54<=30000,"Good", AK54<=35000,"Very Good", AK54<=40000,"High", AK54<=50000,"Excellent", AK54<=100000,"Superb", AK54>100000,"Superb" ), " Affordability.") -> Excellent Economic Resilience with Challenging Affordability. | AP54: We will assume the 5 socio economic sector spending will increase by 5% every year, Socio Ecnomic Sectors are Health, Housing, Energy and Education. Based on this assumption we will predict the value of Heart next year
A55: =_xlfn.CONCAT(UPPER(B55),"|",C55) -> CHINA|2024 | B55: China | C55: 2024 | D55: 112600000000000 | E55: 0.054307116 | F55: 8161972572 | G55: 0.008896486 | H55: 18740000000000 | I55: 0.025725233 | J55: 1410000000 | K55: 0 | L55: 0.16642984 | M55: 3220000000000 | N55: 3750000000000 | O55: 530000000000 | P55: 0.02828175 | Q55: 0.883 | R55: 0.076829268 | S55: 16547420000000 | T55: 0.031 | U55: 512970020000 | V55: 0.027373 | W55: 0.002 | X55: 13290.78 | Y55: 13264.199 | Z55: 0.7985 | AA55: -0.001875 | AB55: 0.35775 | AC55: -0.0020964361 | AD55: 0.44075 | AE55: 0.3133375 | AF55: 0.0633375 | AG55: 0.0963375 | AH55: 0.0333375 | AI55: 0.50635 | AJ55: 0.67368859 | AK55: 5846.1955 | AL55: D+ | AM55: 0.67D+ | AN55: =_xlfn.CONCAT(_xlfn.IFS( AJ55>=0.7,"Superb", AJ55>=0.51,"Excellent", AJ55>=0.41,"Good", AJ55>=0.31,"Satisfactory", AJ55>=0.26,"Moderate", AJ55>=0.1,"Weak", AJ55<0.1,"Very Weak" ), " Economic Resilience with ",_xlfn.IFS( AK55<=2500,"Very Weak", AK55<=5000,"Poor", AK55<=10000,"Challenging", AK55<=12500,"Border Line", AK55<=15000,"Improved", AK55<=20000,"Moderate", AK55<=25000,"Satisfactory", AK55<=30000,"Good", AK55<=35000,"Very Good", AK55<=40000,"High", AK55<=50000,"Excellent", AK55<=100000,"Superb", AK55>100000,"Superb" ), " Affordability.") -> Excellent Economic Resilience with Challenging Affordability. | AP55: We will assume the 5 socio economic sector spending will increase by 5% every year, Socio Ecnomic Sectors are Health, Housing, Energy and Education. Based on this assumption we will predict the value of Heart next year
A56: =_xlfn.CONCAT(UPPER(B56),"|",C56) -> CHINA|2025 | B56: China | C56: 2025 | D56: 113795678000000 | E56: 0.01061881 | F56: 8231613070 | G56: 0.0085323122 | H56: 19232000000000 | I56: 0.026254002 | J56: 1408000000 | K56: -0.0014184397 | L56: 0.16900466 | M56: 3120000000000 | N56: 4120000000000 | O56: 1000000000000 | P56: 0.051996672 | Q56: 0.824 | R56: -0.066817667 | S56: 15847168000000 | T56: 0.03 | U56: 475415040000 | V56: 0.02472 | W56: 0.0153 | X56: 13659.091 | Y56: 13450.107 | Z56: 0.797 | AA56: -0.0018785222 | AB56: 0.357 | AC56: -0.0021008403 | AD56: 0.44 | AE56: 0.32 | AF56: 0.07 | AG56: 0.103 | AH56: 0.04 | AI56: 0.533 | AJ56: 0.72928133 | AK56: 5918.047 | AL56: D+ | AM56: 0.73D+ | AN56: =_xlfn.CONCAT(_xlfn.IFS( AJ56>=0.7,"Superb", AJ56>=0.51,"Excellent", AJ56>=0.41,"Good", AJ56>=0.31,"Satisfactory", AJ56>=0.26,"Moderate", AJ56>=0.1,"Weak", AJ56<0.1,"Very Weak" ), " Economic Resilience with ",_xlfn.IFS( AK56<=2500,"Very Weak", AK56<=5000,"Poor", AK56<=10000,"Challenging", AK56<=12500,"Border Line", AK56<=15000,"Improved", AK56<=20000,"Moderate", AK56<=25000,"Satisfactory", AK56<=30000,"Good", AK56<=35000,"Very Good", AK56<=40000,"High", AK56<=50000,"Excellent", AK56<=100000,"Superb", AK56>100000,"Superb" ), " Affordability.") -> Superb Economic Resilience with Challenging Affordability. | AO56: Second biggest per GDP. Well performed than US due to low Debt/GDP and surplus in Trade. | AP56: We will assume the 5 socio economic sector spending will increase by 5% every year, Socio Ecnomic Sectors are Health, Housing, Energy and Education. Based on this assumption we will predict the value of Heart next year
A57: =_xlfn.CONCAT(UPPER(B57),"|",C57) -> CHINA|2026 | B57: China | C57: 2026 | D57: 120063810405112 | E57: 0.055082342 | F57: 8302201675 | G57: 0.0085753064 | H57: 20373547071991 | I57: 0.059356649 | J57: 1408262141 | K57: 0.00018617981 | L57: 0.16968933 | M57: 3447142857143 | N57: 4348571428571 | O57: 901428571429 | P57: 0.044245048 | Q57: 0.89765251 | R57: 0.08938411 | S57: 18288365606260 | T57: 0.028214286 | U57: 515993172462 | V57: 0.025326624 | W57: 0.0013142857 | X57: 14467.155 | Y57: 14448.141 | Z57: 0.80765472 | AA57: 0.01336853 | AB57: 0.35096769 | AC57: -0.017187663 | AD57: 0.45668703 | AE57: 0.3266625 | AF57: 0.0766625 | AG57: 0.1096625 | AH57: 0.0466625 | AI57: 0.55965 | AJ57: 0.74825775 | AK57: 6598.2788 | AL57: D+ | AM57: 0.75D+ | AN57: =_xlfn.CONCAT(_xlfn.IFS( AJ57>=0.7,"Superb", AJ57>=0.51,"Excellent", AJ57>=0.41,"Good", AJ57>=0.31,"Satisfactory", AJ57>=0.26,"Moderate", AJ57>=0.1,"Weak", AJ57<0.1,"Very Weak" ), " Economic Resilience with ",_xlfn.IFS( AK57<=2500,"Very Weak", AK57<=5000,"Poor", AK57<=10000,"Challenging", AK57<=12500,"Border Line", AK57<=15000,"Improved", AK57<=20000,"Moderate", AK57<=25000,"Satisfactory", AK57<=30000,"Good", AK57<=35000,"Very Good", AK57<=40000,"High", AK57<=50000,"Excellent", AK57<=100000,"Superb", AK57>100000,"Superb" ), " Affordability.") -> Superb Economic Resilience with Challenging Affordability. | AP57: We will assume the 5 socio economic sector spending will increase by 5% every year, Socio Ecnomic Sectors are Health, Housing, Energy and Education. Based on this assumption we will predict the value of Heart next year
A58: =_xlfn.CONCAT(UPPER(B58),"|",C58) -> CHINA|2027 | B58: China | C58: 2027 | D58: 125735541889780 | E58: 0.047239309 | F58: 8372937901 | G58: 0.0085201769 | H58: 21326201311915 | I58: 0.046759371 | J58: 1408179796 | K58: -5.8473238e-05 | L58: 0.16961156 | M58: 3575000000000 | N58: 4578928571429 | O58: 1003928571429 | P58: 0.04707489 | Q58: 0.95358141 | R58: 0.062305738 | S58: 20336269094859 | T58: 0.026339286 | U58: 535642802052 | V58: 0.025116653 | W58: -0.0020107143 | X58: 15144.516 | Y58: 15174.967 | Z58: 0.81544419 | AA58: 0.0096445608 | AB58: 0.3465405 | AC58: -0.01277537 | AD58: 0.46890369 | AE58: 0.33365813 | AF58: 0.083658125 | AG58: 0.11665813 | AH58: 0.053658125 | AI58: 0.5876325 | AJ58: 0.7792023 | AK58: 7115.5981 | AL58: D+ | AM58: 0.78D+ | AN58: =_xlfn.CONCAT(_xlfn.IFS( AJ58>=0.7,"Superb", AJ58>=0.51,"Excellent", AJ58>=0.41,"Good", AJ58>=0.31,"Satisfactory", AJ58>=0.26,"Moderate", AJ58>=0.1,"Weak", AJ58<0.1,"Very Weak" ), " Economic Resilience with ",_xlfn.IFS( AK58<=2500,"Very Weak", AK58<=5000,"Poor", AK58<=10000,"Challenging", AK58<=12500,"Border Line", AK58<=15000,"Improved", AK58<=20000,"Moderate", AK58<=25000,"Satisfactory", AK58<=30000,"Good", AK58<=35000,"Very Good", AK58<=40000,"High", AK58<=50000,"Excellent", AK58<=100000,"Superb", AK58>100000,"Superb" ), " Affordability.") -> Superb Economic Resilience with Challenging Affordability. | AP58: We will assume the 5 socio economic sector spending will increase by 5% every year, Socio Ecnomic Sectors are Health, Housing, Energy and Education. Based on this assumption we will predict the value of Heart next year
A59: =_xlfn.CONCAT(UPPER(B59),"|",C59) -> CHINA|2028 | B59: China | C59: 2028 | D59: 131237442252096 | E59: 0.043757718 | F59: 8443822776 | G59: 0.0084659502 | H59: 22218816211356 | I59: 0.041855316 | J59: 1407980251 | K59: -0.00014170386 | L59: 0.16930242 | M59: 3702857142857 | N59: 4809285714286 | O59: 1106428571429 | P59: 0.049796918 | Q59: 1.0036598 | R59: 0.052516165 | S59: 22300133700131 | T59: 0.024464286 | U59: 545556842307 | V59: 0.024553821 | W59: -0.0053357143 | X59: 15780.631 | Y59: 15864.832 | Z59: 0.82226148 | AA59: 0.0083602071 | AB59: 0.34266313 | AC59: -0.011315418 | AD59: 0.47959835 | AE59: 0.34100353 | AF59: 0.091003531 | AG59: 0.12400353 | AH59: 0.061003531 | AI59: 0.61701412 | AJ59: 0.81155964 | AK59: 7608.747 | AL59: D+ | AM59: 0.81D+ | AN59: =_xlfn.CONCAT(_xlfn.IFS( AJ59>=0.7,"Superb", AJ59>=0.51,"Excellent", AJ59>=0.41,"Good", AJ59>=0.31,"Satisfactory", AJ59>=0.26,"Moderate", AJ59>=0.1,"Weak", AJ59<0.1,"Very Weak" ), " Economic Resilience with ",_xlfn.IFS( AK59<=2500,"Very Weak", AK59<=5000,"Poor", AK59<=10000,"Challenging", AK59<=12500,"Border Line", AK59<=15000,"Improved", AK59<=20000,"Moderate", AK59<=25000,"Satisfactory", AK59<=30000,"Good", AK59<=35000,"Very Good", AK59<=40000,"High", AK59<=50000,"Excellent", AK59<=100000,"Superb", AK59>100000,"Superb" ), " Affordability.") -> Superb Economic Resilience with Challenging Affordability. | AP59: We will assume the 5 socio economic sector spending will increase by 5% every year, Socio Ecnomic Sectors are Health, Housing, Energy and Education. Based on this assumption we will predict the value of Heart next year
A60: =_xlfn.CONCAT(UPPER(B60),"|",C60) -> CHINA|2029 | B60: China | C60: 2029 | D60: 136712479650225 | E60: 0.041718562 | F60: 8514849364 | G60: 0.0084116625 | H60: 23095099157431 | I60: 0.039438777 | J60: 1407739047 | K60: -0.00017131211 | L60: 0.1689319 | M60: 3830714285714 | N60: 5039642857143 | O60: 1208928571429 | P60: 0.052345676 | Q60: 1.0519531 | R60: 0.04811719 | S60: 24294962068990 | T60: 0.022589286 | U60: 548805839594 | V60: 0.02376287 | W60: -0.0086607143 | X60: 16405.81 | Y60: 16547.896 | Z60: 0.82873857 | AA60: 0.0078771683 | AB60: 0.33898559 | AC60: -0.01084864 | AD60: 0.48975297 | AE60: 0.34871621 | AF60: 0.098716208 | AG60: 0.13171621 | AH60: 0.068716208 | AI60: 0.64786483 | AJ60: 0.84537954 | AK60: 8104.3812 | AL60: D+ | AM60: 0.85D+ | AN60: =_xlfn.CONCAT(_xlfn.IFS( AJ60>=0.7,"Superb", AJ60>=0.51,"Excellent", AJ60>=0.41,"Good", AJ60>=0.31,"Satisfactory", AJ60>=0.26,"Moderate", AJ60>=0.1,"Weak", AJ60<0.1,"Very Weak" ), " Economic Resilience with ",_xlfn.IFS( AK60<=2500,"Very Weak", AK60<=5000,"Poor", AK60<=10000,"Challenging", AK60<=12500,"Border Line", AK60<=15000,"Improved", AK60<=20000,"Moderate", AK60<=25000,"Satisfactory", AK60<=30000,"Good", AK60<=35000,"Very Good", AK60<=40000,"High", AK60<=50000,"Excellent", AK60<=100000,"Superb", AK60>100000,"Superb" ), " Affordability.") -> Superb Economic Resilience with Challenging Affordability. | AP60: We will assume the 5 socio economic sector spending will increase by 5% every year, Socio Ecnomic Sectors are Health, Housing, Energy and Education. Based on this assumption we will predict the value of Heart next year
A61: =_xlfn.CONCAT(UPPER(B61),"|",C61) -> CHINA|2030 | B61: China | C61: 2030 | D61: 141834754671550 | F61: 8586617399 | H61: 23512158970811 | J61: 1407328433 | L61: 0.16577149 | M61: 3958571428571 | N61: 5270000000000 | O61: 1311428571429 | P61: 0.055776612 | Q61: 1.0999085 | S61: 25861222423396 | T61: 0.020714286 | U61: 535696750199 | V61: 0.022783818 | W61: -0.011985714 | X61: 16706.945 | Y61: 16907.19 | Z61: 0.83509653 | AB61: 0.33538622 | AD61: 0.49971031 | AE61: 0.35681452 | AF61: 0.10681452 | AG61: 0.13981452 | AH61: 0.076814518 | AI61: 0.68025807 | AJ61: 0.87902236 | AK61: 8448.6971 | AL61: D+ | AM61: 0.88D+ | AN61: =_xlfn.CONCAT(_xlfn.IFS( AJ61>=0.7,"Superb", AJ61>=0.51,"Excellent", AJ61>=0.41,"Good", AJ61>=0.31,"Satisfactory", AJ61>=0.26,"Moderate", AJ61>=0.1,"Weak", AJ61<0.1,"Very Weak" ), " Economic Resilience with ",_xlfn.IFS( AK61<=2500,"Very Weak", AK61<=5000,"Poor", AK61<=10000,"Challenging", AK61<=12500,"Border Line", AK61<=15000,"Improved", AK61<=20000,"Moderate", AK61<=25000,"Satisfactory", AK61<=30000,"Good", AK61<=35000,"Very Good", AK61<=40000,"High", AK61<=50000,"Excellent", AK61<=100000,"Superb", AK61>100000,"Superb" ), " Affordability.") -> Superb Economic Resilience with Challenging Affordability. | AP61: We will assume the 5 socio economic sector spending will increase by 5% every year, Socio Ecnomic Sectors are Health, Housing, Energy and Education. Based on this assumption we will predict the value of Heart next year
A62: =_xlfn.CONCAT(UPPER(B62),"|",C62) -> GERMANY|2019 | B62: Germany | C62: 2019 | D62: 87700000000000 | F62: 7810000000 | H62: 3960000000000 | J62: 83092962 | L62: 0.045153934 | M62: 1450000000000 | N62: 1680000000000 | O62: 230000000000 | P62: 0.058080808 | Q62: 0.3722 | S62: 1473912000000 | T62: 0.001 | U62: 1473912000 | V62: 0.0003722 | W62: 0.014 | X62: 47657.466 | Y62: 46990.261 | Z62: 0.94 | AB62: 0.297 | AD62: 0.643 | AE62: 0.16999916 | AF62: 0.097999157 | AG62: 0.049999157 | AH62: 0.014999157 | AI62: 0.33299663 | AJ62: 0.43585917 | AK62: 30214.738 | AL62: B+ | AM62: 0.44B+ | AN62: =_xlfn.CONCAT(_xlfn.IFS( AJ62>=0.7,"Superb", AJ62>=0.51,"Excellent", AJ62>=0.41,"Good", AJ62>=0.31,"Satisfactory", AJ62>=0.26,"Moderate", AJ62>=0.1,"Weak", AJ62<0.1,"Very Weak" ), " Economic Resilience with ",_xlfn.IFS( AK62<=2500,"Very Weak", AK62<=5000,"Poor", AK62<=10000,"Challenging", AK62<=12500,"Border Line", AK62<=15000,"Improved", AK62<=20000,"Moderate", AK62<=25000,"Satisfactory", AK62<=30000,"Good", AK62<=35000,"Very Good", AK62<=40000,"High", AK62<=50000,"Excellent", AK62<=100000,"Superb", AK62>100000,"Superb" ), " Affordability.") -> Good Economic Resilience with Very Good Affordability. | AP62: We will assume the 5 socio economic sector spending will increase by 5% every year, Socio Ecnomic Sectors are Health, Housing, Energy and Education. Based on this assumption we will predict the value of Heart next year
A63: =_xlfn.CONCAT(UPPER(B63),"|",C63) -> GERMANY|2020 | B63: Germany | C63: 2020 | D63: 84750000000000 | E63: -0.0336374 | F63: 7890000000 | G63: 0.010243278 | H63: 3940000000000 | I63: -0.0050505051 | J63: 83160871 | K63: 0.00081726537 | L63: 0.046489676 | M63: 1330000000000 | N63: 1540000000000 | O63: 210000000000 | P63: 0.053299492 | Q63: 0.4436 | R63: 0.19183235 | S63: 1747784000000 | T63: 0.001 | U63: 1747784000 | V63: 0.0004436 | W63: 0.001 | X63: 47378.051 | Y63: 47330.673 | Z63: 0.94 | AA63: 0 | AB63: 0.305 | AC63: 0.026229508 | AD63: 0.635 | AE63: 0.17438069 | AF63: 0.10238069 | AG63: 0.054380691 | AH63: 0.019380691 | AI63: 0.35052276 | AJ63: 0.44986833 | AK63: 30054.977 | AL63: B+ | AM63: 0.45B+ | AN63: =_xlfn.CONCAT(_xlfn.IFS( AJ63>=0.7,"Superb", AJ63>=0.51,"Excellent", AJ63>=0.41,"Good", AJ63>=0.31,"Satisfactory", AJ63>=0.26,"Moderate", AJ63>=0.1,"Weak", AJ63<0.1,"Very Weak" ), " Economic Resilience with ",_xlfn.IFS( AK63<=2500,"Very Weak", AK63<=5000,"Poor", AK63<=10000,"Challenging", AK63<=12500,"Border Line", AK63<=15000,"Improved", AK63<=20000,"Moderate", AK63<=25000,"Satisfactory", AK63<=30000,"Good", AK63<=35000,"Very Good", AK63<=40000,"High", AK63<=50000,"Excellent", AK63<=100000,"Superb", AK63>100000,"Superb" ), " Affordability.") -> Good Economic Resilience with Very Good Affordability. | AP63: We will assume the 5 socio economic sector spending will increase by 5% every year, Socio Ecnomic Sectors are Health, Housing, Energy and Education. Based on this assumption we will predict the value of Heart next year
A64: =_xlfn.CONCAT(UPPER(B64),"|",C64) -> GERMANY|2021 | B64: Germany | C64: 2021 | D64: 96140000000000 | E64: 0.13439528 | F64: 7950000000 | G64: 0.0076045627 | H64: 4360000000000 | I64: 0.10659898 | J64: 83196078 | K64: 0.00042336016 | L64: 0.04535053 | M64: 1630000000000 | N64: 1850000000000 | O64: 220000000000 | P64: 0.050458716 | Q64: 0.4579 | R64: 0.032236249 | S64: 1996444000000 | T64: 0.001 | U64: 1996444000 | V64: 0.0004579 | W64: 0.031 | X64: 52406.317 | Y64: 50781.721 | Z64: 0.95 | AA64: 0.010638298 | AB64: 0.312 | AC64: 0.022435897 | AD64: 0.638 | AE64: 0.17899283 | AF64: 0.10699283 | AG64: 0.058992833 | AH64: 0.023992833 | AI64: 0.36897133 | AJ64: 0.46432268 | AK64: 32398.738 | AL64: B+ | AM64: 0.46B+ | AN64: =_xlfn.CONCAT(_xlfn.IFS( AJ64>=0.7,"Superb", AJ64>=0.51,"Excellent", AJ64>=0.41,"Good", AJ64>=0.31,"Satisfactory", AJ64>=0.26,"Moderate", AJ64>=0.1,"Weak", AJ64<0.1,"Very Weak" ), " Economic Resilience with ",_xlfn.IFS( AK64<=2500,"Very Weak", AK64<=5000,"Poor", AK64<=10000,"Challenging", AK64<=12500,"Border Line", AK64<=15000,"Improved", AK64<=20000,"Moderate", AK64<=25000,"Satisfactory", AK64<=30000,"Good", AK64<=35000,"Very Good", AK64<=40000,"High", AK64<=50000,"Excellent", AK64<=100000,"Superb", AK64>100000,"Superb" ), " Affordability.") -> Good Economic Resilience with Very Good Affordability. | AP64: We will assume the 5 socio economic sector spending will increase by 5% every year, Socio Ecnomic Sectors are Health, Housing, Energy and Education. Based on this assumption we will predict the value of Heart next year
A65: =_xlfn.CONCAT(UPPER(B65),"|",C65) -> GERMANY|2022 | B65: Germany | C65: 2022 | D65: 101560000000000 | E65: 0.056376118 | F65: 8020000000 | G65: 0.0088050314 | H65: 4200000000000 | I65: -0.036697248 | J65: 83177813 | K65: -0.0002195416 | L65: 0.041354864 | M65: 1810000000000 | N65: 1920000000000 | O65: 110000000000 | P65: 0.026190476 | Q65: 0.4503 | R65: -0.01659751 | S65: 1891260000000 | T65: 0.025 | U65: 47281500000 | V65: 0.0112575 | W65: 0.069 | X65: 50494.235 | Y65: 47010.132 | Z65: 0.94 | AA65: -0.010526316 | AB65: 0.29 | AC65: -0.075862069 | AD65: 0.65 | AE65: 0.18384772 | AF65: 0.11184772 | AG65: 0.063847719 | AH65: 0.028847719 | AI65: 0.38839088 | AJ65: 0.44467872 | AK65: 30556.586 | AL65: B+ | AM65: 0.44B+ | AN65: =_xlfn.CONCAT(_xlfn.IFS( AJ65>=0.7,"Superb", AJ65>=0.51,"Excellent", AJ65>=0.41,"Good", AJ65>=0.31,"Satisfactory", AJ65>=0.26,"Moderate", AJ65>=0.1,"Weak", AJ65<0.1,"Very Weak" ), " Economic Resilience with ",_xlfn.IFS( AK65<=2500,"Very Weak", AK65<=5000,"Poor", AK65<=10000,"Challenging", AK65<=12500,"Border Line", AK65<=15000,"Improved", AK65<=20000,"Moderate", AK65<=25000,"Satisfactory", AK65<=30000,"Good", AK65<=35000,"Very Good", AK65<=40000,"High", AK65<=50000,"Excellent", AK65<=100000,"Superb", AK65>100000,"Superb" ), " Affordability.") -> Good Economic Resilience with Very Good Affordability. | AP65: We will assume the 5 socio economic sector spending will increase by 5% every year, Socio Ecnomic Sectors are Health, Housing, Energy and Education. Based on this assumption we will predict the value of Heart next year
A66: =_xlfn.CONCAT(UPPER(B66),"|",C66) -> GERMANY|2023 | B66: Germany | C66: 2023 | D66: 106800000000000 | E66: 0.051595116 | F66: 8090000000 | G66: 0.0087281796 | H66: 4560000000000 | I66: 0.085714286 | J66: 83287273 | K66: 0.0013159759 | L66: 0.042696629 | M66: 1780000000000 | N66: 1960000000000 | O66: 180000000000 | P66: 0.039473684 | Q66: 0.4436 | R66: -0.01487897 | S66: 2022816000000 | T66: 0.045 | U66: 91026720000 | V66: 0.019962 | W66: 0.059 | X66: 54750.262 | Y66: 51519.996 | Z66: 0.95 | AA66: 0.010638298 | AB66: 0.294 | AC66: 0.013605442 | AD66: 0.656 | AE66: 0.18895813 | AF66: 0.11695812 | AG66: 0.068958125 | AH66: 0.033958125 | AI66: 0.4088325 | AJ66: 0.47104081 | AK66: 33797.118 | AL66: B+ | AM66: 0.47B+ | AN66: =_xlfn.CONCAT(_xlfn.IFS( AJ66>=0.7,"Superb", AJ66>=0.51,"Excellent", AJ66>=0.41,"Good", AJ66>=0.31,"Satisfactory", AJ66>=0.26,"Moderate", AJ66>=0.1,"Weak", AJ66<0.1,"Very Weak" ), " Economic Resilience with ",_xlfn.IFS( AK66<=2500,"Very Weak", AK66<=5000,"Poor", AK66<=10000,"Challenging", AK66<=12500,"Border Line", AK66<=15000,"Improved", AK66<=20000,"Moderate", AK66<=25000,"Satisfactory", AK66<=30000,"Good", AK66<=35000,"Very Good", AK66<=40000,"High", AK66<=50000,"Excellent", AK66<=100000,"Superb", AK66>100000,"Superb" ), " Affordability.") -> Good Economic Resilience with Very Good Affordability. | AP66: We will assume the 5 socio economic sector spending will increase by 5% every year, Socio Ecnomic Sectors are Health, Housing, Energy and Education. Based on this assumption we will predict the value of Heart next year
A67: =_xlfn.CONCAT(UPPER(B67),"|",C67) -> GERMANY|2024 | B67: Germany | C67: 2024 | D67: 112600000000000 | E67: 0.054307116 | F67: 8161972572 | G67: 0.008896486 | H67: 4690000000000 | I67: 0.028508772 | J67: 83516593 | K67: 0.0027533618 | L67: 0.041651865 | M67: 1760000000000 | N67: 1940000000000 | O67: 180000000000 | P67: 0.038379531 | Q67: 0.4397 | R67: -0.0087917042 | S67: 2062193000000 | T67: 0.0315 | U67: 64959079500 | V67: 0.01385055 | W67: 0.023 | X67: 56156.505 | Y67: 54864.906 | Z67: 0.9545 | AA67: 0.0047368421 | AB67: 0.294 | AC67: 0 | AD67: 0.6605 | AE67: 0.1943375 | AF67: 0.1223375 | AG67: 0.0743375 | AH67: 0.0393375 | AI67: 0.43035 | AJ67: 0.49653085 | AK67: 36238.27 | AL67: A- | AM67: 0.5A- | AN67: =_xlfn.CONCAT(_xlfn.IFS( AJ67>=0.7,"Superb", AJ67>=0.51,"Excellent", AJ67>=0.41,"Good", AJ67>=0.31,"Satisfactory", AJ67>=0.26,"Moderate", AJ67>=0.1,"Weak", AJ67<0.1,"Very Weak" ), " Economic Resilience with ",_xlfn.IFS( AK67<=2500,"Very Weak", AK67<=5000,"Poor", AK67<=10000,"Challenging", AK67<=12500,"Border Line", AK67<=15000,"Improved", AK67<=20000,"Moderate", AK67<=25000,"Satisfactory", AK67<=30000,"Good", AK67<=35000,"Very Good", AK67<=40000,"High", AK67<=50000,"Excellent", AK67<=100000,"Superb", AK67>100000,"Superb" ), " Affordability.") -> Good Economic Resilience with High Affordability. | AP67: We will assume the 5 socio economic sector spending will increase by 5% every year, Socio Ecnomic Sectors are Health, Housing, Energy and Education. Based on this assumption we will predict the value of Heart next year
A68: =_xlfn.CONCAT(UPPER(B68),"|",C68) -> GERMANY|2025 | B68: Germany | C68: 2025 | D68: 113795678000000 | E68: 0.01061881 | F68: 8231613070 | G68: 0.0085323122 | H68: 4750000000000 | I68: 0.012793177 | J68: 83600000 | K68: 0.00099868777 | L68: 0.04174148 | M68: 1989000000000 | N68: 2271000000000 | O68: 282000000000 | P68: 0.059368421 | Q68: 0.624 | R68: 0.41914942 | S68: 2964000000000 | T68: 0.0215 | U68: 63726000000 | V68: 0.013416 | W68: 0.02 | X68: 56818.182 | Y68: 55681.818 | Z68: 0.959 | AA68: 0.0047145102 | AB68: 0.294 | AC68: 0 | AD68: 0.665 | AE68: 0.2 | AF68: 0.128 | AG68: 0.08 | AH68: 0.045 | AI68: 0.453 | AJ68: 0.5406939 | AK68: 37028.409 | AL68: A- | AM68: 0.54A- | AN68: =_xlfn.CONCAT(_xlfn.IFS( AJ68>=0.7,"Superb", AJ68>=0.51,"Excellent", AJ68>=0.41,"Good", AJ68>=0.31,"Satisfactory", AJ68>=0.26,"Moderate", AJ68>=0.1,"Weak", AJ68<0.1,"Very Weak" ), " Economic Resilience with ",_xlfn.IFS( AK68<=2500,"Very Weak", AK68<=5000,"Poor", AK68<=10000,"Challenging", AK68<=12500,"Border Line", AK68<=15000,"Improved", AK68<=20000,"Moderate", AK68<=25000,"Satisfactory", AK68<=30000,"Good", AK68<=35000,"Very Good", AK68<=40000,"High", AK68<=50000,"Excellent", AK68<=100000,"Superb", AK68>100000,"Superb" ), " Affordability.") -> Excellent Economic Resilience with High Affordability. | AO68: Third biggest per GDP. Face challenges on low population & economic growth and US tarrifs threat. | AP68: We will assume the 5 socio economic sector spending will increase by 5% every year, Socio Ecnomic Sectors are Health, Housing, Energy and Education. Based on this assumption we will predict the value of Heart next year
A69: =_xlfn.CONCAT(UPPER(B69),"|",C69) -> GERMANY|2026 | B69: Germany | C69: 2026 | D69: 120063810405112 | E69: 0.055082342 | F69: 8302201675 | G69: 0.0085753064 | H69: 4917376110303 | I69: 0.035237076 | J69: 83653517 | K69: 0.00064015221 | L69: 0.040956356 | M69: 2053714285714 | N69: 2263428571429 | O69: 209714285714 | P69: 0.042647599 | Q69: 0.62653911 | R69: 0.0040690795 | S69: 3080928430043 | T69: 0.041785714 | U69: 128738795112 | V69: 0.026180384 | W69: 0.043857143 | X69: 58782.659 | Y69: 56204.619 | Z69: 0.96107873 | AA69: 0.0021676046 | AB69: 0.29216702 | AC69: -0.0062737572 | AD69: 0.66891172 | AE69: 0.2056625 | AF69: 0.1336625 | AG69: 0.0856625 | AH69: 0.0506625 | AI69: 0.47565 | AJ69: 0.53307357 | AK69: 37595.928 | AL69: A- | AM69: 0.53A- | AN69: =_xlfn.CONCAT(_xlfn.IFS( AJ69>=0.7,"Superb", AJ69>=0.51,"Excellent", AJ69>=0.41,"Good", AJ69>=0.31,"Satisfactory", AJ69>=0.26,"Moderate", AJ69>=0.1,"Weak", AJ69<0.1,"Very Weak" ), " Economic Resilience with ",_xlfn.IFS( AK69<=2500,"Very Weak", AK69<=5000,"Poor", AK69<=10000,"Challenging", AK69<=12500,"Border Line", AK69<=15000,"Improved", AK69<=20000,"Moderate", AK69<=25000,"Satisfactory", AK69<=30000,"Good", AK69<=35000,"Very Good", AK69<=40000,"High", AK69<=50000,"Excellent", AK69<=100000,"Superb", AK69>100000,"Superb" ), " Affordability.") -> Excellent Economic Resilience with High Affordability. | AP69: We will assume the 5 socio economic sector spending will increase by 5% every year, Socio Ecnomic Sectors are Health, Housing, Energy and Education. Based on this assumption we will predict the value of Heart next year
A70: =_xlfn.CONCAT(UPPER(B70),"|",C70) -> GERMANY|2027 | B70: Germany | C70: 2027 | D70: 125735541889780 | E70: 0.047239309 | F70: 8372937901 | G70: 0.0085201769 | H70: 5073693400710 | I70: 0.03178876 | J70: 83727390 | K70: 0.00088308782 | L70: 0.040352102 | M70: 2147535714286 | N70: 2359250000000 | O70: 211714285714 | P70: 0.041727844 | Q70: 0.65175762 | R70: 0.040250505 | S70: 3306818340988 | T70: 0.047732143 | U70: 157841525455 | V70: 0.031109788 | W70: 0.047071429 | X70: 60597.773 | Y70: 57745.349 | Z70: 0.96386252 | AA70: 0.0028965245 | AB70: 0.2905857 | AC70: -0.0054418282 | AD70: 0.67327682 | AE70: 0.21160813 | AF70: 0.13960812 | AG70: 0.091608125 | AH70: 0.056608125 | AI70: 0.4994325 | AJ70: 0.55040266 | AK70: 38878.605 | AL70: A- | AM70: 0.55A- | AN70: =_xlfn.CONCAT(_xlfn.IFS( AJ70>=0.7,"Superb", AJ70>=0.51,"Excellent", AJ70>=0.41,"Good", AJ70>=0.31,"Satisfactory", AJ70>=0.26,"Moderate", AJ70>=0.1,"Weak", AJ70<0.1,"Very Weak" ), " Economic Resilience with ",_xlfn.IFS( AK70<=2500,"Very Weak", AK70<=5000,"Poor", AK70<=10000,"Challenging", AK70<=12500,"Border Line", AK70<=15000,"Improved", AK70<=20000,"Moderate", AK70<=25000,"Satisfactory", AK70<=30000,"Good", AK70<=35000,"Very Good", AK70<=40000,"High", AK70<=50000,"Excellent", AK70<=100000,"Superb", AK70>100000,"Superb" ), " Affordability.") -> Excellent Economic Resilience with High Affordability. | AP70: We will assume the 5 socio economic sector spending will increase by 5% every year, Socio Ecnomic Sectors are Health, Housing, Energy and Education. Based on this assumption we will predict the value of Heart next year
A71: =_xlfn.CONCAT(UPPER(B71),"|",C71) -> GERMANY|2028 | B71: Germany | C71: 2028 | D71: 131237442252096 | E71: 0.043757718 | F71: 8443822776 | G71: 0.0084659502 | H71: 5226929164705 | I71: 0.030202015 | J71: 83808208 | K71: 0.00096525124 | L71: 0.039828033 | M71: 2241357142857 | N71: 2455071428571 | O71: 213714285714 | P71: 0.040887159 | Q71: 0.68563871 | R71: 0.051984186 | S71: 3583784972696 | T71: 0.053678571 | U71: 192372457641 | V71: 0.036804107 | W71: 0.050285714 | X71: 62367.748 | Y71: 59231.541 | Z71: 0.96688836 | AA71: 0.003139284 | AB71: 0.28909077 | AC71: -0.0051711382 | AD71: 0.67779759 | AE71: 0.21785103 | AF71: 0.14585103 | AG71: 0.097851031 | AH71: 0.062851031 | AI71: 0.52440412 | AJ71: 0.56831521 | AK71: 40146.996 | AL71: A | AM71: 0.57A | AN71: =_xlfn.CONCAT(_xlfn.IFS( AJ71>=0.7,"Superb", AJ71>=0.51,"Excellent", AJ71>=0.41,"Good", AJ71>=0.31,"Satisfactory", AJ71>=0.26,"Moderate", AJ71>=0.1,"Weak", AJ71<0.1,"Very Weak" ), " Economic Resilience with ",_xlfn.IFS( AK71<=2500,"Very Weak", AK71<=5000,"Poor", AK71<=10000,"Challenging", AK71<=12500,"Border Line", AK71<=15000,"Improved", AK71<=20000,"Moderate", AK71<=25000,"Satisfactory", AK71<=30000,"Good", AK71<=35000,"Very Good", AK71<=40000,"High", AK71<=50000,"Excellent", AK71<=100000,"Superb", AK71>100000,"Superb" ), " Affordability.") -> Excellent Economic Resilience with Excellent Affordability. | AP71: We will assume the 5 socio economic sector spending will increase by 5% every year, Socio Ecnomic Sectors are Health, Housing, Energy and Education. Based on this assumption we will predict the value of Heart next year
A72: =_xlfn.CONCAT(UPPER(B72),"|",C72) -> GERMANY|2029 | B72: Germany | C72: 2029 | D72: 136712479650225 | E72: 0.041718562 | F72: 8514849364 | G72: 0.0084116625 | H72: 5379731727209 | I72: 0.029233716 | J72: 83891509 | K72: 0.00099394399 | L72: 0.0393507 | M72: 2335178571429 | N72: 2550892857143 | O72: 215714285714 | P72: 0.040097592 | Q72: 0.72319054 | R72: 0.054769128 | S72: 3890571119454 | T72: 0.059625 | U72: 231975302997 | V72: 0.043120236 | W72: 0.0535 | X72: 64127.25 | Y72: 60696.442 | Z72: 0.97000191 | AA72: 0.0032201747 | AB72: 0.28762726 | AC72: -0.0050882052 | AD72: 0.68237465 | AE72: 0.22440608 | AF72: 0.15240608 | AG72: 0.10440608 | AH72: 0.069406083 | AI72: 0.55062433 | AJ72: 0.58695239 | AK72: 41417.713 | AL72: A | AM72: 0.59A | AN72: =_xlfn.CONCAT(_xlfn.IFS( AJ72>=0.7,"Superb", AJ72>=0.51,"Excellent", AJ72>=0.41,"Good", AJ72>=0.31,"Satisfactory", AJ72>=0.26,"Moderate", AJ72>=0.1,"Weak", AJ72<0.1,"Very Weak" ), " Economic Resilience with ",_xlfn.IFS( AK72<=2500,"Very Weak", AK72<=5000,"Poor", AK72<=10000,"Challenging", AK72<=12500,"Border Line", AK72<=15000,"Improved", AK72<=20000,"Moderate", AK72<=25000,"Satisfactory", AK72<=30000,"Good", AK72<=35000,"Very Good", AK72<=40000,"High", AK72<=50000,"Excellent", AK72<=100000,"Superb", AK72>100000,"Superb" ), " Affordability.") -> Excellent Economic Resilience with Excellent Affordability. | AP72: We will assume the 5 socio economic sector spending will increase by 5% every year, Socio Ecnomic Sectors are Health, Housing, Energy and Education. Based on this assumption we will predict the value of Heart next year
A73: =_xlfn.CONCAT(UPPER(B73),"|",C73) -> GERMANY|2030 | B73: Germany | C73: 2030 | D73: 141834754671550 | F73: 8586617399 | H73: 5511009600601 | J73: 83996431 | L73: 0.038855142 | M73: 2429000000000 | N73: 2646714285714 | O73: 217714285714 | P73: 0.039505336 | Q73: 0.76254043 | S73: 4202367636285 | T73: 0.065571429 | U73: 275555249294 | V73: 0.050000865 | W73: 0.056714286 | X73: 65610.045 | Y73: 61889.018 | Z73: 0.97314916 | AB73: 0.28617601 | AD73: 0.68697315 | AE73: 0.23128889 | AF73: 0.15928889 | AG73: 0.11128889 | AH73: 0.076288887 | AI73: 0.57815555 | AJ73: 0.60651516 | AK73: 42516.094 | AL73: A | AM73: 0.61A | AN73: =_xlfn.CONCAT(_xlfn.IFS( AJ73>=0.7,"Superb", AJ73>=0.51,"Excellent", AJ73>=0.41,"Good", AJ73>=0.31,"Satisfactory", AJ73>=0.26,"Moderate", AJ73>=0.1,"Weak", AJ73<0.1,"Very Weak" ), " Economic Resilience with ",_xlfn.IFS( AK73<=2500,"Very Weak", AK73<=5000,"Poor", AK73<=10000,"Challenging", AK73<=12500,"Border Line", AK73<=15000,"Improved", AK73<=20000,"Moderate", AK73<=25000,"Satisfactory", AK73<=30000,"Good", AK73<=35000,"Very Good", AK73<=40000,"High", AK73<=50000,"Excellent", AK73<=100000,"Superb", AK73>100000,"Superb" ), " Affordability.") -> Excellent Economic Resilience with Excellent Affordability. | AP73: We will assume the 5 socio economic sector spending will increase by 5% every year, Socio Ecnomic Sectors are Health, Housing, Energy and Education. Based on this assumption we will predict the value of Heart next year
A74: =_xlfn.CONCAT(UPPER(B74),"|",C74) -> INDONESIA|2019 | B74: Indonesia | C74: 2019 | D74: 87700000000000 | F74: 7810000000 | H74: 1120000000000 | J74: 272489381 | L74: 0.01277081 | M74: 213035000000 | N74: 208057800000 | O74: -4977200000 | P74: -0.0044439286 | Q74: 0.306 | S74: 342720000000 | T74: 0.06 | U74: 20563200000 | V74: 0.01836 | W74: 0.03030585 | X74: 4110.2519 | Y74: 3985.6872 | Z74: 0.71 | AB74: 0.354 | AD74: 0.356 | AE74: 0.15238333 | AF74: 0.0093833296 | AG74: 0.13238333 | AH74: 0.01238333 | AI74: 0.30653332 | AJ74: 0.2965002 | AK74: 1418.9047 | AL74: D- | AM74: 0.3D- | AN74: =_xlfn.CONCAT(_xlfn.IFS( AJ74>=0.7,"Superb", AJ74>=0.51,"Excellent", AJ74>=0.41,"Good", AJ74>=0.31,"Satisfactory", AJ74>=0.26,"Moderate", AJ74>=0.1,"Weak", AJ74<0.1,"Very Weak" ), " Economic Resilience with ",_xlfn.IFS( AK74<=2500,"Very Weak", AK74<=5000,"Poor", AK74<=10000,"Challenging", AK74<=12500,"Border Line", AK74<=15000,"Improved", AK74<=20000,"Moderate", AK74<=25000,"Satisfactory", AK74<=30000,"Good", AK74<=35000,"Very Good", AK74<=40000,"High", AK74<=50000,"Excellent", AK74<=100000,"Superb", AK74>100000,"Superb" ), " Affordability.") -> Moderate Economic Resilience with Very Weak Affordability. | AP74: We will assume the 5 socio economic sector spending will increase by 5% every year, Socio Ecnomic Sectors are Health, Housing, Energy and Education. Based on this assumption we will predict the value of Heart next year
A75: =_xlfn.CONCAT(UPPER(B75),"|",C75) -> INDONESIA|2020 | B75: Indonesia | C75: 2020 | D75: 84750000000000 | E75: -0.0336374 | F75: 7890000000 | G75: 0.010243278 | H75: 1060000000000 | I75: -0.053571429 | J75: 274814866 | K75: 0.0085342225 | L75: 0.012507375 | M75: 165647000000 | N75: 183546600000 | O75: 17899600000 | P75: 0.016886415 | Q75: 0.397 | R75: 0.29738562 | S75: 420820000000 | T75: 0.045 | U75: 18936900000 | V75: 0.017865 | W75: 0.01919835 | X75: 3857.1421 | Y75: 3783.0914 | Z75: 0.72 | AA75: 0.014084507 | AB75: 0.353 | AC75: -0.0028328612 | AD75: 0.367 | AE75: 0.15641666 | AF75: 0.013416663 | AG75: 0.13641666 | AH75: 0.016416663 | AI75: 0.32266665 | AJ75: 0.33419544 | AK75: 1388.3945 | AL75: D- | AM75: 0.33D- | AN75: =_xlfn.CONCAT(_xlfn.IFS( AJ75>=0.7,"Superb", AJ75>=0.51,"Excellent", AJ75>=0.41,"Good", AJ75>=0.31,"Satisfactory", AJ75>=0.26,"Moderate", AJ75>=0.1,"Weak", AJ75<0.1,"Very Weak" ), " Economic Resilience with ",_xlfn.IFS( AK75<=2500,"Very Weak", AK75<=5000,"Poor", AK75<=10000,"Challenging", AK75<=12500,"Border Line", AK75<=15000,"Improved", AK75<=20000,"Moderate", AK75<=25000,"Satisfactory", AK75<=30000,"Good", AK75<=35000,"Very Good", AK75<=40000,"High", AK75<=50000,"Excellent", AK75<=100000,"Superb", AK75>100000,"Superb" ), " Affordability.") -> Satisfactory Economic Resilience with Very Weak Affordability. | AP75: We will assume the 5 socio economic sector spending will increase by 5% every year, Socio Ecnomic Sectors are Health, Housing, Energy and Education. Based on this assumption we will predict the value of Heart next year
A76: =_xlfn.CONCAT(UPPER(B76),"|",C76) -> INDONESIA|2021 | B76: Indonesia | C76: 2021 | D76: 96140000000000 | E76: 0.13439528 | F76: 7950000000 | G76: 0.0076045627 | H76: 1190000000000 | I76: 0.12264151 | J76: 276758053 | K76: 0.0070708948 | L76: 0.012377782 | M76: 222924000000 | N76: 254109500000 | O76: 31185500000 | P76: 0.026206303 | Q76: 0.411 | R76: 0.035264484 | S76: 489090000000 | T76: 0.035 | U76: 17118150000 | V76: 0.014385 | W76: 0.01560079 | X76: 4299.7845 | Y76: 4232.7045 | Z76: 0.71 | AA76: -0.013888889 | AB76: 0.355 | AC76: 0.0056338028 | AD76: 0.355 | AE76: 0.16066228 | AF76: 0.017662277 | AG76: 0.14066228 | AH76: 0.020662277 | AI76: 0.33964911 | AJ76: 0.36384819 | AK76: 1502.6101 | AL76: D- | AM76: 0.36D- | AN76: =_xlfn.CONCAT(_xlfn.IFS( AJ76>=0.7,"Superb", AJ76>=0.51,"Excellent", AJ76>=0.41,"Good", AJ76>=0.31,"Satisfactory", AJ76>=0.26,"Moderate", AJ76>=0.1,"Weak", AJ76<0.1,"Very Weak" ), " Economic Resilience with ",_xlfn.IFS( AK76<=2500,"Very Weak", AK76<=5000,"Poor", AK76<=10000,"Challenging", AK76<=12500,"Border Line", AK76<=15000,"Improved", AK76<=20000,"Moderate", AK76<=25000,"Satisfactory", AK76<=30000,"Good", AK76<=35000,"Very Good", AK76<=40000,"High", AK76<=50000,"Excellent", AK76<=100000,"Superb", AK76>100000,"Superb" ), " Affordability.") -> Satisfactory Economic Resilience with Very Weak Affordability. | AP76: We will assume the 5 socio economic sector spending will increase by 5% every year, Socio Ecnomic Sectors are Health, Housing, Energy and Education. Based on this assumption we will predict the value of Heart next year
A77: =_xlfn.CONCAT(UPPER(B77),"|",C77) -> INDONESIA|2022 | B77: Indonesia | C77: 2022 | D77: 101560000000000 | E77: 0.056376118 | F77: 8020000000 | G77: 0.0088050314 | H77: 1320000000000 | I77: 0.1092437 | J77: 278830529 | K77: 0.0074884036 | L77: 0.012997243 | M77: 276507000000 | N77: 323218200000 | O77: 46711200000 | P77: 0.035387273 | Q77: 0.397 | R77: -0.03406326 | S77: 524040000000 | T77: 0.035 | U77: 18341400000 | V77: 0.013895 | W77: 0.04209465 | X77: 4734.0584 | Y77: 4534.7798 | Z77: 0.71 | AA77: 0 | AB77: 0.355 | AC77: 0 | AD77: 0.355 | AE77: 0.16513134 | AF77: 0.022131344 | AG77: 0.14513134 | AH77: 0.025131344 | AI77: 0.35752537 | AJ77: 0.39201489 | AK77: 1609.8468 | AL77: D- | AM77: 0.39D- | AN77: =_xlfn.CONCAT(_xlfn.IFS( AJ77>=0.7,"Superb", AJ77>=0.51,"Excellent", AJ77>=0.41,"Good", AJ77>=0.31,"Satisfactory", AJ77>=0.26,"Moderate", AJ77>=0.1,"Weak", AJ77<0.1,"Very Weak" ), " Economic Resilience with ",_xlfn.IFS( AK77<=2500,"Very Weak", AK77<=5000,"Poor", AK77<=10000,"Challenging", AK77<=12500,"Border Line", AK77<=15000,"Improved", AK77<=20000,"Moderate", AK77<=25000,"Satisfactory", AK77<=30000,"Good", AK77<=35000,"Very Good", AK77<=40000,"High", AK77<=50000,"Excellent", AK77<=100000,"Superb", AK77>100000,"Superb" ), " Affordability.") -> Satisfactory Economic Resilience with Very Weak Affordability. | AP77: We will assume the 5 socio economic sector spending will increase by 5% every year, Socio Ecnomic Sectors are Health, Housing, Energy and Education. Based on this assumption we will predict the value of Heart next year
A78: =_xlfn.CONCAT(UPPER(B78),"|",C78) -> INDONESIA|2023 | B78: Indonesia | C78: 2023 | D78: 106800000000000 | E78: 0.051595116 | F78: 8090000000 | G78: 0.0087281796 | H78: 1370000000000 | I78: 0.037878788 | J78: 281190067 | K78: 0.0084622656 | L78: 0.012827715 | M78: 268508000000 | N78: 298282100000 | O78: 29774100000 | P78: 0.02173292 | Q78: 0.392 | R78: -0.012594458 | S78: 537040000000 | T78: 0.0575 | U78: 30879800000 | V78: 0.02254 | W78: 0.036693869999999996 | X78: 4872.1493 | Y78: 4693.3713 | Z78: 0.73 | AA78: 0.028169014 | AB78: 0.361 | AC78: 0.016620499 | AD78: 0.369 | AE78: 0.16983562 | AF78: 0.026835625 | AG78: 0.14983563 | AH78: 0.029835625 | AI78: 0.3763425 | AJ78: 0.38836314 | AK78: 1731.854 | AL78: D- | AM78: 0.39D- | AN78: =_xlfn.CONCAT(_xlfn.IFS( AJ78>=0.7,"Superb", AJ78>=0.51,"Excellent", AJ78>=0.41,"Good", AJ78>=0.31,"Satisfactory", AJ78>=0.26,"Moderate", AJ78>=0.1,"Weak", AJ78<0.1,"Very Weak" ), " Economic Resilience with ",_xlfn.IFS( AK78<=2500,"Very Weak", AK78<=5000,"Poor", AK78<=10000,"Challenging", AK78<=12500,"Border Line", AK78<=15000,"Improved", AK78<=20000,"Moderate", AK78<=25000,"Satisfactory", AK78<=30000,"Good", AK78<=35000,"Very Good", AK78<=40000,"High", AK78<=50000,"Excellent", AK78<=100000,"Superb", AK78>100000,"Superb" ), " Affordability.") -> Satisfactory Economic Resilience with Very Weak Affordability. | AP78: We will assume the 5 socio economic sector spending will increase by 5% every year, Socio Ecnomic Sectors are Health, Housing, Energy and Education. Based on this assumption we will predict the value of Heart next year
A79: =_xlfn.CONCAT(UPPER(B79),"|",C79) -> INDONESIA|2024 | B79: Indonesia | C79: 2024 | D79: 112600000000000 | E79: 0.054307116 | F79: 8161972572 | G79: 0.008896486 | H79: 1400000000000 | I79: 0.02189781 | J79: 283487931 | K79: 0.0081719245 | L79: 0.012433393 | M79: 284696000000 | N79: 309745600000 | O79: 25049600000 | P79: 0.017892571 | Q79: 0.388 | R79: -0.010204082 | S79: 543200000000 | T79: 0.0625 | U79: 33950000000 | V79: 0.02425 | W79: 0.02181513 | X79: 4938.4818 | Y79: 4830.7482 | Z79: 0.729 | AA79: -0.001369863 | AB79: 0.349 | AC79: -0.034383954 | AD79: 0.38 | AE79: 0.1747875 | AF79: 0.0317875 | AG79: 0.1547875 | AH79: 0.0347875 | AI79: 0.39615 | AJ79: 0.40222596 | AK79: 1835.6843 | AL79: D- | AM79: 0.4D- | AN79: =_xlfn.CONCAT(_xlfn.IFS( AJ79>=0.7,"Superb", AJ79>=0.51,"Excellent", AJ79>=0.41,"Good", AJ79>=0.31,"Satisfactory", AJ79>=0.26,"Moderate", AJ79>=0.1,"Weak", AJ79<0.1,"Very Weak" ), " Economic Resilience with ",_xlfn.IFS( AK79<=2500,"Very Weak", AK79<=5000,"Poor", AK79<=10000,"Challenging", AK79<=12500,"Border Line", AK79<=15000,"Improved", AK79<=20000,"Moderate", AK79<=25000,"Satisfactory", AK79<=30000,"Good", AK79<=35000,"Very Good", AK79<=40000,"High", AK79<=50000,"Excellent", AK79<=100000,"Superb", AK79>100000,"Superb" ), " Affordability.") -> Satisfactory Economic Resilience with Very Weak Affordability. | AP79: We will assume the 5 socio economic sector spending will increase by 5% every year, Socio Ecnomic Sectors are Health, Housing, Energy and Education. Based on this assumption we will predict the value of Heart next year
A80: =_xlfn.CONCAT(UPPER(B80),"|",C80) -> INDONESIA|2025 | B80: Indonesia | C80: 2025 | D80: 113795678000000 | E80: 0.01061881 | F80: 8231613070 | G80: 0.0085323122 | H80: 1429743000000 | I80: 0.021245 | J80: 285000000 | K80: 0.0053338038 | L80: 0.012564124 | M80: 283250000000 | N80: 313150000000 | O80: 29900000000 | P80: 0.020912849 | Q80: 0.40499999 | R80: 0.043814406 | S80: 579045900000 | T80: 0.055 | U80: 31847524500 | V80: 0.022274999 | W80: 0.0187 | X80: 5016.6421 | Y80: 4922.8309 | Z80: 0.728 | AA80: -0.0013717421 | AB80: 0.379 | AC80: 0.079155673 | AD80: 0.349 | AE80: 0.18 | AF80: 0.037 | AG80: 0.16 | AH80: 0.04 | AI80: 0.417 | AJ80: 0.42820197 | AK80: 1718.068 | AL80: D- | AM80: 0.43D- | AN80: =_xlfn.CONCAT(_xlfn.IFS( AJ80>=0.7,"Superb", AJ80>=0.51,"Excellent", AJ80>=0.41,"Good", AJ80>=0.31,"Satisfactory", AJ80>=0.26,"Moderate", AJ80>=0.1,"Weak", AJ80<0.1,"Very Weak" ), " Economic Resilience with ",_xlfn.IFS( AK80<=2500,"Very Weak", AK80<=5000,"Poor", AK80<=10000,"Challenging", AK80<=12500,"Border Line", AK80<=15000,"Improved", AK80<=20000,"Moderate", AK80<=25000,"Satisfactory", AK80<=30000,"Good", AK80<=35000,"Very Good", AK80<=40000,"High", AK80<=50000,"Excellent", AK80<=100000,"Superb", AK80>100000,"Superb" ), " Affordability.") -> Good Economic Resilience with Very Weak Affordability. | AO80: 17th largest per GDP. Facing several economic challenges including low growth, Affordability and impact of global trade uncertain factors. | AP80: We will assume the 5 socio economic sector spending will increase by 5% every year, Socio Ecnomic Sectors are Health, Housing, Energy and Education. Based on this assumption we will predict the value of Heart next year
A81: =_xlfn.CONCAT(UPPER(B81),"|",C81) -> INDONESIA|2026 | B81: Indonesia | C81: 2026 | D81: 120063810405112 | E81: 0.055082342 | F81: 8302201675 | G81: 0.0085753064 | H81: 1508553792545 | I81: 0.055122349 | J81: 2.8727598e+08 | K81: 0.0079859102 | L81: 0.0125646 | M81: 315556285714 | N81: 357422428571 | O81: 41866142857 | P81: 0.027752502 | Q81: 0.42442944 | R81: 0.047973953 | S81: 640274641509 | T81: 0.056071429 | U81: 35901113827 | V81: 0.023798365 | W81: 0.025131104 | X81: 5251.2353 | Y81: 5119.266 | Z81: 0.73191161 | AA81: 0.0053730859 | AB81: 0.37574172 | AC81: -0.0086715959 | AD81: 0.35616989 | AE81: 0.1852125 | AF81: 0.0422125 | AG81: 0.1652125 | AH81: 0.0452125 | AI81: 0.43785 | AJ81: 0.45436874 | AK81: 1823.3284 | AL81: D- | AM81: 0.45D- | AN81: =_xlfn.CONCAT(_xlfn.IFS( AJ81>=0.7,"Superb", AJ81>=0.51,"Excellent", AJ81>=0.41,"Good", AJ81>=0.31,"Satisfactory", AJ81>=0.26,"Moderate", AJ81>=0.1,"Weak", AJ81<0.1,"Very Weak" ), " Economic Resilience with ",_xlfn.IFS( AK81<=2500,"Very Weak", AK81<=5000,"Poor", AK81<=10000,"Challenging", AK81<=12500,"Border Line", AK81<=15000,"Improved", AK81<=20000,"Moderate", AK81<=25000,"Satisfactory", AK81<=30000,"Good", AK81<=35000,"Very Good", AK81<=40000,"High", AK81<=50000,"Excellent", AK81<=100000,"Superb", AK81>100000,"Superb" ), " Affordability.") -> Good Economic Resilience with Very Weak Affordability. | AP81: We will assume the 5 socio economic sector spending will increase by 5% every year, Socio Ecnomic Sectors are Health, Housing, Energy and Education. Based on this assumption we will predict the value of Heart next year
A82: =_xlfn.CONCAT(UPPER(B82),"|",C82) -> INDONESIA|2027 | B82: Indonesia | C82: 2027 | D82: 125735541889780 | E82: 0.047239309 | F82: 8372937901 | G82: 0.0085201769 | H82: 1578641747568 | I82: 0.046460362 | J82: 2.894575e+08 | K82: 0.0075937977 | L82: 0.012555255 | M82: 333210821429 | N82: 379274114286 | O82: 46063292857 | P82: 0.029179067 | Q82: 0.43967996 | R82: 0.035931816 | S82: 694097141492 | T82: 0.057589286 | U82: 39972558595 | V82: 0.025320855 | W82: 0.024827858 | X82: 5453.7946 | Y82: 5318.3886 | Z82: 0.73537559 | AA82: 0.0047327917 | AB82: 0.37670713 | AC82: 0.0025627618 | AD82: 0.35866846 | AE82: 0.19068562 | AF82: 0.047685625 | AG82: 0.17068563 | AH82: 0.050685625 | AI82: 0.4597425 | AJ82: 0.47615597 | AK82: 1907.5382 | AL82: D- | AM82: 0.48D- | AN82: =_xlfn.CONCAT(_xlfn.IFS( AJ82>=0.7,"Superb", AJ82>=0.51,"Excellent", AJ82>=0.41,"Good", AJ82>=0.31,"Satisfactory", AJ82>=0.26,"Moderate", AJ82>=0.1,"Weak", AJ82<0.1,"Very Weak" ), " Economic Resilience with ",_xlfn.IFS( AK82<=2500,"Very Weak", AK82<=5000,"Poor", AK82<=10000,"Challenging", AK82<=12500,"Border Line", AK82<=15000,"Improved", AK82<=20000,"Moderate", AK82<=25000,"Satisfactory", AK82<=30000,"Good", AK82<=35000,"Very Good", AK82<=40000,"High", AK82<=50000,"Excellent", AK82<=100000,"Superb", AK82>100000,"Superb" ), " Affordability.") -> Good Economic Resilience with Very Weak Affordability. | AP82: We will assume the 5 socio economic sector spending will increase by 5% every year, Socio Ecnomic Sectors are Health, Housing, Energy and Education. Based on this assumption we will predict the value of Heart next year
A83: =_xlfn.CONCAT(UPPER(B83),"|",C83) -> INDONESIA|2028 | B83: Indonesia | C83: 2028 | D83: 131237442252096 | E83: 0.043757718 | F83: 8443822776 | G83: 0.0084659502 | H83: 1646137802725 | I83: 0.042755777 | J83: 2.9160927e+08 | K83: 0.0074338 | L83: 0.012543202 | M83: 350865357143 | N83: 401125800000 | O83: 50260442857 | P83: 0.030532342 | Q83: 0.45354592 | R83: 0.031536482 | S83: 746599084117 | T83: 0.059107143 | U83: 44129338722 | V83: 0.026807803 | W83: 0.024524611 | X83: 5645.0119 | Y83: 5506.5702 | Z83: 0.7386891 | AA83: 0.0045058757 | AB83: 0.37912329 | AC83: 0.0063730096 | AD83: 0.35956582 | AE83: 0.19643241 | AF83: 0.053432406 | AG83: 0.17643241 | AH83: 0.056432406 | AI83: 0.48272962 | AJ83: 0.49899737 | AK83: 1979.9744 | AL83: D- | AM83: 0.5D- | AN83: =_xlfn.CONCAT(_xlfn.IFS( AJ83>=0.7,"Superb", AJ83>=0.51,"Excellent", AJ83>=0.41,"Good", AJ83>=0.31,"Satisfactory", AJ83>=0.26,"Moderate", AJ83>=0.1,"Weak", AJ83<0.1,"Very Weak" ), " Economic Resilience with ",_xlfn.IFS( AK83<=2500,"Very Weak", AK83<=5000,"Poor", AK83<=10000,"Challenging", AK83<=12500,"Border Line", AK83<=15000,"Improved", AK83<=20000,"Moderate", AK83<=25000,"Satisfactory", AK83<=30000,"Good", AK83<=35000,"Very Good", AK83<=40000,"High", AK83<=50000,"Excellent", AK83<=100000,"Superb", AK83>100000,"Superb" ), " Affordability.") -> Good Economic Resilience with Very Weak Affordability. | AP83: We will assume the 5 socio economic sector spending will increase by 5% every year, Socio Ecnomic Sectors are Health, Housing, Energy and Education. Based on this assumption we will predict the value of Heart next year
A84: =_xlfn.CONCAT(UPPER(B84),"|",C84) -> INDONESIA|2029 | B84: Indonesia | C84: 2029 | D84: 136712479650225 | E84: 0.041718562 | F84: 8514849364 | G84: 0.0084116625 | H84: 1713101714869 | I84: 0.040679409 | J84: 2.9375272e+08 | K84: 0.0073504212 | L84: 0.01253069 | M84: 368519892857 | N84: 422977485714 | O84: 54457592857 | P84: 0.031788885 | Q84: 0.46698122 | R84: 0.029622802 | S84: 799986330529 | T84: 0.060625 | U84: 48499171288 | V84: 0.028310737 | W84: 0.024221364 | X84: 5831.7816 | Y84: 5690.5279 | Z84: 0.74195102 | AA84: 0.0044158158 | AB84: 0.38206068 | AC84: 0.0076882853 | AD84: 0.35989034 | AE84: 0.20246653 | AF84: 0.059466527 | AG84: 0.18246653 | AH84: 0.062466527 | AI84: 0.50686611 | AJ84: 0.52287494 | AK84: 2047.966 | AL84: D- | AM84: 0.52D- | AN84: =_xlfn.CONCAT(_xlfn.IFS( AJ84>=0.7,"Superb", AJ84>=0.51,"Excellent", AJ84>=0.41,"Good", AJ84>=0.31,"Satisfactory", AJ84>=0.26,"Moderate", AJ84>=0.1,"Weak", AJ84<0.1,"Very Weak" ), " Economic Resilience with ",_xlfn.IFS( AK84<=2500,"Very Weak", AK84<=5000,"Poor", AK84<=10000,"Challenging", AK84<=12500,"Border Line", AK84<=15000,"Improved", AK84<=20000,"Moderate", AK84<=25000,"Satisfactory", AK84<=30000,"Good", AK84<=35000,"Very Good", AK84<=40000,"High", AK84<=50000,"Excellent", AK84<=100000,"Superb", AK84>100000,"Superb" ), " Affordability.") -> Excellent Economic Resilience with Very Weak Affordability. | AP84: We will assume the 5 socio economic sector spending will increase by 5% every year, Socio Ecnomic Sectors are Health, Housing, Energy and Education. Based on this assumption we will predict the value of Heart next year
A85: =_xlfn.CONCAT(UPPER(B85),"|",C85) -> INDONESIA|2030 | B85: Indonesia | C85: 2030 | D85: 141834754671550 | F85: 8586617399 | H85: 1777491512403 | J85: 2.9588243e+08 | L85: 0.012532129 | M85: 386174428571 | N85: 444829171429 | O85: 58654742857 | P85: 0.032998606 | Q85: 0.48032333 | S85: 853770646815 | T85: 0.062142857 | U85: 53055747338 | V85: 0.029848664 | W85: 0.023918117 | X85: 6007.4249 | Y85: 5863.7386 | Z85: 0.74519576 | AB85: 0.3851937 | AD85: 0.36000206 | AE85: 0.20880235 | AF85: 0.065802353 | AG85: 0.18880235 | AH85: 0.068802353 | AI85: 0.53220941 | AJ85: 0.54789148 | AK85: 2110.958 | AL85: D- | AM85: 0.55D- | AN85: =_xlfn.CONCAT(_xlfn.IFS( AJ85>=0.7,"Superb", AJ85>=0.51,"Excellent", AJ85>=0.41,"Good", AJ85>=0.31,"Satisfactory", AJ85>=0.26,"Moderate", AJ85>=0.1,"Weak", AJ85<0.1,"Very Weak" ), " Economic Resilience with ",_xlfn.IFS( AK85<=2500,"Very Weak", AK85<=5000,"Poor", AK85<=10000,"Challenging", AK85<=12500,"Border Line", AK85<=15000,"Improved", AK85<=20000,"Moderate", AK85<=25000,"Satisfactory", AK85<=30000,"Good", AK85<=35000,"Very Good", AK85<=40000,"High", AK85<=50000,"Excellent", AK85<=100000,"Superb", AK85>100000,"Superb" ), " Affordability.") -> Excellent Economic Resilience with Very Weak Affordability. | AP85: We will assume the 5 socio economic sector spending will increase by 5% every year, Socio Ecnomic Sectors are Health, Housing, Energy and Education. Based on this assumption we will predict the value of Heart next year
A86: =_xlfn.CONCAT(UPPER(B86),"|",C86) -> BRAZIL|2019 | B86: Brazil | C86: 2019 | D86: 87700000000000 | F86: 7810000000 | H86: 1873288000000 | J86: 207455459 | L86: 0.021360182 | M86: 276634800000 | N86: 264563000000 | O86: -12071800000 | P86: -0.0064441773 | Q86: 0.926 | S86: 1734664688000 | T86: 0.065 | U86: 112753204720 | V86: 0.06019 | W86: 0.03732976 | X86: 9029.8323 | Y86: 8692.7508 | Z86: 0.776 | AB86: 0.535 | AD86: 0.241 | AE86: 0.0830456 | AF86: 0.0670456 | AG86: 0.0760456 | AH86: 0.0730456 | AI86: 0.2991824 | AJ86: 0.2539084 | AK86: 2094.9529 | AL86: D- | AM86: 0.25D- | AN86: =_xlfn.CONCAT(_xlfn.IFS( AJ86>=0.7,"Superb", AJ86>=0.51,"Excellent", AJ86>=0.41,"Good", AJ86>=0.31,"Satisfactory", AJ86>=0.26,"Moderate", AJ86>=0.1,"Weak", AJ86<0.1,"Very Weak" ), " Economic Resilience with ",_xlfn.IFS( AK86<=2500,"Very Weak", AK86<=5000,"Poor", AK86<=10000,"Challenging", AK86<=12500,"Border Line", AK86<=15000,"Improved", AK86<=20000,"Moderate", AK86<=25000,"Satisfactory", AK86<=30000,"Good", AK86<=35000,"Very Good", AK86<=40000,"High", AK86<=50000,"Excellent", AK86<=100000,"Superb", AK86>100000,"Superb" ), " Affordability.") -> Weak Economic Resilience with Very Weak Affordability. | AP86: We will assume the 5 socio economic sector spending will increase by 5% every year, Socio Ecnomic Sectors are Health, Housing, Energy and Education. Based on this assumption we will predict the value of Heart next year
A87: =_xlfn.CONCAT(UPPER(B87),"|",C87) -> BRAZIL|2020 | B87: Brazil | C87: 2020 | D87: 84750000000000 | E87: -0.0336374 | F87: 7890000000 | G87: 0.010243278 | H87: 1476107000000 | I87: -0.21202346 | J87: 208660842 | K87: 0.0058103219 | L87: 0.017417192 | M87: 233941300000 | N87: 242872100000 | O87: 8930800000 | P87: 0.0060502389 | Q87: 0.987 | R87: 0.06587473 | S87: 1456917609000 | T87: 0.02 | U87: 29138352180 | V87: 0.01974 | W87: 0.03211768 | X87: 7074.1927 | Y87: 6846.986 | Z87: 0.77 | AA87: -0.0077319588 | AB87: 0.489 | AC87: -0.09406953 | AD87: 0.281 | AE87: 0.08698221 | AF87: 0.07098221 | AG87: 0.07998221 | AH87: 0.07698221 | AI87: 0.31492884 | AJ87: 0.31865627 | AK87: 1924.0031 | AL87: D- | AM87: 0.32D- | AN87: =_xlfn.CONCAT(_xlfn.IFS( AJ87>=0.7,"Superb", AJ87>=0.51,"Excellent", AJ87>=0.41,"Good", AJ87>=0.31,"Satisfactory", AJ87>=0.26,"Moderate", AJ87>=0.1,"Weak", AJ87<0.1,"Very Weak" ), " Economic Resilience with ",_xlfn.IFS( AK87<=2500,"Very Weak", AK87<=5000,"Poor", AK87<=10000,"Challenging", AK87<=12500,"Border Line", AK87<=15000,"Improved", AK87<=20000,"Moderate", AK87<=25000,"Satisfactory", AK87<=30000,"Good", AK87<=35000,"Very Good", AK87<=40000,"High", AK87<=50000,"Excellent", AK87<=100000,"Superb", AK87>100000,"Superb" ), " Affordability.") -> Satisfactory Economic Resilience with Very Weak Affordability. | AP87: We will assume the 5 socio economic sector spending will increase by 5% every year, Socio Ecnomic Sectors are Health, Housing, Energy and Education. Based on this assumption we will predict the value of Heart next year
A88: =_xlfn.CONCAT(UPPER(B88),"|",C88) -> BRAZIL|2021 | B88: Brazil | C88: 2021 | D88: 96140000000000 | E88: 0.13439528 | F88: 7950000000 | G88: 0.0076045627 | H88: 1670647000000 | I88: 0.13179261 | J88: 209550294 | K88: 0.0042626685 | L88: 0.017377231 | M88: 309853300000 | N88: 319251200000 | O88: 9397900000 | P88: 0.0056253056 | Q88: 0.85 | R88: -0.13880446 | S88: 1420049950000 | T88: 0.0925 | U88: 131354620375 | V88: 0.078625 | W88: 0.0830166 | X88: 7972.5347 | Y88: 7310.682 | Z88: 0.768 | AA88: -0.0025974026 | AB88: 0.529 | AC88: 0.075614367 | AD88: 0.239 | AE88: 0.091126011 | AF88: 0.075126011 | AG88: 0.084126011 | AH88: 0.081126011 | AI88: 0.33150404 | AJ88: 0.27588158 | AK88: 1747.253 | AL88: D- | AM88: 0.28D- | AN88: =_xlfn.CONCAT(_xlfn.IFS( AJ88>=0.7,"Superb", AJ88>=0.51,"Excellent", AJ88>=0.41,"Good", AJ88>=0.31,"Satisfactory", AJ88>=0.26,"Moderate", AJ88>=0.1,"Weak", AJ88<0.1,"Very Weak" ), " Economic Resilience with ",_xlfn.IFS( AK88<=2500,"Very Weak", AK88<=5000,"Poor", AK88<=10000,"Challenging", AK88<=12500,"Border Line", AK88<=15000,"Improved", AK88<=20000,"Moderate", AK88<=25000,"Satisfactory", AK88<=30000,"Good", AK88<=35000,"Very Good", AK88<=40000,"High", AK88<=50000,"Excellent", AK88<=100000,"Superb", AK88>100000,"Superb" ), " Affordability.") -> Moderate Economic Resilience with Very Weak Affordability. | AP88: We will assume the 5 socio economic sector spending will increase by 5% every year, Socio Ecnomic Sectors are Health, Housing, Energy and Education. Based on this assumption we will predict the value of Heart next year
A89: =_xlfn.CONCAT(UPPER(B89),"|",C89) -> BRAZIL|2022 | B89: Brazil | C89: 2022 | D89: 101560000000000 | E89: 0.056376118 | F89: 8020000000 | G89: 0.0088050314 | H89: 1951924000000 | I89: 0.16836411 | J89: 210306415 | K89: 0.0036083032 | L89: 0.019219417 | M89: 374482500000 | N89: 383177600000 | O89: 8695100000 | P89: 0.0044546304 | Q89: 0.791 | R89: -0.069411765 | S89: 1543971884000 | T89: 0.1375 | U89: 212296134050 | V89: 0.1087625 | W89: 0.09280106 | X89: 9281.3336 | Y89: 8420.016 | Z89: 0.78 | AA89: 0.015625 | AB89: 0.52 | AC89: -0.017307692 | AD89: 0.26 | AE89: 0.095487906 | AF89: 0.079487906 | AG89: 0.088487906 | AH89: 0.085487906 | AI89: 0.34895162 | AJ89: 0.26386317 | AK89: 2189.2042 | AL89: D- | AM89: 0.26D- | AN89: =_xlfn.CONCAT(_xlfn.IFS( AJ89>=0.7,"Superb", AJ89>=0.51,"Excellent", AJ89>=0.41,"Good", AJ89>=0.31,"Satisfactory", AJ89>=0.26,"Moderate", AJ89>=0.1,"Weak", AJ89<0.1,"Very Weak" ), " Economic Resilience with ",_xlfn.IFS( AK89<=2500,"Very Weak", AK89<=5000,"Poor", AK89<=10000,"Challenging", AK89<=12500,"Border Line", AK89<=15000,"Improved", AK89<=20000,"Moderate", AK89<=25000,"Satisfactory", AK89<=30000,"Good", AK89<=35000,"Very Good", AK89<=40000,"High", AK89<=50000,"Excellent", AK89<=100000,"Superb", AK89>100000,"Superb" ), " Affordability.") -> Moderate Economic Resilience with Very Weak Affordability. | AP89: We will assume the 5 socio economic sector spending will increase by 5% every year, Socio Ecnomic Sectors are Health, Housing, Energy and Education. Based on this assumption we will predict the value of Heart next year
A90: =_xlfn.CONCAT(UPPER(B90),"|",C90) -> BRAZIL|2023 | B90: Brazil | C90: 2023 | D90: 106800000000000 | E90: 0.051595116 | F90: 8090000000 | G90: 0.0087281796 | H90: 2191132000000 | I90: 0.12254985 | J90: 211140729 | K90: 0.0039671353 | L90: 0.020516217 | M90: 343939900000 | N90: 393731600000 | O90: 49791700000 | P90: 0.02272419 | Q90: 0.83 | R90: 0.049304678 | S90: 1818639560000 | T90: 0.1175 | U90: 213690148300 | V90: 0.097525 | W90: 0.04593563 | X90: 10377.59 | Y90: 9900.8892 | Z90: 0.783 | AA90: 0.0038461538 | AB90: 0.516 | AC90: -0.007751938 | AD90: 0.267 | AE90: 0.10007937 | AF90: 0.084079375 | AG90: 0.093079375 | AH90: 0.090079375 | AI90: 0.3673175 | AJ90: 0.31303291 | AK90: 2643.5374 | AL90: D | AM90: 0.31D | AN90: =_xlfn.CONCAT(_xlfn.IFS( AJ90>=0.7,"Superb", AJ90>=0.51,"Excellent", AJ90>=0.41,"Good", AJ90>=0.31,"Satisfactory", AJ90>=0.26,"Moderate", AJ90>=0.1,"Weak", AJ90<0.1,"Very Weak" ), " Economic Resilience with ",_xlfn.IFS( AK90<=2500,"Very Weak", AK90<=5000,"Poor", AK90<=10000,"Challenging", AK90<=12500,"Border Line", AK90<=15000,"Improved", AK90<=20000,"Moderate", AK90<=25000,"Satisfactory", AK90<=30000,"Good", AK90<=35000,"Very Good", AK90<=40000,"High", AK90<=50000,"Excellent", AK90<=100000,"Superb", AK90>100000,"Superb" ), " Affordability.") -> Satisfactory Economic Resilience with Poor Affordability. | AP90: We will assume the 5 socio economic sector spending will increase by 5% every year, Socio Ecnomic Sectors are Health, Housing, Energy and Education. Based on this assumption we will predict the value of Heart next year
A91: =_xlfn.CONCAT(UPPER(B91),"|",C91) -> BRAZIL|2024 | B91: Brazil | C91: 2024 | D91: 112600000000000 | E91: 0.054307116 | F91: 8161972572 | G91: 0.008896486 | H91: 2185822000000 | I91: -0.0024234049 | J91: 211998573 | K91: 0.0040629016 | L91: 0.019412274 | M91: 385708900000 | N91: 392105400000 | O91: 6396500000 | P91: 0.0029263591 | Q91: 0.819 | R91: -0.013253012 | S91: 1790188218000 | T91: 0.1225 | U91: 219298056705 | V91: 0.1003275 | W91: 0.04367464 | X91: 10310.551 | Y91: 9860.241 | Z91: 0.7845 | AA91: 0.0019157088 | AB91: 0.516 | AC91: 0 | AD91: 0.2685 | AE91: 0.1049125 | AF91: 0.0889125 | AG91: 0.0979125 | AH91: 0.0949125 | AI91: 0.38665 | AJ91: 0.30866113 | AK91: 2647.4747 | AL91: D | AM91: 0.31D | AN91: =_xlfn.CONCAT(_xlfn.IFS( AJ91>=0.7,"Superb", AJ91>=0.51,"Excellent", AJ91>=0.41,"Good", AJ91>=0.31,"Satisfactory", AJ91>=0.26,"Moderate", AJ91>=0.1,"Weak", AJ91<0.1,"Very Weak" ), " Economic Resilience with ",_xlfn.IFS( AK91<=2500,"Very Weak", AK91<=5000,"Poor", AK91<=10000,"Challenging", AK91<=12500,"Border Line", AK91<=15000,"Improved", AK91<=20000,"Moderate", AK91<=25000,"Satisfactory", AK91<=30000,"Good", AK91<=35000,"Very Good", AK91<=40000,"High", AK91<=50000,"Excellent", AK91<=100000,"Superb", AK91>100000,"Superb" ), " Affordability.") -> Moderate Economic Resilience with Poor Affordability. | AP91: We will assume the 5 socio economic sector spending will increase by 5% every year, Socio Ecnomic Sectors are Health, Housing, Energy and Education. Based on this assumption we will predict the value of Heart next year
A92: =_xlfn.CONCAT(UPPER(B92),"|",C92) -> BRAZIL|2025 | B92: Brazil | C92: 2025 | D92: 113795678000000 | E92: 0.01061881 | F92: 8231613070 | G92: 0.0085323122 | H92: 2126000000000 | I92: -0.027368194 | J92: 212600000 | K92: 0.0028369389 | L92: 0.018682608 | M92: 300000000000 | N92: 374000000000 | O92: 74000000000 | P92: 0.03480715 | Q92: 0.8728 | R92: 0.065689866 | S92: 1855572800000 | T92: 0.15 | U92: 278335920000 | V92: 0.13092 | W92: 0.0437 | X92: 10000 | Y92: 9563 | Z92: 0.786 | AA92: 0.0019120459 | AB92: 0.516 | AC92: 0 | AD92: 0.27 | AE92: 0.11 | AF92: 0.094 | AG92: 0.103 | AH92: 0.1 | AI92: 0.407 | AJ92: 0.32956976 | AK92: 2582.01 | AL92: D | AM92: 0.33D | AN92: =_xlfn.CONCAT(_xlfn.IFS( AJ92>=0.7,"Superb", AJ92>=0.51,"Excellent", AJ92>=0.41,"Good", AJ92>=0.31,"Satisfactory", AJ92>=0.26,"Moderate", AJ92>=0.1,"Weak", AJ92<0.1,"Very Weak" ), " Economic Resilience with ",_xlfn.IFS( AK92<=2500,"Very Weak", AK92<=5000,"Poor", AK92<=10000,"Challenging", AK92<=12500,"Border Line", AK92<=15000,"Improved", AK92<=20000,"Moderate", AK92<=25000,"Satisfactory", AK92<=30000,"Good", AK92<=35000,"Very Good", AK92<=40000,"High", AK92<=50000,"Excellent", AK92<=100000,"Superb", AK92>100000,"Superb" ), " Affordability.") -> Satisfactory Economic Resilience with Poor Affordability. | AO92: 10th largest per GDP. Facing economic growth and US tarrifs challenges.High debt,rising inflation and low productivity compromised per capita income.Also must fix political uncertainity to focus on economic diversification. | AP92: We will assume the 5 socio economic sector spending will increase by 5% every year, Socio Ecnomic Sectors are Health, Housing, Energy and Education. Based on this assumption we will predict the value of Heart next year
A93: =_xlfn.CONCAT(UPPER(B93),"|",C93) -> BRAZIL|2026 | B93: Brazil | C93: 2026 | D93: 120063810405112 | E93: 0.055082342 | F93: 8302201675 | G93: 0.0085753064 | H93: 2250260162496 | I93: 0.058447866 | J93: 2.1355004e+08 | K93: 0.0044686941 | L93: 0.018742202 | M93: 376039728571 | N93: 438708414286 | O93: 62668685714 | P93: 0.027849529 | Q93: 0.83060417 | R93: -0.048345357 | S93: 1869075479804 | T93: 0.17 | U93: 317742831567 | V93: 0.14120271 | W93: 0.054817006 | X93: 10537.39 | Y93: 9959.7621 | Z93: 0.78824236 | AA93: 0.0028528785 | AB93: 0.51362886 | AC93: -0.0046164386 | AD93: 0.2746135 | AE93: 0.1150875 | AF93: 0.0990875 | AG93: 0.1080875 | AH93: 0.1050875 | AI93: 0.42735 | AJ93: 0.33273902 | AK93: 2735.0851 | AL93: D | AM93: 0.33D | AN93: =_xlfn.CONCAT(_xlfn.IFS( AJ93>=0.7,"Superb", AJ93>=0.51,"Excellent", AJ93>=0.41,"Good", AJ93>=0.31,"Satisfactory", AJ93>=0.26,"Moderate", AJ93>=0.1,"Weak", AJ93<0.1,"Very Weak" ), " Economic Resilience with ",_xlfn.IFS( AK93<=2500,"Very Weak", AK93<=5000,"Poor", AK93<=10000,"Challenging", AK93<=12500,"Border Line", AK93<=15000,"Improved", AK93<=20000,"Moderate", AK93<=25000,"Satisfactory", AK93<=30000,"Good", AK93<=35000,"Very Good", AK93<=40000,"High", AK93<=50000,"Excellent", AK93<=100000,"Superb", AK93>100000,"Superb" ), " Affordability.") -> Satisfactory Economic Resilience with Poor Affordability. | AP93: We will assume the 5 socio economic sector spending will increase by 5% every year, Socio Ecnomic Sectors are Health, Housing, Energy and Education. Based on this assumption we will predict the value of Heart next year
A94: =_xlfn.CONCAT(UPPER(B94),"|",C94) -> BRAZIL|2027 | B94: Brazil | C94: 2027 | D94: 125735541889780 | E94: 0.047239309 | F94: 8372937901 | G94: 0.0085201769 | H94: 2351950417757 | I94: 0.045190444 | J94: 2.1443592e+08 | K94: 0.0041483132 | L94: 0.018705534 | M94: 390601064286 | N94: 463753342857 | O94: 73152278571 | P94: 0.031102815 | Q94: 0.80704753 | R94: -0.028360849 | S94: 1898135781528 | T94: 0.18732143 | U94: 355561506218 | V94: 0.1511773 | W94: 0.055000708 | X94: 10968.081 | Y94: 10364.828 | Z94: 0.79059048 | AA94: 0.0029789276 | AB94: 0.51192011 | AC94: -0.003337939 | AD94: 0.27867037 | AE94: 0.12042938 | AF94: 0.10442938 | AG94: 0.11342937 | AH94: 0.11042937 | AI94: 0.4487175 | AJ94: 0.34734855 | AK94: 2888.3706 | AL94: D | AM94: 0.35D | AN94: =_xlfn.CONCAT(_xlfn.IFS( AJ94>=0.7,"Superb", AJ94>=0.51,"Excellent", AJ94>=0.41,"Good", AJ94>=0.31,"Satisfactory", AJ94>=0.26,"Moderate", AJ94>=0.1,"Weak", AJ94<0.1,"Very Weak" ), " Economic Resilience with ",_xlfn.IFS( AK94<=2500,"Very Weak", AK94<=5000,"Poor", AK94<=10000,"Challenging", AK94<=12500,"Border Line", AK94<=15000,"Improved", AK94<=20000,"Moderate", AK94<=25000,"Satisfactory", AK94<=30000,"Good", AK94<=35000,"Very Good", AK94<=40000,"High", AK94<=50000,"Excellent", AK94<=100000,"Superb", AK94>100000,"Superb" ), " Affordability.") -> Satisfactory Economic Resilience with Poor Affordability. | AP94: We will assume the 5 socio economic sector spending will increase by 5% every year, Socio Ecnomic Sectors are Health, Housing, Energy and Education. Based on this assumption we will predict the value of Heart next year
A95: =_xlfn.CONCAT(UPPER(B95),"|",C95) -> BRAZIL|2028 | B95: Brazil | C95: 2028 | D95: 131237442252096 | E95: 0.043757718 | F95: 8443822776 | G95: 0.0084659502 | H95: 2446323293071 | I95: 0.040125368 | J95: 2.1530045e+08 | K95: 0.0040316585 | L95: 0.018640437 | M95: 405162400000 | N95: 488798271429 | O95: 83635871429 | P95: 0.034188397 | Q95: 0.78982366 | R95: -0.021341832 | S95: 1932164016127 | T95: 0.20464286 | U95: 395403564729 | V95: 0.16163177 | W95: 0.055184411 | X95: 11362.37 | Y95: 10735.344 | Z95: 0.79297562 | AA95: 0.0030169063 | AB95: 0.51043686 | AC95: -0.0029058265 | AD95: 0.28253875 | AE95: 0.12603834 | AF95: 0.11003834 | AG95: 0.11903834 | AH95: 0.11603834 | AI95: 0.47115337 | AJ95: 0.36235044 | AK95: 3033.1507 | AL95: D | AM95: 0.36D | AN95: =_xlfn.CONCAT(_xlfn.IFS( AJ95>=0.7,"Superb", AJ95>=0.51,"Excellent", AJ95>=0.41,"Good", AJ95>=0.31,"Satisfactory", AJ95>=0.26,"Moderate", AJ95>=0.1,"Weak", AJ95<0.1,"Very Weak" ), " Economic Resilience with ",_xlfn.IFS( AK95<=2500,"Very Weak", AK95<=5000,"Poor", AK95<=10000,"Challenging", AK95<=12500,"Border Line", AK95<=15000,"Improved", AK95<=20000,"Moderate", AK95<=25000,"Satisfactory", AK95<=30000,"Good", AK95<=35000,"Very Good", AK95<=40000,"High", AK95<=50000,"Excellent", AK95<=100000,"Superb", AK95>100000,"Superb" ), " Affordability.") -> Satisfactory Economic Resilience with Poor Affordability. | AP95: We will assume the 5 socio economic sector spending will increase by 5% every year, Socio Ecnomic Sectors are Health, Housing, Energy and Education. Based on this assumption we will predict the value of Heart next year
A96: =_xlfn.CONCAT(UPPER(B96),"|",C96) -> BRAZIL|2029 | B96: Brazil | C96: 2029 | D96: 136712479650225 | E96: 0.041718562 | F96: 8514849364 | G96: 0.0084116625 | H96: 2538510628611 | I96: 0.037684036 | J96: 2.1615787e+08 | K96: 0.0039824606 | L96: 0.018568244 | M96: 419723735714 | N96: 513843200000 | O96: 94119464286 | P96: 0.037076648 | Q96: 0.77486129 | R96: -0.018943935 | S96: 1966993625023 | T96: 0.22196429 | U96: 436602334983 | V96: 0.17199153 | W96: 0.055368113 | X96: 11743.78 | Y96: 11093.55 | Z96: 0.79537485 | AA96: 0.0030256027 | AB96: 0.50903439 | AC96: -0.0027551601 | AD96: 0.28634045 | AE96: 0.13192776 | AF96: 0.11592776 | AG96: 0.12492776 | AH96: 0.12192776 | AI96: 0.49471104 | AJ96: 0.3783644 | AK96: 3176.532 | AL96: D | AM96: 0.38D | AN96: =_xlfn.CONCAT(_xlfn.IFS( AJ96>=0.7,"Superb", AJ96>=0.51,"Excellent", AJ96>=0.41,"Good", AJ96>=0.31,"Satisfactory", AJ96>=0.26,"Moderate", AJ96>=0.1,"Weak", AJ96<0.1,"Very Weak" ), " Economic Resilience with ",_xlfn.IFS( AK96<=2500,"Very Weak", AK96<=5000,"Poor", AK96<=10000,"Challenging", AK96<=12500,"Border Line", AK96<=15000,"Improved", AK96<=20000,"Moderate", AK96<=25000,"Satisfactory", AK96<=30000,"Good", AK96<=35000,"Very Good", AK96<=40000,"High", AK96<=50000,"Excellent", AK96<=100000,"Superb", AK96>100000,"Superb" ), " Affordability.") -> Satisfactory Economic Resilience with Poor Affordability. | AP96: We will assume the 5 socio economic sector spending will increase by 5% every year, Socio Ecnomic Sectors are Health, Housing, Energy and Education. Based on this assumption we will predict the value of Heart next year
A97: =_xlfn.CONCAT(UPPER(B97),"|",C97) -> BRAZIL|2030 | B97: Brazil | C97: 2030 | D97: 141834754671550 | F97: 8586617399 | H97: 2657145175791 | J97: 2.1695507e+08 | L97: 0.018734091 | M97: 434285071429 | N97: 538888128571 | O97: 104603057143 | P97: 0.039366708 | Q97: 0.76075177 | S97: 2021427904330 | T97: 0.23928571 | U97: 483698819965 | V97: 0.18203703 | W97: 0.055551816 | X97: 12247.444 | Y97: 11567.077 | Z97: 0.79778012 | AB97: 0.50766235 | AD97: 0.29011776 | AE97: 0.13811165 | AF97: 0.12211165 | AG97: 0.13111165 | AH97: 0.12811165 | AI97: 0.5194466 | AJ97: 0.39551036 | AK97: 3355.8144 | AL97: D | AM97: 0.4D | AN97: =_xlfn.CONCAT(_xlfn.IFS( AJ97>=0.7,"Superb", AJ97>=0.51,"Excellent", AJ97>=0.41,"Good", AJ97>=0.31,"Satisfactory", AJ97>=0.26,"Moderate", AJ97>=0.1,"Weak", AJ97<0.1,"Very Weak" ), " Economic Resilience with ",_xlfn.IFS( AK97<=2500,"Very Weak", AK97<=5000,"Poor", AK97<=10000,"Challenging", AK97<=12500,"Border Line", AK97<=15000,"Improved", AK97<=20000,"Moderate", AK97<=25000,"Satisfactory", AK97<=30000,"Good", AK97<=35000,"Very Good", AK97<=40000,"High", AK97<=50000,"Excellent", AK97<=100000,"Superb", AK97>100000,"Superb" ), " Affordability.") -> Satisfactory Economic Resilience with Poor Affordability. | AP97: We will assume the 5 socio economic sector spending will increase by 5% every year, Socio Ecnomic Sectors are Health, Housing, Energy and Education. Based on this assumption we will predict the value of Heart next year
A98: =_xlfn.CONCAT(UPPER(B98),"|",C98) -> TURKEY|2019 | B98: Turkey | C98: 2019 | D98: 87700000000000 | F98: 7810000000 | H98: 775853100000 | J98: 82579440 | L98: 0.0088466716 | M98: 229253600000 | N98: 256263400000 | O98: 27009800000 | P98: 0.034813034 | Q98: 0.33460074 | S98: 259601021391 | T98: 0.24 | U98: 62304245134 | V98: 0.080304178 | W98: 0.15176822 | X98: 9395.2332 | Y98: 7969.3354 | Z98: 0.842 | AB98: 0.438 | AD98: 0.404 | AE98: 0.16950259 | AF98: 0.021502594 | AG98: 0.074502594 | AH98: 0.017502594 | AI98: 0.28301038 | AJ98: 0.24636591 | AK98: 3219.6115 | AL98: D | AM98: 0.25D | AN98: =_xlfn.CONCAT(_xlfn.IFS( AJ98>=0.7,"Superb", AJ98>=0.51,"Excellent", AJ98>=0.41,"Good", AJ98>=0.31,"Satisfactory", AJ98>=0.26,"Moderate", AJ98>=0.1,"Weak", AJ98<0.1,"Very Weak" ), " Economic Resilience with ",_xlfn.IFS( AK98<=2500,"Very Weak", AK98<=5000,"Poor", AK98<=10000,"Challenging", AK98<=12500,"Border Line", AK98<=15000,"Improved", AK98<=20000,"Moderate", AK98<=25000,"Satisfactory", AK98<=30000,"Good", AK98<=35000,"Very Good", AK98<=40000,"High", AK98<=50000,"Excellent", AK98<=100000,"Superb", AK98>100000,"Superb" ), " Affordability.") -> Weak Economic Resilience with Poor Affordability. | AP98: We will assume the 5 socio economic sector spending will increase by 5% every year, Socio Ecnomic Sectors are Health, Housing, Energy and Education. Based on this assumption we will predict the value of Heart next year, In the case of Argentina we have assumed the 5% increase in inflation every year similarly with Interest Rate.
A99: =_xlfn.CONCAT(UPPER(B99),"|",C99) -> TURKEY|2020 | B99: Turkey | C99: 2020 | D99: 84750000000000 | E99: -0.0336374 | F99: 7890000000 | G99: 0.010243278 | H99: 733628200000 | I99: -0.054423834 | J99: 83384680 | K99: 0.0097510954 | L99: 0.0086563799 | M99: 232192200000 | N99: 210844800000 | O99: -21347400000 | P99: -0.029098391 | Q99: 0.41039652 | R99: 0.22652604 | S99: 301078460254 | T99: 0.0875 | U99: 26344365272 | V99: 0.035909695 | W99: 0.12278957 | X99: 8798.1174 | Y99: 7717.8003 | Z99: 0.835 | AA99: -0.0083135392 | AB99: 0.43 | AC99: -0.018604651 | AD99: 0.405 | AE99: 0.17322642 | AF99: 0.025226415 | AG99: 0.078226415 | AH99: 0.021226415 | AI99: 0.29790566 | AJ99: 0.24155395 | AK99: 3125.7091 | AL99: D | AM99: 0.24D | AN99: =_xlfn.CONCAT(_xlfn.IFS( AJ99>=0.7,"Superb", AJ99>=0.51,"Excellent", AJ99>=0.41,"Good", AJ99>=0.31,"Satisfactory", AJ99>=0.26,"Moderate", AJ99>=0.1,"Weak", AJ99<0.1,"Very Weak" ), " Economic Resilience with ",_xlfn.IFS( AK99<=2500,"Very Weak", AK99<=5000,"Poor", AK99<=10000,"Challenging", AK99<=12500,"Border Line", AK99<=15000,"Improved", AK99<=20000,"Moderate", AK99<=25000,"Satisfactory", AK99<=30000,"Good", AK99<=35000,"Very Good", AK99<=40000,"High", AK99<=50000,"Excellent", AK99<=100000,"Superb", AK99>100000,"Superb" ), " Affordability.") -> Weak Economic Resilience with Poor Affordability. | AP99: We will assume the 5 socio economic sector spending will increase by 5% every year, Socio Ecnomic Sectors are Health, Housing, Energy and Education. Based on this assumption we will predict the value of Heart next year, In the case of Argentina we have assumed the 5% increase in inflation every year similarly with Interest Rate.
A100: =_xlfn.CONCAT(UPPER(B100),"|",C100) -> TURKEY|2021 | B100: Turkey | C100: 2021 | D100: 96140000000000 | E100: 0.13439528 | F100: 7950000000 | G100: 0.0076045627 | H100: 839938700000 | I100: 0.1449106 | J100: 84147318 | K100: 0.0091460206 | L100: 0.0087366206 | M100: 290243000000 | N100: 294429000000 | O100: 4186000000 | P100: 0.004983697 | Q100: 0.41637512 | R100: 0.014567862 | S100: 349729577005 | T100: 0.19 | U100: 66448619631 | V100: 0.079111273 | W100: 0.19596493 | X100: 9981.7644 | Y100: 8025.6886 | Z100: 0.841 | AA100: 0.0071856287 | AB100: 0.444 | AC100: 0.031531532 | AD100: 0.397 | AE100: 0.17714623 | AF100: 0.029146227 | AG100: 0.082146227 | AH100: 0.025146227 | AI100: 0.31358491 | AJ100: 0.24819395 | AK100: 3186.1984 | AL100: D | AM100: 0.25D | AN100: =_xlfn.CONCAT(_xlfn.IFS( AJ100>=0.7,"Superb", AJ100>=0.51,"Excellent", AJ100>=0.41,"Good", AJ100>=0.31,"Satisfactory", AJ100>=0.26,"Moderate", AJ100>=0.1,"Weak", AJ100<0.1,"Very Weak" ), " Economic Resilience with ",_xlfn.IFS( AK100<=2500,"Very Weak", AK100<=5000,"Poor", AK100<=10000,"Challenging", AK100<=12500,"Border Line", AK100<=15000,"Improved", AK100<=20000,"Moderate", AK100<=25000,"Satisfactory", AK100<=30000,"Good", AK100<=35000,"Very Good", AK100<=40000,"High", AK100<=50000,"Excellent", AK100<=100000,"Superb", AK100>100000,"Superb" ), " Affordability.") -> Weak Economic Resilience with Poor Affordability. | AP100: We will assume the 5 socio economic sector spending will increase by 5% every year, Socio Ecnomic Sectors are Health, Housing, Energy and Education. Based on this assumption we will predict the value of Heart next year, In the case of Argentina we have assumed the 5% increase in inflation every year similarly with Interest Rate.
...

Sheet Preprocessing1
A1: Year | B1: ='G20+3 Countries'!B3 -> 2025
A3: ='G20+3 Countries'!B4 -> 2025 - HEART SCORE G-20+2 RANKING | C3: Country | D3: Heart Value | E3: Heart Affordibility Value | F3: HEART SCORE | G3: Brief Description of HEART Scores
A4: RESILIENCE | B4: AFFORDABILITY
A5: =_xlfn.RANK.EQ(D5,$D$5:$D$26,0) -> 20 | B5: =_xlfn.RANK.EQ(E5,$E$5:$E$26,0) -> 17 | C5: ARGENTINA | D5: =VLOOKUP(_xlfn.CONCAT(UPPER(C5),"|",$B$1),MasterSheet_WithPredictive!A:AP,36,FALSE) -> 0.21731494 | E5: =VLOOKUP(_xlfn.CONCAT(UPPER(C5),"|",$B$1),MasterSheet_WithPredictive!A:AP,37,FALSE) -> 4641.7306 | F5: =VLOOKUP(_xlfn.CONCAT(UPPER(C5),"|",$B$1),MasterSheet_WithPredictive!A:AP,39,FALSE) -> 0.22D | G5: =VLOOKUP(_xlfn.CONCAT(UPPER(C5),"|",$B$1),MasterSheet_WithPredictive!A:AP,40,FALSE) -> Weak Economic Resilience with Poor Affordability.
A6: =_xlfn.RANK.EQ(D6,$D$5:$D$26,0) -> 17 | B6: =_xlfn.RANK.EQ(E6,$E$5:$E$26,0) -> 4 | C6: AUSTRALIA | D6: =VLOOKUP(_xlfn.CONCAT(UPPER(C6),"|",$B$1),MasterSheet_WithPredictive!A:AP,36,FALSE) -> 0.33887795 | E6: =VLOOKUP(_xlfn.CONCAT(UPPER(C6),"|",$B$1),MasterSheet_WithPredictive!A:AP,37,FALSE) -> 39300.547 | F6: =VLOOKUP(_xlfn.CONCAT(UPPER(C6),"|",$B$1),MasterSheet_WithPredictive!A:AP,39,FALSE) -> 0.34A- | G6: =VLOOKUP(_xlfn.CONCAT(UPPER(C6),"|",$B$1),MasterSheet_WithPredictive!A:AP,40,FALSE) -> Satisfactory Economic Resilience with High Affordability.
A7: =_xlfn.RANK.EQ(D7,$D$5:$D$26,0) -> 18 | B7: =_xlfn.RANK.EQ(E7,$E$5:$E$26,0) -> 19 | C7: BRAZIL | D7: =VLOOKUP(_xlfn.CONCAT(UPPER(C7),"|",$B$1),MasterSheet_WithPredictive!A:AP,36,FALSE) -> 0.32956976 | E7: =VLOOKUP(_xlfn.CONCAT(UPPER(C7),"|",$B$1),MasterSheet_WithPredictive!A:AP,37,FALSE) -> 2582.01 | F7: =VLOOKUP(_xlfn.CONCAT(UPPER(C7),"|",$B$1),MasterSheet_WithPredictive!A:AP,39,FALSE) -> 0.33D | G7: =VLOOKUP(_xlfn.CONCAT(UPPER(C7),"|",$B$1),MasterSheet_WithPredictive!A:AP,40,FALSE) -> Satisfactory Economic Resilience with Poor Affordability.
A8: =_xlfn.RANK.EQ(D8,$D$5:$D$26,0) -> 12 | B8: =_xlfn.RANK.EQ(E8,$E$5:$E$26,0) -> 6 | C8: CANADA | D8: =VLOOKUP(_xlfn.CONCAT(UPPER(C8),"|",$B$1),MasterSheet_WithPredictive!A:AP,36,FALSE) -> 0.41057598 | E8: =VLOOKUP(_xlfn.CONCAT(UPPER(C8),"|",$B$1),MasterSheet_WithPredictive!A:AP,37,FALSE) -> 34043.939 | F8: =VLOOKUP(_xlfn.CONCAT(UPPER(C8),"|",$B$1),MasterSheet_WithPredictive!A:AP,39,FALSE) -> 0.41B+ | G8: =VLOOKUP(_xlfn.CONCAT(UPPER(C8),"|",$B$1),MasterSheet_WithPredictive!A:AP,40,FALSE) -> Good Economic Resilience with Very Good Affordability.
A9: =_xlfn.RANK.EQ(D9,$D$5:$D$26,0) -> 2 | B9: =_xlfn.RANK.EQ(E9,$E$5:$E$26,0) -> 15 | C9: CHINA | D9: =VLOOKUP(_xlfn.CONCAT(UPPER(C9),"|",$B$1),MasterSheet_WithPredictive!A:AP,36,FALSE) -> 0.72928133 | E9: =VLOOKUP(_xlfn.CONCAT(UPPER(C9),"|",$B$1),MasterSheet_WithPredictive!A:AP,37,FALSE) -> 5918.047 | F9: =VLOOKUP(_xlfn.CONCAT(UPPER(C9),"|",$B$1),MasterSheet_WithPredictive!A:AP,39,FALSE) -> 0.73D+ | G9: =VLOOKUP(_xlfn.CONCAT(UPPER(C9),"|",$B$1),MasterSheet_WithPredictive!A:AP,40,FALSE) -> Superb Economic Resilience with Challenging Affordability.
A10: =_xlfn.RANK.EQ(D10,$D$5:$D$26,0) -> 10 | B10: =_xlfn.RANK.EQ(E10,$E$5:$E$26,0) -> 8 | C10: FRANCE | D10: =VLOOKUP(_xlfn.CONCAT(UPPER(C10),"|",$B$1),MasterSheet_WithPredictive!A:AP,36,FALSE) -> 0.44373071 | E10: =VLOOKUP(_xlfn.CONCAT(UPPER(C10),"|",$B$1),MasterSheet_WithPredictive!A:AP,37,FALSE) -> 28532.029 | F10: =VLOOKUP(_xlfn.CONCAT(UPPER(C10),"|",$B$1),MasterSheet_WithPredictive!A:AP,39,FALSE) -> 0.44B | G10: =VLOOKUP(_xlfn.CONCAT(UPPER(C10),"|",$B$1),MasterSheet_WithPredictive!A:AP,40,FALSE) -> Good Economic Resilience with Good Affordability.
A11: =_xlfn.RANK.EQ(D11,$D$5:$D$26,0) -> 4 | B11: =_xlfn.RANK.EQ(E11,$E$5:$E$26,0) -> 5 | C11: GERMANY | D11: =VLOOKUP(_xlfn.CONCAT(UPPER(C11),"|",$B$1),MasterSheet_WithPredictive!A:AP,36,FALSE) -> 0.5406939 | E11: =VLOOKUP(_xlfn.CONCAT(UPPER(C11),"|",$B$1),MasterSheet_WithPredictive!A:AP,37,FALSE) -> 37028.409 | F11: =VLOOKUP(_xlfn.CONCAT(UPPER(C11),"|",$B$1),MasterSheet_WithPredictive!A:AP,39,FALSE) -> 0.54A- | G11: =VLOOKUP(_xlfn.CONCAT(UPPER(C11),"|",$B$1),MasterSheet_WithPredictive!A:AP,40,FALSE) -> Excellent Economic Resilience with High Affordability.
A12: =_xlfn.RANK.EQ(D12,$D$5:$D$26,0) -> 22 | B12: =_xlfn.RANK.EQ(E12,$E$5:$E$26,0) -> 21 | C12: INDIA | D12: =VLOOKUP(_xlfn.CONCAT(UPPER(C12),"|",$B$1),MasterSheet_WithPredictive!A:AP,36,FALSE) -> 0.17064857 | E12: =VLOOKUP(_xlfn.CONCAT(UPPER(C12),"|",$B$1),MasterSheet_WithPredictive!A:AP,37,FALSE) -> 1019.3773 | F12: =VLOOKUP(_xlfn.CONCAT(UPPER(C12),"|",$B$1),MasterSheet_WithPredictive!A:AP,39,FALSE) -> 0.17D- | G12: =VLOOKUP(_xlfn.CONCAT(UPPER(C12),"|",$B$1),MasterSheet_WithPredictive!A:AP,40,FALSE) -> Weak Economic Resilience with Very Weak Affordability.
A13: =_xlfn.RANK.EQ(D13,$D$5:$D$26,0) -> 11 | B13: =_xlfn.RANK.EQ(E13,$E$5:$E$26,0) -> 20 | C13: INDONESIA | D13: =VLOOKUP(_xlfn.CONCAT(UPPER(C13),"|",$B$1),MasterSheet_WithPredictive!A:AP,36,FALSE) -> 0.42820197 | E13: =VLOOKUP(_xlfn.CONCAT(UPPER(C13),"|",$B$1),MasterSheet_WithPredictive!A:AP,37,FALSE) -> 1718.068 | F13: =VLOOKUP(_xlfn.CONCAT(UPPER(C13),"|",$B$1),MasterSheet_WithPredictive!A:AP,39,FALSE) -> 0.43D- | G13: =VLOOKUP(_xlfn.CONCAT(UPPER(C13),"|",$B$1),MasterSheet_WithPredictive!A:AP,40,FALSE) -> Good Economic Resilience with Very Weak Affordability.
A14: =_xlfn.RANK.EQ(D14,$D$5:$D$26,0) -> 9 | B14: =_xlfn.RANK.EQ(E14,$E$5:$E$26,0) -> 9 | C14: ITALY | D14: =VLOOKUP(_xlfn.CONCAT(UPPER(C14),"|",$B$1),MasterSheet_WithPredictive!A:AP,36,FALSE) -> 0.44806752 | E14: =VLOOKUP(_xlfn.CONCAT(UPPER(C14),"|",$B$1),MasterSheet_WithPredictive!A:AP,37,FALSE) -> 23178.936 | F14: =VLOOKUP(_xlfn.CONCAT(UPPER(C14),"|",$B$1),MasterSheet_WithPredictive!A:AP,39,FALSE) -> 0.45B- | G14: =VLOOKUP(_xlfn.CONCAT(UPPER(C14),"|",$B$1),MasterSheet_WithPredictive!A:AP,40,FALSE) -> Good Economic Resilience with Satisfactory Affordability.
A15: =_xlfn.RANK.EQ(D15,$D$5:$D$26,0) -> 13 | B15: =_xlfn.RANK.EQ(E15,$E$5:$E$26,0) -> 10 | C15: JAPAN | D15: =VLOOKUP(_xlfn.CONCAT(UPPER(C15),"|",$B$1),MasterSheet_WithPredictive!A:AP,36,FALSE) -> 0.4093241 | E15: =VLOOKUP(_xlfn.CONCAT(UPPER(C15),"|",$B$1),MasterSheet_WithPredictive!A:AP,37,FALSE) -> 21574.556 | F15: =VLOOKUP(_xlfn.CONCAT(UPPER(C15),"|",$B$1),MasterSheet_WithPredictive!A:AP,39,FALSE) -> 0.41B- | G15: =VLOOKUP(_xlfn.CONCAT(UPPER(C15),"|",$B$1),MasterSheet_WithPredictive!A:AP,40,FALSE) -> Satisfactory Economic Resilience with Satisfactory Affordability.
A16: =_xlfn.RANK.EQ(D16,$D$5:$D$26,0) -> 19 | B16: =_xlfn.RANK.EQ(E16,$E$5:$E$26,0) -> 16 | C16: MEXICO | D16: =VLOOKUP(_xlfn.CONCAT(UPPER(C16),"|",$B$1),MasterSheet_WithPredictive!A:AP,36,FALSE) -> 0.32240579 | E16: =VLOOKUP(_xlfn.CONCAT(UPPER(C16),"|",$B$1),MasterSheet_WithPredictive!A:AP,37,FALSE) -> 4744.1785 | F16: =VLOOKUP(_xlfn.CONCAT(UPPER(C16),"|",$B$1),MasterSheet_WithPredictive!A:AP,39,FALSE) -> 0.32D | G16: =VLOOKUP(_xlfn.CONCAT(UPPER(C16),"|",$B$1),MasterSheet_WithPredictive!A:AP,40,FALSE) -> Satisfactory Economic Resilience with Poor Affordability.
... A26: =_xlfn.RANK.EQ(D26,$D$5:$D$26,0) -> 3 | B26: =_xlfn.RANK.EQ(E26,$E$5:$E$26,0) -> 2 | C26: USA | D26: =VLOOKUP(_xlfn.CONCAT(UPPER(C26),"|",$B$1),MasterSheet_WithPredictive!A:AP,36,FALSE) -> 0.65331133 | E26: =VLOOKUP(_xlfn.CONCAT(UPPER(C26),"|",$B$1),MasterSheet_WithPredictive!A:AP,37,FALSE) -> 46536.323 | F26: =VLOOKUP(_xlfn.CONCAT(UPPER(C26),"|",$B$1),MasterSheet_WithPredictive!A:AP,39,FALSE) -> 0.65A | G26: =VLOOKUP(_xlfn.CONCAT(UPPER(C26),"|",$B$1),MasterSheet_WithPredictive!A:AP,40,FALSE) -> Excellent Economic Resilience with Excellent Affordability.

Sheet Preprocessing2
A1: Year | B1: =Preprocessing1!B1+1 -> 2026
A3: ='G20+3 Countries'!B4 -> 2025 - HEART SCORE G-20+2 RANKING | C3: Country | D3: Heart Value | E3: Heart Affordibility Value | F3: HEART SCORE | G3: Brief Description of HEART Scores
A4: RESILIENCE | B4: AFFORDABILITY
A5: =_xlfn.RANK.EQ(D5,$D$5:$D$26,0) -> 21 | B5: =_xlfn.RANK.EQ(E5,$E$5:$E$26,0) -> 17 | C5: ARGENTINA | D5: =VLOOKUP(_xlfn.CONCAT(UPPER(C5),"|",$B$1),MasterSheet_WithPredictive!A:AP,36,FALSE) -> 0.17949957 | E5: =VLOOKUP(_xlfn.CONCAT(UPPER(C5),"|",$B$1),MasterSheet_WithPredictive!A:AP,37,FALSE) -> 5054.5558 | F5: =VLOOKUP(_xlfn.CONCAT(UPPER(C5),"|",$B$1),MasterSheet_WithPredictive!A:AP,39,FALSE) -> 0.18D+ | G5: =VLOOKUP(_xlfn.CONCAT(UPPER(C5),"|",$B$1),MasterSheet_WithPredictive!A:AP,40,FALSE) -> Weak Economic Resilience with Challenging Affordability.
A6: =_xlfn.RANK.EQ(D6,$D$5:$D$26,0) -> 17 | B6: =_xlfn.RANK.EQ(E6,$E$5:$E$26,0) -> 4 | C6: AUSTRALIA | D6: =VLOOKUP(_xlfn.CONCAT(UPPER(C6),"|",$B$1),MasterSheet_WithPredictive!A:AP,36,FALSE) -> 0.36641244 | E6: =VLOOKUP(_xlfn.CONCAT(UPPER(C6),"|",$B$1),MasterSheet_WithPredictive!A:AP,37,FALSE) -> 40830.692 | F6: =VLOOKUP(_xlfn.CONCAT(UPPER(C6),"|",$B$1),MasterSheet_WithPredictive!A:AP,39,FALSE) -> 0.37A | G6: =VLOOKUP(_xlfn.CONCAT(UPPER(C6),"|",$B$1),MasterSheet_WithPredictive!A:AP,40,FALSE) -> Satisfactory Economic Resilience with Excellent Affordability.
A7: =_xlfn.RANK.EQ(D7,$D$5:$D$26,0) -> 19 | B7: =_xlfn.RANK.EQ(E7,$E$5:$E$26,0) -> 19 | C7: BRAZIL | D7: =VLOOKUP(_xlfn.CONCAT(UPPER(C7),"|",$B$1),MasterSheet_WithPredictive!A:AP,36,FALSE) -> 0.33273902 | E7: =VLOOKUP(_xlfn.CONCAT(UPPER(C7),"|",$B$1),MasterSheet_WithPredictive!A:AP,37,FALSE) -> 2735.0851 | F7: =VLOOKUP(_xlfn.CONCAT(UPPER(C7),"|",$B$1),MasterSheet_WithPredictive!A:AP,39,FALSE) -> 0.33D | G7: =VLOOKUP(_xlfn.CONCAT(UPPER(C7),"|",$B$1),MasterSheet_WithPredictive!A:AP,40,FALSE) -> Satisfactory Economic Resilience with Poor Affordability.
A8: =_xlfn.RANK.EQ(D8,$D$5:$D$26,0) -> 12 | B8: =_xlfn.RANK.EQ(E8,$E$5:$E$26,0) -> 6 | C8: CANADA | D8: =VLOOKUP(_xlfn.CONCAT(UPPER(C8),"|",$B$1),MasterSheet_WithPredictive!A:AP,36,FALSE) -> 0.42782282 | E8: =VLOOKUP(_xlfn.CONCAT(UPPER(C8),"|",$B$1),MasterSheet_WithPredictive!A:AP,37,FALSE) -> 35715.441 | F8: =VLOOKUP(_xlfn.CONCAT(UPPER(C8),"|",$B$1),MasterSheet_WithPredictive!A:AP,39,FALSE) -> 0.43A- | G8: =VLOOKUP(_xlfn.CONCAT(UPPER(C8),"|",$B$1),MasterSheet_WithPredictive!A:AP,40,FALSE) -> Good Economic Resilience with High Affordability.
A9: =_xlfn.RANK.EQ(D9,$D$5:$D$26,0) -> 2 | B9: =_xlfn.RANK.EQ(E9,$E$5:$E$26,0) -> 15 | C9: CHINA | D9: =VLOOKUP(_xlfn.CONCAT(UPPER(C9),"|",$B$1),MasterSheet_WithPredictive!A:AP,36,FALSE) -> 0.74825775 | E9: =VLOOKUP(_xlfn.CONCAT(UPPER(C9),"|",$B$1),MasterSheet_WithPredictive!A:AP,37,FALSE) -> 6598.2788 | F9: =VLOOKUP(_xlfn.CONCAT(UPPER(C9),"|",$B$1),MasterSheet_WithPredictive!A:AP,39,FALSE) -> 0.75D+ | G9: =VLOOKUP(_xlfn.CONCAT(UPPER(C9),"|",$B$1),MasterSheet_WithPredictive!A:AP,40,FALSE) -> Superb Economic Resilience with Challenging Affordability.
A10: =_xlfn.RANK.EQ(D10,$D$5:$D$26,0) -> 10 | B10: =_xlfn.RANK.EQ(E10,$E$5:$E$26,0) -> 8 | C10: FRANCE | D10: =VLOOKUP(_xlfn.CONCAT(UPPER(C10),"|",$B$1),MasterSheet_WithPredictive!A:AP,36,FALSE) -> 0.45214522 | E10: =VLOOKUP(_xlfn.CONCAT(UPPER(C10),"|",$B$1),MasterSheet_WithPredictive!A:AP,37,FALSE) -> 28918.141 | F10: =VLOOKUP(_xlfn.CONCAT(UPPER(C10),"|",$B$1),MasterSheet_WithPredictive!A:AP,39,FALSE) -> 0.45B | G10: =VLOOKUP(_xlfn.CONCAT(UPPER(C10),"|",$B$1),MasterSheet_WithPredictive!A:AP,40,FALSE) -> Good Economic Resilience with Good Affordability.
A11: =_xlfn.RANK.EQ(D11,$D$5:$D$26,0) -> 7 | B11: =_xlfn.RANK.EQ(E11,$E$5:$E$26,0) -> 5 | C11: GERMANY | D11: =VLOOKUP(_xlfn.CONCAT(UPPER(C11),"|",$B$1),MasterSheet_WithPredictive!A:AP,36,FALSE) -> 0.53307357 | E11: =VLOOKUP(_xlfn.CONCAT(UPPER(C11),"|",$B$1),MasterSheet_WithPredictive!A:AP,37,FALSE) -> 37595.928 | F11: =VLOOKUP(_xlfn.CONCAT(UPPER(C11),"|",$B$1),MasterSheet_WithPredictive!A:AP,39,FALSE) -> 0.53A- | G11: =VLOOKUP(_xlfn.CONCAT(UPPER(C11),"|",$B$1),MasterSheet_WithPredictive!A:AP,40,FALSE) -> Excellent Economic Resilience with High Affordability.
A12: =_xlfn.RANK.EQ(D12,$D$5:$D$26,0) -> 22 | B12: =_xlfn.RANK.EQ(E12,$E$5:$E$26,0) -> 21 | C12: INDIA | D12: =VLOOKUP(_xlfn.CONCAT(UPPER(C12),"|",$B$1),MasterSheet_WithPredictive!A:AP,36,FALSE) -> 0.17865044 | E12: =VLOOKUP(_xlfn.CONCAT(UPPER(C12),"|",$B$1),MasterSheet_WithPredictive!A:AP,37,FALSE) -> 1087.3557 | F12: =VLOOKUP(_xlfn.CONCAT(UPPER(C12),"|",$B$1),MasterSheet_WithPredictive!A:AP,39,FALSE) -> 0.18D- | G12: =VLOOKUP(_xlfn.CONCAT(UPPER(C12),"|",$B$1),MasterSheet_WithPredictive!A:AP,40,FALSE) -> Weak Economic Resilience with Very Weak Affordability.
A13: =_xlfn.RANK.EQ(D13,$D$5:$D$26,0) -> 9 | B13: =_xlfn.RANK.EQ(E13,$E$5:$E$26,0) -> 20 | C13: INDONESIA | D13: =VLOOKUP(_xlfn.CONCAT(UPPER(C13),"|",$B$1),MasterSheet_WithPredictive!A:AP,36,FALSE) -> 0.45436874 | E13: =VLOOKUP(_xlfn.CONCAT(UPPER(C13),"|",$B$1),MasterSheet_WithPredictive!A:AP,37,FALSE) -> 1823.3284 | F13: =VLOOKUP(_xlfn.CONCAT(UPPER(C13),"|",$B$1),MasterSheet_WithPredictive!A:AP,39,FALSE) -> 0.45D- | G13: =VLOOKUP(_xlfn.CONCAT(UPPER(C13),"|",$B$1),MasterSheet_WithPredictive!A:AP,40,FALSE) -> Good Economic Resilience with Very Weak Affordability.
A14: =_xlfn.RANK.EQ(D14,$D$5:$D$26,0) -> 11 | B14: =_xlfn.RANK.EQ(E14,$E$5:$E$26,0) -> 9 | C14: ITALY | D14: =VLOOKUP(_xlfn.CONCAT(UPPER(C14),"|",$B$1),MasterSheet_WithPredictive!A:AP,36,FALSE) -> 0.44480711 | E14: =VLOOKUP(_xlfn.CONCAT(UPPER(C14),"|",$B$1),MasterSheet_WithPredictive!A:AP,37,FALSE) -> 24320.302 | F14: =VLOOKUP(_xlfn.CONCAT(UPPER(C14),"|",$B$1),MasterSheet_WithPredictive!A:AP,39,FALSE) -> 0.44B- | G14: =VLOOKUP(_xlfn.CONCAT(UPPER(C14),"|",$B$1),MasterSheet_WithPredictive!A:AP,40,FALSE) -> Good Economic Resilience with Satisfactory Affordability.
A15: =_xlfn.RANK.EQ(D15,$D$5:$D$26,0) -> 13 | B15: =_xlfn.RANK.EQ(E15,$E$5:$E$26,0) -> 12 | C15: JAPAN | D15: =VLOOKUP(_xlfn.CONCAT(UPPER(C15),"|",$B$1),MasterSheet_WithPredictive!A:AP,36,FALSE) -> 0.41193132 | E15: =VLOOKUP(_xlfn.CONCAT(UPPER(C15),"|",$B$1),MasterSheet_WithPredictive!A:AP,37,FALSE) -> 20283.696 | F15: =VLOOKUP(_xlfn.CONCAT(UPPER(C15),"|",$B$1),MasterSheet_WithPredictive!A:AP,39,FALSE) -> 0.41B- | G15: =VLOOKUP(_xlfn.CONCAT(UPPER(C15),"|",$B$1),MasterSheet_WithPredictive!A:AP,40,FALSE) -> Good Economic Resilience with Satisfactory Affordability.
A16: =_xlfn.RANK.EQ(D16,$D$5:$D$26,0) -> 18 | B16: =_xlfn.RANK.EQ(E16,$E$5:$E$26,0) -> 16 | C16: MEXICO | D16: =VLOOKUP(_xlfn.CONCAT(UPPER(C16),"|",$B$1),MasterSheet_WithPredictive!A:AP,36,FALSE) -> 0.33595204 | E16: =VLOOKUP(_xlfn.CONCAT(UPPER(C16),"|",$B$1),MasterSheet_WithPredictive!A:AP,37,FALSE) -> 5273.2703 | F16: =VLOOKUP(_xlfn.CONCAT(UPPER(C16),"|",$B$1),MasterSheet_WithPredictive!A:AP,39,FALSE) -> 0.34D+ | G16: =VLOOKUP(_xlfn.CONCAT(UPPER(C16),"|",$B$1),MasterSheet_WithPredictive!A:AP,40,FALSE) -> Satisfactory Economic Resilience with Challenging Affordability.
... A26: =_xlfn.RANK.EQ(D26,$D$5:$D$26,0) -> 3 | B26: =_xlfn.RANK.EQ(E26,$E$5:$E$26,0) -> 3 | C26: USA | D26: =VLOOKUP(_xlfn.CONCAT(UPPER(C26),"|",$B$1),MasterSheet_WithPredictive!A:AP,36,FALSE) -> 0.65244811 | E26: =VLOOKUP(_xlfn.CONCAT(UPPER(C26),"|",$B$1),MasterSheet_WithPredictive!A:AP,37,FALSE) -> 47800.056 | F26: =VLOOKUP(_xlfn.CONCAT(UPPER(C26),"|",$B$1),MasterSheet_WithPredictive!A:AP,39,FALSE) -> 0.65A | G26: =VLOOKUP(_xlfn.CONCAT(UPPER(C26),"|",$B$1),MasterSheet_WithPredictive!A:AP,40,FALSE) -> Excellent Economic Resilience with Excellent Affordability.

Sheet RESILIENCE
A1: Country/Year | B1: 2019 | C1: 2020 | D1: 2021 | E1: 2022 | F1: 2023 | G1: 2024 | H1: 2025 | I1: 2026 | J1: 2027 | K1: 2028 | L1: 2029 | M1: 2030
A2: ARGENTINA | B2: =VLOOKUP(_xlfn.CONCAT($A2,"|",B$1),MasterSheet_WithPredictive!$A$1:$AP$265,36,FALSE) -> 0.0063511136 | C2: =VLOOKUP(_xlfn.CONCAT($A2,"|",C$1),MasterSheet_WithPredictive!$A$1:$AP$265,36,FALSE) -> 0.13381562 | D2: =VLOOKUP(_xlfn.CONCAT($A2,"|",D$1),MasterSheet_WithPredictive!$A$1:$AP$265,36,FALSE) -> 0.078594388 | E2: =VLOOKUP(_xlfn.CONCAT($A2,"|",E$1),MasterSheet_WithPredictive!$A$1:$AP$265,36,FALSE) -> 0.053012193 | F2: =VLOOKUP(_xlfn.CONCAT($A2,"|",F$1),MasterSheet_WithPredictive!$A$1:$AP$265,36,FALSE) -> -0.74616742 | G2: =VLOOKUP(_xlfn.CONCAT($A2,"|",G$1),MasterSheet_WithPredictive!$A$1:$AP$265,36,FALSE) -> -0.41314192 | H2: =VLOOKUP(_xlfn.CONCAT($A2,"|",H$1),MasterSheet_WithPredictive!$A$1:$AP$265,36,FALSE) -> 0.21731494 | I2: =VLOOKUP(_xlfn.CONCAT($A2,"|",I$1),MasterSheet_WithPredictive!$A$1:$AP$265,36,FALSE) -> 0.17949957 | ... M2: =VLOOKUP(_xlfn.CONCAT($A2,"|",M$1),MasterSheet_WithPredictive!$A$1:$AP$265,36,FALSE) -> 0.17820394
A3: AUSTRALIA | B3: =VLOOKUP(_xlfn.CONCAT($A3,"|",B$1),MasterSheet_WithPredictive!$A$1:$AP$265,36,FALSE) -> 0.27107646 | C3: =VLOOKUP(_xlfn.CONCAT($A3,"|",C$1),MasterSheet_WithPredictive!$A$1:$AP$265,36,FALSE) -> 0.28690305 | D3: =VLOOKUP(_xlfn.CONCAT($A3,"|",D$1),MasterSheet_WithPredictive!$A$1:$AP$265,36,FALSE) -> 0.30094211 | E3: =VLOOKUP(_xlfn.CONCAT($A3,"|",E$1),MasterSheet_WithPredictive!$A$1:$AP$265,36,FALSE) -> 0.3321358 | F3: =VLOOKUP(_xlfn.CONCAT($A3,"|",F$1),MasterSheet_WithPredictive!$A$1:$AP$265,36,FALSE) -> 0.33867661 | G3: =VLOOKUP(_xlfn.CONCAT($A3,"|",G$1),MasterSheet_WithPredictive!$A$1:$AP$265,36,FALSE) -> 0.33159071 | H3: =VLOOKUP(_xlfn.CONCAT($A3,"|",H$1),MasterSheet_WithPredictive!$A$1:$AP$265,36,FALSE) -> 0.33887795 | I3: =VLOOKUP(_xlfn.CONCAT($A3,"|",I$1),MasterSheet_WithPredictive!$A$1:$AP$265,36,FALSE) -> 0.36641244 | ... M3: =VLOOKUP(_xlfn.CONCAT($A3,"|",M$1),MasterSheet_WithPredictive!$A$1:$AP$265,36,FALSE) -> 0.42816903
A4: BRAZIL | B4: =VLOOKUP(_xlfn.CONCAT($A4,"|",B$1),MasterSheet_WithPredictive!$A$1:$AP$265,36,FALSE) -> 0.2539084 | C4: =VLOOKUP(_xlfn.CONCAT($A4,"|",C$1),MasterSheet_WithPredictive!$A$1:$AP$265,36,FALSE) -> 0.31865627 | D4: =VLOOKUP(_xlfn.CONCAT($A4,"|",D$1),MasterSheet_WithPredictive!$A$1:$AP$265,36,FALSE) -> 0.27588158 | E4: =VLOOKUP(_xlfn.CONCAT($A4,"|",E$1),MasterSheet_WithPredictive!$A$1:$AP$265,36,FALSE) -> 0.26386317 | F4: =VLOOKUP(_xlfn.CONCAT($A4,"|",F$1),MasterSheet_WithPredictive!$A$1:$AP$265,36,FALSE) -> 0.31303291 | G4: =VLOOKUP(_xlfn.CONCAT($A4,"|",G$1),MasterSheet_WithPredictive!$A$1:$AP$265,36,FALSE) -> 0.30866113 | H4: =VLOOKUP(_xlfn.CONCAT($A4,"|",H$1),MasterSheet_WithPredictive!$A$1:$AP$265,36,FALSE) -> 0.32956976 | I4: =VLOOKUP(_xlfn.CONCAT($A4,"|",I$1),MasterSheet_WithPredictive!$A$1:$AP$265,36,FALSE) -> 0.33273902 | ... M4: =VLOOKUP(_xlfn.CONCAT($A4,"|",M$1),MasterSheet_WithPredictive!$A$1:$AP$265,36,FALSE) -> 0.39551036
A5: CANADA | B5: =VLOOKUP(_xlfn.CONCAT($A5,"|",B$1),MasterSheet_WithPredictive!$A$1:$AP$265,36,FALSE) -> 0.29433083 | C5: =VLOOKUP(_xlfn.CONCAT($A5,"|",C$1),MasterSheet_WithPredictive!$A$1:$AP$265,36,FALSE) -> 0.30973258 | D5: =VLOOKUP(_xlfn.CONCAT($A5,"|",D$1),MasterSheet_WithPredictive!$A$1:$AP$265,36,FALSE) -> 0.35103906 | E5: =VLOOKUP(_xlfn.CONCAT($A5,"|",E$1),MasterSheet_WithPredictive!$A$1:$AP$265,36,FALSE) -> 0.36935511 | F5: =VLOOKUP(_xlfn.CONCAT($A5,"|",F$1),MasterSheet_WithPredictive!$A$1:$AP$265,36,FALSE) -> 0.35932593 | G5: =VLOOKUP(_xlfn.CONCAT($A5,"|",G$1),MasterSheet_WithPredictive!$A$1:$AP$265,36,FALSE) -> 0.37055184 | H5: =VLOOKUP(_xlfn.CONCAT($A5,"|",H$1),MasterSheet_WithPredictive!$A$1:$AP$265,36,FALSE) -> 0.41057598 | I5: =VLOOKUP(_xlfn.CONCAT($A5,"|",I$1),MasterSheet_WithPredictive!$A$1:$AP$265,36,FALSE) -> 0.42782282 | ... M5: =VLOOKUP(_xlfn.CONCAT($A5,"|",M$1),MasterSheet_WithPredictive!$A$1:$AP$265,36,FALSE) -> 0.51349312
A6: CHINA | B6: =VLOOKUP(_xlfn.CONCAT($A6,"|",B$1),MasterSheet_WithPredictive!$A$1:$AP$265,36,FALSE) -> 0.54210207 | C6: =VLOOKUP(_xlfn.CONCAT($A6,"|",C$1),MasterSheet_WithPredictive!$A$1:$AP$265,36,FALSE) -> 0.58719639 | D6: =VLOOKUP(_xlfn.CONCAT($A6,"|",D$1),MasterSheet_WithPredictive!$A$1:$AP$265,36,FALSE) -> 0.62172532 | E6: =VLOOKUP(_xlfn.CONCAT($A6,"|",E$1),MasterSheet_WithPredictive!$A$1:$AP$265,36,FALSE) -> 0.64146874 | F6: =VLOOKUP(_xlfn.CONCAT($A6,"|",F$1),MasterSheet_WithPredictive!$A$1:$AP$265,36,FALSE) -> 0.64460904 | G6: =VLOOKUP(_xlfn.CONCAT($A6,"|",G$1),MasterSheet_WithPredictive!$A$1:$AP$265,36,FALSE) -> 0.67368859 | H6: =VLOOKUP(_xlfn.CONCAT($A6,"|",H$1),MasterSheet_WithPredictive!$A$1:$AP$265,36,FALSE) -> 0.72928133 | I6: =VLOOKUP(_xlfn.CONCAT($A6,"|",I$1),MasterSheet_WithPredictive!$A$1:$AP$265,36,FALSE) -> 0.74825775 | ... M6: =VLOOKUP(_xlfn.CONCAT($A6,"|",M$1),MasterSheet_WithPredictive!$A$1:$AP$265,36,FALSE) -> 0.87902236
A7: FRANCE | B7: =VLOOKUP(_xlfn.CONCAT($A7,"|",B$1),MasterSheet_WithPredictive!$A$1:$AP$265,36,FALSE) -> 0.37371675 | C7: =VLOOKUP(_xlfn.CONCAT($A7,"|",C$1),MasterSheet_WithPredictive!$A$1:$AP$265,36,FALSE) -> 0.38154543 | D7: =VLOOKUP(_xlfn.CONCAT($A7,"|",D$1),MasterSheet_WithPredictive!$A$1:$AP$265,36,FALSE) -> 0.40562201 | E7: =VLOOKUP(_xlfn.CONCAT($A7,"|",E$1),MasterSheet_WithPredictive!$A$1:$AP$265,36,FALSE) -> 0.37961267 | F7: =VLOOKUP(_xlfn.CONCAT($A7,"|",F$1),MasterSheet_WithPredictive!$A$1:$AP$265,36,FALSE) -> 0.39075806 | G7: =VLOOKUP(_xlfn.CONCAT($A7,"|",G$1),MasterSheet_WithPredictive!$A$1:$AP$265,36,FALSE) -> 0.440436 | H7: =VLOOKUP(_xlfn.CONCAT($A7,"|",H$1),MasterSheet_WithPredictive!$A$1:$AP$265,36,FALSE) -> 0.44373071 | I7: =VLOOKUP(_xlfn.CONCAT($A7,"|",I$1),MasterSheet_WithPredictive!$A$1:$AP$265,36,FALSE) -> 0.45214522 | ... M7: =VLOOKUP(_xlfn.CONCAT($A7,"|",M$1),MasterSheet_WithPredictive!$A$1:$AP$265,36,FALSE) -> 0.51787077
A8: GERMANY | B8: =VLOOKUP(_xlfn.CONCAT($A8,"|",B$1),MasterSheet_WithPredictive!$A$1:$AP$265,36,FALSE) -> 0.43585917 | C8: =VLOOKUP(_xlfn.CONCAT($A8,"|",C$1),MasterSheet_WithPredictive!$A$1:$AP$265,36,FALSE) -> 0.44986833 | D8: =VLOOKUP(_xlfn.CONCAT($A8,"|",D$1),MasterSheet_WithPredictive!$A$1:$AP$265,36,FALSE) -> 0.46432268 | E8: =VLOOKUP(_xlfn.CONCAT($A8,"|",E$1),MasterSheet_WithPredictive!$A$1:$AP$265,36,FALSE) -> 0.44467872 | F8: =VLOOKUP(_xlfn.CONCAT($A8,"|",F$1),MasterSheet_WithPredictive!$A$1:$AP$265,36,FALSE) -> 0.47104081 | G8: =VLOOKUP(_xlfn.CONCAT($A8,"|",G$1),MasterSheet_WithPredictive!$A$1:$AP$265,36,FALSE) -> 0.49653085 | H8: =VLOOKUP(_xlfn.CONCAT($A8,"|",H$1),MasterSheet_WithPredictive!$A$1:$AP$265,36,FALSE) -> 0.5406939 | I8: =VLOOKUP(_xlfn.CONCAT($A8,"|",I$1),MasterSheet_WithPredictive!$A$1:$AP$265,36,FALSE) -> 0.53307357 | ... M8: =VLOOKUP(_xlfn.CONCAT($A8,"|",M$1),MasterSheet_WithPredictive!$A$1:$AP$265,36,FALSE) -> 0.60651516
A9: INDIA | B9: =VLOOKUP(_xlfn.CONCAT($A9,"|",B$1),MasterSheet_WithPredictive!$A$1:$AP$265,36,FALSE) -> 0.10016258 | C9: =VLOOKUP(_xlfn.CONCAT($A9,"|",C$1),MasterSheet_WithPredictive!$A$1:$AP$265,36,FALSE) -> 0.12978589 | D9: =VLOOKUP(_xlfn.CONCAT($A9,"|",D$1),MasterSheet_WithPredictive!$A$1:$AP$265,36,FALSE) -> 0.1449915 | E9: =VLOOKUP(_xlfn.CONCAT($A9,"|",E$1),MasterSheet_WithPredictive!$A$1:$AP$265,36,FALSE) -> 0.15900447 | F9: =VLOOKUP(_xlfn.CONCAT($A9,"|",F$1),MasterSheet_WithPredictive!$A$1:$AP$265,36,FALSE) -> 0.13999833 | G9: =VLOOKUP(_xlfn.CONCAT($A9,"|",G$1),MasterSheet_WithPredictive!$A$1:$AP$265,36,FALSE) -> 0.1496629 | H9: =VLOOKUP(_xlfn.CONCAT($A9,"|",H$1),MasterSheet_WithPredictive!$A$1:$AP$265,36,FALSE) -> 0.17064857 | I9: =VLOOKUP(_xlfn.CONCAT($A9,"|",I$1),MasterSheet_WithPredictive!$A$1:$AP$265,36,FALSE) -> 0.17865044 | ... M9: =VLOOKUP(_xlfn.CONCAT($A9,"|",M$1),MasterSheet_WithPredictive!$A$1:$AP$265,36,FALSE) -> 0.22059018
A10: INDONESIA | B10: =VLOOKUP(_xlfn.CONCAT($A10,"|",B$1),MasterSheet_WithPredictive!$A$1:$AP$265,36,FALSE) -> 0.2965002 | C10: =VLOOKUP(_xlfn.CONCAT($A10,"|",C$1),MasterSheet_WithPredictive!$A$1:$AP$265,36,FALSE) -> 0.33419544 | D10: =VLOOKUP(_xlfn.CONCAT($A10,"|",D$1),MasterSheet_WithPredictive!$A$1:$AP$265,36,FALSE) -> 0.36384819 | E10: =VLOOKUP(_xlfn.CONCAT($A10,"|",E$1),MasterSheet_WithPredictive!$A$1:$AP$265,36,FALSE) -> 0.39201489 | F10: =VLOOKUP(_xlfn.CONCAT($A10,"|",F$1),MasterSheet_WithPredictive!$A$1:$AP$265,36,FALSE) -> 0.38836314 | G10: =VLOOKUP(_xlfn.CONCAT($A10,"|",G$1),MasterSheet_WithPredictive!$A$1:$AP$265,36,FALSE) -> 0.40222596 | H10: =VLOOKUP(_xlfn.CONCAT($A10,"|",H$1),MasterSheet_WithPredictive!$A$1:$AP$265,36,FALSE) -> 0.42820197 | I10: =VLOOKUP(_xlfn.CONCAT($A10,"|",I$1),MasterSheet_WithPredictive!$A$1:$AP$265,36,FALSE) -> 0.45436874 | ... M10: =VLOOKUP(_xlfn.CONCAT($A10,"|",M$1),MasterSheet_WithPredictive!$A$1:$AP$265,36,FALSE) -> 0.54789148
A11: ITALY | B11: =VLOOKUP(_xlfn.CONCAT($A11,"|",B$1),MasterSheet_WithPredictive!$A$1:$AP$265,36,FALSE) -> 0.3203765 | C11: =VLOOKUP(_xlfn.CONCAT($A11,"|",C$1),MasterSheet_WithPredictive!$A$1:$AP$265,36,FALSE) -> 0.34717895 | D11: =VLOOKUP(_xlfn.CONCAT($A11,"|",D$1),MasterSheet_WithPredictive!$A$1:$AP$265,36,FALSE) -> 0.34923981 | E11: =VLOOKUP(_xlfn.CONCAT($A11,"|",E$1),MasterSheet_WithPredictive!$A$1:$AP$265,36,FALSE) -> 0.35204329 | F11: =VLOOKUP(_xlfn.CONCAT($A11,"|",F$1),MasterSheet_WithPredictive!$A$1:$AP$265,36,FALSE) -> 0.40486222 | G11: =VLOOKUP(_xlfn.CONCAT($A11,"|",G$1),MasterSheet_WithPredictive!$A$1:$AP$265,36,FALSE) -> 0.36879725 | H11: =VLOOKUP(_xlfn.CONCAT($A11,"|",H$1),MasterSheet_WithPredictive!$A$1:$AP$265,36,FALSE) -> 0.44806752 | I11: =VLOOKUP(_xlfn.CONCAT($A11,"|",I$1),MasterSheet_WithPredictive!$A$1:$AP$265,36,FALSE) -> 0.44480711 | ... M11: =VLOOKUP(_xlfn.CONCAT($A11,"|",M$1),MasterSheet_WithPredictive!$A$1:$AP$265,36,FALSE) -> 0.54203966
A12: JAPAN | B12: =VLOOKUP(_xlfn.CONCAT($A12,"|",B$1),MasterSheet_WithPredictive!$A$1:$AP$265,36,FALSE) -> 0.34120834 | C12: =VLOOKUP(_xlfn.CONCAT($A12,"|",C$1),MasterSheet_WithPredictive!$A$1:$AP$265,36,FALSE) -> 0.35763097 | D12: =VLOOKUP(_xlfn.CONCAT($A12,"|",D$1),MasterSheet_WithPredictive!$A$1:$AP$265,36,FALSE) -> 0.36376386 | E12: =VLOOKUP(_xlfn.CONCAT($A12,"|",E$1),MasterSheet_WithPredictive!$A$1:$AP$265,36,FALSE) -> 0.3378124 | F12: =VLOOKUP(_xlfn.CONCAT($A12,"|",F$1),MasterSheet_WithPredictive!$A$1:$AP$265,36,FALSE) -> 0.37530416 | G12: =VLOOKUP(_xlfn.CONCAT($A12,"|",G$1),MasterSheet_WithPredictive!$A$1:$AP$265,36,FALSE) -> 0.39179624 | H12: =VLOOKUP(_xlfn.CONCAT($A12,"|",H$1),MasterSheet_WithPredictive!$A$1:$AP$265,36,FALSE) -> 0.4093241 | I12: =VLOOKUP(_xlfn.CONCAT($A12,"|",I$1),MasterSheet_WithPredictive!$A$1:$AP$265,36,FALSE) -> 0.41193132 | ... M12: =VLOOKUP(_xlfn.CONCAT($A12,"|",M$1),MasterSheet_WithPredictive!$A$1:$AP$265,36,FALSE) -> 0.48448953
A13: MEXICO | B13: =VLOOKUP(_xlfn.CONCAT($A13,"|",B$1),MasterSheet_WithPredictive!$A$1:$AP$265,36,FALSE) -> 0.26139883 | C13: =VLOOKUP(_xlfn.CONCAT($A13,"|",C$1),MasterSheet_WithPredictive!$A$1:$AP$265,36,FALSE) -> 0.30272815 | D13: =VLOOKUP(_xlfn.CONCAT($A13,"|",D$1),MasterSheet_WithPredictive!$A$1:$AP$265,36,FALSE) -> 0.28831771 | E13: =VLOOKUP(_xlfn.CONCAT($A13,"|",E$1),MasterSheet_WithPredictive!$A$1:$AP$265,36,FALSE) -> 0.29009735 | F13: =VLOOKUP(_xlfn.CONCAT($A13,"|",F$1),MasterSheet_WithPredictive!$A$1:$AP$265,36,FALSE) -> 0.30019345 | G13: =VLOOKUP(_xlfn.CONCAT($A13,"|",G$1),MasterSheet_WithPredictive!$A$1:$AP$265,36,FALSE) -> 0.32098759 | H13: =VLOOKUP(_xlfn.CONCAT($A13,"|",H$1),MasterSheet_WithPredictive!$A$1:$AP$265,36,FALSE) -> 0.32240579 | I13: =VLOOKUP(_xlfn.CONCAT($A13,"|",I$1),MasterSheet_WithPredictive!$A$1:$AP$265,36,FALSE) -> 0.33595204 | ... M13: =VLOOKUP(_xlfn.CONCAT($A13,"|",M$1),MasterSheet_WithPredictive!$A$1:$AP$265,36,FALSE) -> 0.38983137
... A23: USA | B23: =VLOOKUP(_xlfn.CONCAT($A23,"|",B$1),MasterSheet_WithPredictive!$A$1:$AP$265,36,FALSE) -> 0.52860187 | C23: =VLOOKUP(_xlfn.CONCAT($A23,"|",C$1),MasterSheet_WithPredictive!$A$1:$AP$265,36,FALSE) -> 0.57076469 | D23: =VLOOKUP(_xlfn.CONCAT($A23,"|",D$1),MasterSheet_WithPredictive!$A$1:$AP$265,36,FALSE) -> 0.58152153 | E23: =VLOOKUP(_xlfn.CONCAT($A23,"|",E$1),MasterSheet_WithPredictive!$A$1:$AP$265,36,FALSE) -> 0.58517858 | F23: =VLOOKUP(_xlfn.CONCAT($A23,"|",F$1),MasterSheet_WithPredictive!$A$1:$AP$265,36,FALSE) -> 0.58082263 | G23: =VLOOKUP(_xlfn.CONCAT($A23,"|",G$1),MasterSheet_WithPredictive!$A$1:$AP$265,36,FALSE) -> 0.59890522 | H23: =VLOOKUP(_xlfn.CONCAT($A23,"|",H$1),MasterSheet_WithPredictive!$A$1:$AP$265,36,FALSE) -> 0.65331133 | I23: =VLOOKUP(_xlfn.CONCAT($A23,"|",I$1),MasterSheet_WithPredictive!$A$1:$AP$265,36,FALSE) -> 0.65244811 | ... M23: =VLOOKUP(_xlfn.CONCAT($A23,"|",M$1),MasterSheet_WithPredictive!$A$1:$AP$265,36,FALSE) -> 0.72720431

Sheet AFFORDIBILITY
A1: Country/Year | B1: 2019 | C1: 2020 | D1: 2021 | E1: 2022 | F1: 2023 | G1: 2024 | H1: 2025 | I1: 2026 | J1: 2027 | K1: 2028 | L1: 2029 | M1: 2030
A2: ARGENTINA | B2: =VLOOKUP(_xlfn.CONCAT($A2,"|",B$1),MasterSheet_WithPredictive!$A$1:$AP$265,37,FALSE) -> 1956.4985 | C2: =VLOOKUP(_xlfn.CONCAT($A2,"|",C$1),MasterSheet_WithPredictive!$A$1:$AP$265,37,FALSE) -> 2267.4307 | D2: =VLOOKUP(_xlfn.CONCAT($A2,"|",D$1),MasterSheet_WithPredictive!$A$1:$AP$265,37,FALSE) -> 2139.7005 | E2: =VLOOKUP(_xlfn.CONCAT($A2,"|",E$1),MasterSheet_WithPredictive!$A$1:$AP$265,37,FALSE) -> 742.23004 | F2: =VLOOKUP(_xlfn.CONCAT($A2,"|",F$1),MasterSheet_WithPredictive!$A$1:$AP$265,37,FALSE) -> -2685.6056 | G2: =VLOOKUP(_xlfn.CONCAT($A2,"|",G$1),MasterSheet_WithPredictive!$A$1:$AP$265,37,FALSE) -> -5729.4278 | H2: =VLOOKUP(_xlfn.CONCAT($A2,"|",H$1),MasterSheet_WithPredictive!$A$1:$AP$265,37,FALSE) -> 4641.7306 | I2: =VLOOKUP(_xlfn.CONCAT($A2,"|",I$1),MasterSheet_WithPredictive!$A$1:$AP$265,37,FALSE) -> 5054.5558 | ... M2: =VLOOKUP(_xlfn.CONCAT($A2,"|",M$1),MasterSheet_WithPredictive!$A$1:$AP$265,37,FALSE) -> 6243.9966
A3: AUSTRALIA | B3: =VLOOKUP(_xlfn.CONCAT($A3,"|",B$1),MasterSheet_WithPredictive!$A$1:$AP$265,37,FALSE) -> 32692.04 | C3: =VLOOKUP(_xlfn.CONCAT($A3,"|",C$1),MasterSheet_WithPredictive!$A$1:$AP$265,37,FALSE) -> 31028.996 | D3: =VLOOKUP(_xlfn.CONCAT($A3,"|",D$1),MasterSheet_WithPredictive!$A$1:$AP$265,37,FALSE) -> 36532.641 | E3: =VLOOKUP(_xlfn.CONCAT($A3,"|",E$1),MasterSheet_WithPredictive!$A$1:$AP$265,37,FALSE) -> 37892.941 | F3: =VLOOKUP(_xlfn.CONCAT($A3,"|",F$1),MasterSheet_WithPredictive!$A$1:$AP$265,37,FALSE) -> 38830.924 | G3: =VLOOKUP(_xlfn.CONCAT($A3,"|",G$1),MasterSheet_WithPredictive!$A$1:$AP$265,37,FALSE) -> 39609.212 | H3: =VLOOKUP(_xlfn.CONCAT($A3,"|",H$1),MasterSheet_WithPredictive!$A$1:$AP$265,37,FALSE) -> 39300.547 | I3: =VLOOKUP(_xlfn.CONCAT($A3,"|",I$1),MasterSheet_WithPredictive!$A$1:$AP$265,37,FALSE) -> 40830.692 | ... M3: =VLOOKUP(_xlfn.CONCAT($A3,"|",M$1),MasterSheet_WithPredictive!$A$1:$AP$265,37,FALSE) -> 45824.021
A4: BRAZIL | B4: =VLOOKUP(_xlfn.CONCAT($A4,"|",B$1),MasterSheet_WithPredictive!$A$1:$AP$265,37,FALSE) -> 2094.9529 | C4: =VLOOKUP(_xlfn.CONCAT($A4,"|",C$1),MasterSheet_WithPredictive!$A$1:$AP$265,37,FALSE) -> 1924.0031 | D4: =VLOOKUP(_xlfn.CONCAT($A4,"|",D$1),MasterSheet_WithPredictive!$A$1:$AP$265,37,FALSE) -> 1747.253 | E4: =VLOOKUP(_xlfn.CONCAT($A4,"|",E$1),MasterSheet_WithPredictive!$A$1:$AP$265,37,FALSE) -> 2189.2042 | F4: =VLOOKUP(_xlfn.CONCAT($A4,"|",F$1),MasterSheet_WithPredictive!$A$1:$AP$265,37,FALSE) -> 2643.5374 | G4: =VLOOKUP(_xlfn.CONCAT($A4,"|",G$1),MasterSheet_WithPredictive!$A$1:$AP$265,37,FALSE) -> 2647.4747 | H4: =VLOOKUP(_xlfn.CONCAT($A4,"|",H$1),MasterSheet_WithPredictive!$A$1:$AP$265,37,FALSE) -> 2582.01 | I4: =VLOOKUP(_xlfn.CONCAT($A4,"|",I$1),MasterSheet_WithPredictive!$A$1:$AP$265,37,FALSE) -> 2735.0851 | ... M4: =VLOOKUP(_xlfn.CONCAT($A4,"|",M$1),MasterSheet_WithPredictive!$A$1:$AP$265,37,FALSE) -> 3355.8144
A5: CANADA | B5: =VLOOKUP(_xlfn.CONCAT($A5,"|",B$1),MasterSheet_WithPredictive!$A$1:$AP$265,37,FALSE) -> 27405.941 | C5: =VLOOKUP(_xlfn.CONCAT($A5,"|",C$1),MasterSheet_WithPredictive!$A$1:$AP$265,37,FALSE) -> 27275.404 | D5: =VLOOKUP(_xlfn.CONCAT($A5,"|",D$1),MasterSheet_WithPredictive!$A$1:$AP$265,37,FALSE) -> 32136.279 | E5: =VLOOKUP(_xlfn.CONCAT($A5,"|",E$1),MasterSheet_WithPredictive!$A$1:$AP$265,37,FALSE) -> 33528.832 | F5: =VLOOKUP(_xlfn.CONCAT($A5,"|",F$1),MasterSheet_WithPredictive!$A$1:$AP$265,37,FALSE) -> 33602.519 | G5: =VLOOKUP(_xlfn.CONCAT($A5,"|",G$1),MasterSheet_WithPredictive!$A$1:$AP$265,37,FALSE) -> 34340.778 | H5: =VLOOKUP(_xlfn.CONCAT($A5,"|",H$1),MasterSheet_WithPredictive!$A$1:$AP$265,37,FALSE) -> 34043.939 | I5: =VLOOKUP(_xlfn.CONCAT($A5,"|",I$1),MasterSheet_WithPredictive!$A$1:$AP$265,37,FALSE) -> 35715.441 | ... M5: =VLOOKUP(_xlfn.CONCAT($A5,"|",M$1),MasterSheet_WithPredictive!$A$1:$AP$265,37,FALSE) -> 40375.122
A6: CHINA | B6: =VLOOKUP(_xlfn.CONCAT($A6,"|",B$1),MasterSheet_WithPredictive!$A$1:$AP$265,37,FALSE) -> 3790.1229 | C6: =VLOOKUP(_xlfn.CONCAT($A6,"|",C$1),MasterSheet_WithPredictive!$A$1:$AP$265,37,FALSE) -> 4142.8085 | D6: =VLOOKUP(_xlfn.CONCAT($A6,"|",D$1),MasterSheet_WithPredictive!$A$1:$AP$265,37,FALSE) -> 5533.1872 | E6: =VLOOKUP(_xlfn.CONCAT($A6,"|",E$1),MasterSheet_WithPredictive!$A$1:$AP$265,37,FALSE) -> 5475.2113 | F6: =VLOOKUP(_xlfn.CONCAT($A6,"|",F$1),MasterSheet_WithPredictive!$A$1:$AP$265,37,FALSE) -> 5709.2713 | G6: =VLOOKUP(_xlfn.CONCAT($A6,"|",G$1),MasterSheet_WithPredictive!$A$1:$AP$265,37,FALSE) -> 5846.1955 | H6: =VLOOKUP(_xlfn.CONCAT($A6,"|",H$1),MasterSheet_WithPredictive!$A$1:$AP$265,37,FALSE) -> 5918.047 | I6: =VLOOKUP(_xlfn.CONCAT($A6,"|",I$1),MasterSheet_WithPredictive!$A$1:$AP$265,37,FALSE) -> 6598.2788 | ... M6: =VLOOKUP(_xlfn.CONCAT($A6,"|",M$1),MasterSheet_WithPredictive!$A$1:$AP$265,37,FALSE) -> 8448.6971
A7: FRANCE | B7: =VLOOKUP(_xlfn.CONCAT($A7,"|",B$1),MasterSheet_WithPredictive!$A$1:$AP$265,37,FALSE) -> 23097.149 | C7: =VLOOKUP(_xlfn.CONCAT($A7,"|",C$1),MasterSheet_WithPredictive!$A$1:$AP$265,37,FALSE) -> 23117.047 | D7: =VLOOKUP(_xlfn.CONCAT($A7,"|",D$1),MasterSheet_WithPredictive!$A$1:$AP$265,37,FALSE) -> 25159.091 | E7: =VLOOKUP(_xlfn.CONCAT($A7,"|",E$1),MasterSheet_WithPredictive!$A$1:$AP$265,37,FALSE) -> 23231.14 | F7: =VLOOKUP(_xlfn.CONCAT($A7,"|",F$1),MasterSheet_WithPredictive!$A$1:$AP$265,37,FALSE) -> 25171.551 | G7: =VLOOKUP(_xlfn.CONCAT($A7,"|",G$1),MasterSheet_WithPredictive!$A$1:$AP$265,37,FALSE) -> 27651.057 | H7: =VLOOKUP(_xlfn.CONCAT($A7,"|",H$1),MasterSheet_WithPredictive!$A$1:$AP$265,37,FALSE) -> 28532.029 | I7: =VLOOKUP(_xlfn.CONCAT($A7,"|",I$1),MasterSheet_WithPredictive!$A$1:$AP$265,37,FALSE) -> 28918.141 | ... M7: =VLOOKUP(_xlfn.CONCAT($A7,"|",M$1),MasterSheet_WithPredictive!$A$1:$AP$265,37,FALSE) -> 32636.176
A8: GERMANY | B8: =VLOOKUP(_xlfn.CONCAT($A8,"|",B$1),MasterSheet_WithPredictive!$A$1:$AP$265,37,FALSE) -> 30214.738 | C8: =VLOOKUP(_xlfn.CONCAT($A8,"|",C$1),MasterSheet_WithPredictive!$A$1:$AP$265,37,FALSE) -> 30054.977 | D8: =VLOOKUP(_xlfn.CONCAT($A8,"|",D$1),MasterSheet_WithPredictive!$A$1:$AP$265,37,FALSE) -> 32398.738 | E8: =VLOOKUP(_xlfn.CONCAT($A8,"|",E$1),MasterSheet_WithPredictive!$A$1:$AP$265,37,FALSE) -> 30556.586 | F8: =VLOOKUP(_xlfn.CONCAT($A8,"|",F$1),MasterSheet_WithPredictive!$A$1:$AP$265,37,FALSE) -> 33797.118 | G8: =VLOOKUP(_xlfn.CONCAT($A8,"|",G$1),MasterSheet_WithPredictive!$A$1:$AP$265,37,FALSE) -> 36238.27 | H8: =VLOOKUP(_xlfn.CONCAT($A8,"|",H$1),MasterSheet_WithPredictive!$A$1:$AP$265,37,FALSE) -> 37028.409 | I8: =VLOOKUP(_xlfn.CONCAT($A8,"|",I$1),MasterSheet_WithPredictive!$A$1:$AP$265,37,FALSE) -> 37595.928 | ... M8: =VLOOKUP(_xlfn.CONCAT($A8,"|",M$1),MasterSheet_WithPredictive!$A$1:$AP$265,37,FALSE) -> 42516.094
A9: INDIA | B9: =VLOOKUP(_xlfn.CONCAT($A9,"|",B$1),MasterSheet_WithPredictive!$A$1:$AP$265,37,FALSE) -> 615.65704 | C9: =VLOOKUP(_xlfn.CONCAT($A9,"|",C$1),MasterSheet_WithPredictive!$A$1:$AP$265,37,FALSE) -> 559.19946 | D9: =VLOOKUP(_xlfn.CONCAT($A9,"|",D$1),MasterSheet_WithPredictive!$A$1:$AP$265,37,FALSE) -> 680.39284 | E9: =VLOOKUP(_xlfn.CONCAT($A9,"|",E$1),MasterSheet_WithPredictive!$A$1:$AP$265,37,FALSE) -> 760.62336 | F9: =VLOOKUP(_xlfn.CONCAT($A9,"|",F$1),MasterSheet_WithPredictive!$A$1:$AP$265,37,FALSE) -> 851.43012 | G9: =VLOOKUP(_xlfn.CONCAT($A9,"|",G$1),MasterSheet_WithPredictive!$A$1:$AP$265,37,FALSE) -> 915.01685 | H9: =VLOOKUP(_xlfn.CONCAT($A9,"|",H$1),MasterSheet_WithPredictive!$A$1:$AP$265,37,FALSE) -> 1019.3773 | I9: =VLOOKUP(_xlfn.CONCAT($A9,"|",I$1),MasterSheet_WithPredictive!$A$1:$AP$265,37,FALSE) -> 1087.3557 | ... M9: =VLOOKUP(_xlfn.CONCAT($A9,"|",M$1),MasterSheet_WithPredictive!$A$1:$AP$265,37,FALSE) -> 1474.4857
A10: INDONESIA | B10: =VLOOKUP(_xlfn.CONCAT($A10,"|",B$1),MasterSheet_WithPredictive!$A$1:$AP$265,37,FALSE) -> 1418.9047 | C10: =VLOOKUP(_xlfn.CONCAT($A10,"|",C$1),MasterSheet_WithPredictive!$A$1:$AP$265,37,FALSE) -> 1388.3945 | D10: =VLOOKUP(_xlfn.CONCAT($A10,"|",D$1),MasterSheet_WithPredictive!$A$1:$AP$265,37,FALSE) -> 1502.6101 | E10: =VLOOKUP(_xlfn.CONCAT($A10,"|",E$1),MasterSheet_WithPredictive!$A$1:$AP$265,37,FALSE) -> 1609.8468 | F10: =VLOOKUP(_xlfn.CONCAT($A10,"|",F$1),MasterSheet_WithPredictive!$A$1:$AP$265,37,FALSE) -> 1731.854 | G10: =VLOOKUP(_xlfn.CONCAT($A10,"|",G$1),MasterSheet_WithPredictive!$A$1:$AP$265,37,FALSE) -> 1835.6843 | H10: =VLOOKUP(_xlfn.CONCAT($A10,"|",H$1),MasterSheet_WithPredictive!$A$1:$AP$265,37,FALSE) -> 1718.068 | I10: =VLOOKUP(_xlfn.CONCAT($A10,"|",I$1),MasterSheet_WithPredictive!$A$1:$AP$265,37,FALSE) -> 1823.3284 | ... M10: =VLOOKUP(_xlfn.CONCAT($A10,"|",M$1),MasterSheet_WithPredictive!$A$1:$AP$265,37,FALSE) -> 2110.958
A11: ITALY | B11: =VLOOKUP(_xlfn.CONCAT($A11,"|",B$1),MasterSheet_WithPredictive!$A$1:$AP$265,37,FALSE) -> 17945.664 | C11: =VLOOKUP(_xlfn.CONCAT($A11,"|",C$1),MasterSheet_WithPredictive!$A$1:$AP$265,37,FALSE) -> 17288.995 | D11: =VLOOKUP(_xlfn.CONCAT($A11,"|",D$1),MasterSheet_WithPredictive!$A$1:$AP$265,37,FALSE) -> 19961.429 | E11: =VLOOKUP(_xlfn.CONCAT($A11,"|",E$1),MasterSheet_WithPredictive!$A$1:$AP$265,37,FALSE) -> 18754.193 | F11: =VLOOKUP(_xlfn.CONCAT($A11,"|",F$1),MasterSheet_WithPredictive!$A$1:$AP$265,37,FALSE) -> 21388.726 | G11: =VLOOKUP(_xlfn.CONCAT($A11,"|",G$1),MasterSheet_WithPredictive!$A$1:$AP$265,37,FALSE) -> 23433.323 | H11: =VLOOKUP(_xlfn.CONCAT($A11,"|",H$1),MasterSheet_WithPredictive!$A$1:$AP$265,37,FALSE) -> 23178.936 | I11: =VLOOKUP(_xlfn.CONCAT($A11,"|",I$1),MasterSheet_WithPredictive!$A$1:$AP$265,37,FALSE) -> 24320.302 | ... M11: =VLOOKUP(_xlfn.CONCAT($A11,"|",M$1),MasterSheet_WithPredictive!$A$1:$AP$265,37,FALSE) -> 28890.229
A12: JAPAN | B12: =VLOOKUP(_xlfn.CONCAT($A12,"|",B$1),MasterSheet_WithPredictive!$A$1:$AP$265,37,FALSE) -> 23655.028 | C12: =VLOOKUP(_xlfn.CONCAT($A12,"|",C$1),MasterSheet_WithPredictive!$A$1:$AP$265,37,FALSE) -> 23722.293 | D12: =VLOOKUP(_xlfn.CONCAT($A12,"|",D$1),MasterSheet_WithPredictive!$A$1:$AP$265,37,FALSE) -> 24611.193 | E12: =VLOOKUP(_xlfn.CONCAT($A12,"|",E$1),MasterSheet_WithPredictive!$A$1:$AP$265,37,FALSE) -> 20589.08 | F12: =VLOOKUP(_xlfn.CONCAT($A12,"|",F$1),MasterSheet_WithPredictive!$A$1:$AP$265,37,FALSE) -> 20732.707 | G12: =VLOOKUP(_xlfn.CONCAT($A12,"|",G$1),MasterSheet_WithPredictive!$A$1:$AP$265,37,FALSE) -> 20482.247 | H12: =VLOOKUP(_xlfn.CONCAT($A12,"|",H$1),MasterSheet_WithPredictive!$A$1:$AP$265,37,FALSE) -> 21574.556 | I12: =VLOOKUP(_xlfn.CONCAT($A12,"|",I$1),MasterSheet_WithPredictive!$A$1:$AP$265,37,FALSE) -> 20283.696 | ... M12: =VLOOKUP(_xlfn.CONCAT($A12,"|",M$1),MasterSheet_WithPredictive!$A$1:$AP$265,37,FALSE) -> 17522.383
A13: MEXICO | B13: =VLOOKUP(_xlfn.CONCAT($A13,"|",B$1),MasterSheet_WithPredictive!$A$1:$AP$265,37,FALSE) -> 3237.5767 | C13: =VLOOKUP(_xlfn.CONCAT($A13,"|",C$1),MasterSheet_WithPredictive!$A$1:$AP$265,37,FALSE) -> 2852.677 | D13: =VLOOKUP(_xlfn.CONCAT($A13,"|",D$1),MasterSheet_WithPredictive!$A$1:$AP$265,37,FALSE) -> 3107.8594 | E13: =VLOOKUP(_xlfn.CONCAT($A13,"|",E$1),MasterSheet_WithPredictive!$A$1:$AP$265,37,FALSE) -> 3624.2812 | F13: =VLOOKUP(_xlfn.CONCAT($A13,"|",F$1),MasterSheet_WithPredictive!$A$1:$AP$265,37,FALSE) -> 4864.6938 | G13: =VLOOKUP(_xlfn.CONCAT($A13,"|",G$1),MasterSheet_WithPredictive!$A$1:$AP$265,37,FALSE) -> 5132.6612 | H13: =VLOOKUP(_xlfn.CONCAT($A13,"|",H$1),MasterSheet_WithPredictive!$A$1:$AP$265,37,FALSE) -> 4744.1785 | I13: =VLOOKUP(_xlfn.CONCAT($A13,"|",I$1),MasterSheet_WithPredictive!$A$1:$AP$265,37,FALSE) -> 5273.2703 | ... M13: =VLOOKUP(_xlfn.CONCAT($A13,"|",M$1),MasterSheet_WithPredictive!$A$1:$AP$265,37,FALSE) -> 7140.183
... A23: USA | B23: =VLOOKUP(_xlfn.CONCAT($A23,"|",B$1),MasterSheet_WithPredictive!$A$1:$AP$265,37,FALSE) -> 33048.424 | C23: =VLOOKUP(_xlfn.CONCAT($A23,"|",C$1),MasterSheet_WithPredictive!$A$1:$AP$265,37,FALSE) -> 33702.879 | D23: =VLOOKUP(_xlfn.CONCAT($A23,"|",D$1),MasterSheet_WithPredictive!$A$1:$AP$265,37,FALSE) -> 35793.975 | E23: =VLOOKUP(_xlfn.CONCAT($A23,"|",E$1),MasterSheet_WithPredictive!$A$1:$AP$265,37,FALSE) -> 36631.784 | F23: =VLOOKUP(_xlfn.CONCAT($A23,"|",F$1),MasterSheet_WithPredictive!$A$1:$AP$265,37,FALSE) -> 40700.24 | G23: =VLOOKUP(_xlfn.CONCAT($A23,"|",G$1),MasterSheet_WithPredictive!$A$1:$AP$265,37,FALSE) -> 43428.321 | H23: =VLOOKUP(_xlfn.CONCAT($A23,"|",H$1),MasterSheet_WithPredictive!$A$1:$AP$265,37,FALSE) -> 46536.323 | I23: =VLOOKUP(_xlfn.CONCAT($A23,"|",I$1),MasterSheet_WithPredictive!$A$1:$AP$265,37,FALSE) -> 47800.056 | ... M23: =VLOOKUP(_xlfn.CONCAT($A23,"|",M$1),MasterSheet_WithPredictive!$A$1:$AP$265,37,FALSE) -> 57381.403

Sheet G20+3 Countries
C2: HEART SCORE RANKING OF G-20+3 COUNTRIES IN TERMS OF "ECONOMIC RESILIENCE" & "AFFORDABILITY"
B3: 2025
B4: =B3 & " - HEART SCORE G-20+2 RANKING" -> 2025 - HEART SCORE G-20+2 RANKING | D4: Country | E4: HEART SCORE | F4: Brief Description of HEART Scores | G4: =_xlfn.CONCAT("Outlook - ",B3+1) -> Outlook - 2026
B5: RESILIENCE | C5: AFFORDABILITY
A6: 1 | B6: =Preprocessing1!A5 -> 20 | C6: =Preprocessing1!B5 -> 17 | D6: =Preprocessing1!C5 -> ARGENTINA | E6: =Preprocessing1!F5 -> 0.22D | F6: =Preprocessing1!G5 -> Weak Economic Resilience with Poor Affordability. | G6: =_xlfn.CONCAT("Heart Score: ",Preprocessing2!F5,", Resilience Rank: ",Preprocessing2!A5,", Affordability Rank: ",Preprocessing2!B5) -> Heart Score: 0.18D+, Resilience Rank: 21, Affordability Rank: 17
A7: 2 | B7: =Preprocessing1!A6 -> 17 | C7: =Preprocessing1!B6 -> 4 | D7: =Preprocessing1!C6 -> AUSTRALIA | E7: =Preprocessing1!F6 -> 0.34A- | F7: =Preprocessing1!G6 -> Satisfactory Economic Resilience with High Affordability. | G7: =_xlfn.CONCAT("Heart Score: ",Preprocessing2!F6,", Resilience Rank: ",Preprocessing2!A6,", Affordability Rank: ",Preprocessing2!B6) -> Heart Score: 0.37A, Resilience Rank: 17, Affordability Rank: 4
A8: 3 | B8: =Preprocessing1!A7 -> 18 | C8: =Preprocessing1!B7 -> 19 | D8: =Preprocessing1!C7 -> BRAZIL | E8: =Preprocessing1!F7 -> 0.33D | F8: =Preprocessing1!G7 -> Satisfactory Economic Resilience with Poor Affordability. | G8: =_xlfn.CONCAT("Heart Score: ",Preprocessing2!F7,", Resilience Rank: ",Preprocessing2!A7,", Affordability Rank: ",Preprocessing2!B7) -> Heart Score: 0.33D, Resilience Rank: 19, Affordability Rank: 19
A9: 4 | B9: =Preprocessing1!A8 -> 12 | C9: =Preprocessing1!B8 -> 6 | D9: =Preprocessing1!C8 -> CANADA | E9: =Preprocessing1!F8 -> 0.41B+ | F9: =Preprocessing1!G8 -> Good Economic Resilience with Very Good Affordability. | G9: =_xlfn.CONCAT("Heart Score: ",Preprocessing2!F8,", Resilience Rank: ",Preprocessing2!A8,", Affordability Rank: ",Preprocessing2!B8) -> Heart Score: 0.43A-, Resilience Rank: 12, Affordability Rank: 6
A10: 5 | B10: =Preprocessing1!A9 -> 2 | C10: =Preprocessing1!B9 -> 15 | D10: =Preprocessing1!C9 -> CHINA | E10: =Preprocessing1!F9 -> 0.73D+ | F10: =Preprocessing1!G9 -> Superb Economic Resilience with Challenging Affordability. | G10: =_xlfn.CONCAT("Heart Score: ",Preprocessing2!F9,", Resilience Rank: ",Preprocessing2!A9,", Affordability Rank: ",Preprocessing2!B9) -> Heart Score: 0.75D+, Resilience Rank: 2, Affordability Rank: 15
A11: 6 | B11: =Preprocessing1!A10 -> 10 | C11: =Preprocessing1!B10 -> 8 | D11: =Preprocessing1!C10 -> FRANCE | E11: =Preprocessing1!F10 -> 0.44B | F11: =Preprocessing1!G10 -> Good Economic Resilience with Good Affordability. | G11: =_xlfn.CONCAT("Heart Score: ",Preprocessing2!F10,", Resilience Rank: ",Preprocessing2!A10,", Affordability Rank: ",Preprocessing2!B10) -> Heart Score: 0.45B, Resilience Rank: 10, Affordability Rank: 8
